Workbook

Sheet Start Here
B2: Debt Freedom Planner
B3: Budget · Debt Payoff (Snowball or Avalanche) · Savings Goals
B5: HOW TO USE
B6: 1. Only edit the YELLOW cells. Everything else calculates automatically.
B7: 2. Monthly Budget: enter your take-home income and planned vs. actual spending.
B8: 3. Debt Payoff: list up to 8 debts, choose Snowball or Avalanche, and add any extra monthly payment.
B9: The sheet tells you your debt-free date, total interest, and when each debt is paid off.
B10: 4. Savings Goals: enter each goal, what you've saved, and your monthly contribution.
B11: 5. The example values are there to show the format. Overwrite them with your own numbers.
B13: SNOWBALL vs. AVALANCHE
B14: Snowball pays the smallest balance first. Quick wins keep you motivated.
B15: Avalanche pays the highest interest rate first. It costs the least in total interest.
... B26: Example cell to edit

Sheet Monthly Budget
B2: Monthly Budget
B4: Income | C4: Planned | D4: Actual | E4: Difference | G4: This month at a glance
B5: Paycheck 1 | C5: 2100 | D5: 2100 | E5: =D5-C5 -> 0 | G5: Income (actual) | H5: =D9 -> 4440
B6: Paycheck 2 | C6: 2100 | D6: 2100 | E6: =D6-C6 -> 0 | G6: Spending (actual) | H6: =D26 -> 4167
B7: Side income | C7: 300 | D7: 240 | E7: =D7-C7 -> -60 | G7: Left over | H7: =D9-D26 -> 273
B8: Other | C8: 0 | D8: 0 | E8: =D8-C8 -> 0 | G8: Savings rate | H8: =IFERROR('Savings Goals'!E15/D9,0) -> 0.078828829
B9: Total income | C9: =SUM(C5:C8) -> 4500 | D9: =SUM(D5:D8) -> 4440 | E9: =D9-C9 -> -60 | G9: Unassigned (planned) | H9: =C9-C26 -> 420
B11: Expense | C11: Planned | D11: Actual | E11: Left / (Over) | G11: Tip: aim for 'Unassigned (planned)' = $0. Give every dollar a job.
B12: Rent / Mortgage | C12: 1400 | D12: 1400 | E12: =C12-D12 -> 0
B13: Utilities | C13: 180 | D13: 195 | E13: =C13-D13 -> -15
B14: Groceries | C14: 450 | D14: 510 | E14: =C14-D14 -> -60
B15: Transportation | C15: 250 | D15: 230 | E15: =C15-D15 -> 20
B16: Insurance | C16: 160 | D16: 160 | E16: =C16-D16 -> 0
B17: Phone / Internet | C17: 110 | D17: 110 | E17: =C17-D17 -> 0
B18: Subscriptions | C18: 45 | D18: 62 | E18: =C18-D18 -> -17
B19: Dining out | C19: 150 | D19: 210 | E19: =C19-D19 -> -60
B20: Personal / Fun | C20: 120 | D20: 95 | E20: =C20-D20 -> 25
B21: Health | C21: 60 | D21: 40 | E21: =C21-D21 -> 20
B22: Debt payments | C22: ='Debt Payoff'!D17 -> 805 | D22: ='Debt Payoff'!D17 -> 805 | E22: =C22-D22 -> 0
B23: Savings | C23: ='Savings Goals'!E15 -> 350 | D23: ='Savings Goals'!E15 -> 350 | E23: =C23-D23 -> 0
B24: Other | C24: 0 | D24: 0 | E24: =C24-D24 -> 0
B25: Other | C25: 0 | D25: 0 | E25: =C25-D25 -> 0
B26: Total expenses | C26: =SUM(C12:C25) -> 4080 | D26: =SUM(D12:D25) -> 4167 | E26: =C26-D26 -> -87

Sheet Debt Payoff
B2: Debt Payoff Planner
B4: Payoff method | C4: Avalanche | D4: ← pick from list
B5: Extra payment / month | C5: 200 | D5: ← on top of all minimum payments
B6: Start month | C6: 46327
B8: Debt name | C8: Balance | D8: APR | E8: Min payment | F8: Pay order | H8: Paid off in (months) | I8: Paid off | J8: Interest paid
B9: Credit card A | C9: 4200 | D9: 0.2449 | E9: 120 | F9: =IF(N(C9)<=0,"",COUNTIF($L$9:$L$16,"<"&L9)+1) -> 1 | H9: =IF(N(C9)<=0,"",IF(INDEX(Calc!AY:AY,363)>0.005,"30+ yrs",COUNTIF(Calc!AY3:AY362,">0.005")+1)) -> 16 | I9: =IF(N(C9)<=0,"",IF(ISNUMBER(H9),EDATE($C$6,H9-1),"—")) -> 46784 | J9: =IF(N(C9)<=0,"",SUM(Calc!J3:J362)) -> 739.22412 | L9: =IF(N(C9)<=0,1000000000000,IF($C$4="Snowball",C9,-D9))+ROW()/1000000000 -> -0.24489999
B10: Credit card B | C10: 1350 | D10: 0.1999 | E10: 40 | F10: =IF(N(C10)<=0,"",COUNTIF($L$9:$L$16,"<"&L10)+1) -> 2 | H10: =IF(N(C10)<=0,"",IF(INDEX(Calc!AZ:AZ,363)>0.005,"30+ yrs",COUNTIF(Calc!AZ3:AZ362,">0.005")+1)) -> 19 | I10: =IF(N(C10)<=0,"",IF(ISNUMBER(H10),EDATE($C$6,H10-1),"—")) -> 46874 | J10: =IF(N(C10)<=0,"",SUM(Calc!K3:K362)) -> 347.09753 | L10: =IF(N(C10)<=0,1000000000000,IF($C$4="Snowball",C10,-D10))+ROW()/1000000000 -> -0.19989999
B11: Car loan | C11: 9800 | D11: 0.069 | E11: 285 | F11: =IF(N(C11)<=0,"",COUNTIF($L$9:$L$16,"<"&L11)+1) -> 3 | H11: =IF(N(C11)<=0,"",IF(INDEX(Calc!BA:BA,363)>0.005,"30+ yrs",COUNTIF(Calc!BA3:BA362,">0.005")+1)) -> 27 | I11: =IF(N(C11)<=0,"",IF(ISNUMBER(H11),EDATE($C$6,H11-1),"—")) -> 47119 | J11: =IF(N(C11)<=0,"",SUM(Calc!L3:L362)) -> 968.89087 | L11: =IF(N(C11)<=0,1000000000000,IF($C$4="Snowball",C11,-D11))+ROW()/1000000000 -> -0.068999989
B12: Student loan | C12: 14500 | D12: 0.055 | E12: 160 | F12: =IF(N(C12)<=0,"",COUNTIF($L$9:$L$16,"<"&L12)+1) -> 4 | H12: =IF(N(C12)<=0,"",IF(INDEX(Calc!BB:BB,363)>0.005,"30+ yrs",COUNTIF(Calc!BB3:BB362,">0.005")+1)) -> 43 | I12: =IF(N(C12)<=0,"",IF(ISNUMBER(H12),EDATE($C$6,H12-1),"—")) -> 47604 | J12: =IF(N(C12)<=0,"",SUM(Calc!M3:M362)) -> 2081.9657 | L12: =IF(N(C12)<=0,1000000000000,IF($C$4="Snowball",C12,-D12))+ROW()/1000000000 -> -0.054999988
C13: 0 | D13: 0 | E13: 0 | F13: =IF(N(C13)<=0,"",COUNTIF($L$9:$L$16,"<"&L13)+1) | H13: =IF(N(C13)<=0,"",IF(INDEX(Calc!BC:BC,363)>0.005,"30+ yrs",COUNTIF(Calc!BC3:BC362,">0.005")+1)) | I13: =IF(N(C13)<=0,"",IF(ISNUMBER(H13),EDATE($C$6,H13-1),"—")) | J13: =IF(N(C13)<=0,"",SUM(Calc!N3:N362)) | L13: =IF(N(C13)<=0,1000000000000,IF($C$4="Snowball",C13,-D13))+ROW()/1000000000 -> 1000000000000
C14: 0 | D14: 0 | E14: 0 | F14: =IF(N(C14)<=0,"",COUNTIF($L$9:$L$16,"<"&L14)+1) | H14: =IF(N(C14)<=0,"",IF(INDEX(Calc!BD:BD,363)>0.005,"30+ yrs",COUNTIF(Calc!BD3:BD362,">0.005")+1)) | I14: =IF(N(C14)<=0,"",IF(ISNUMBER(H14),EDATE($C$6,H14-1),"—")) | J14: =IF(N(C14)<=0,"",SUM(Calc!O3:O362)) | L14: =IF(N(C14)<=0,1000000000000,IF($C$4="Snowball",C14,-D14))+ROW()/1000000000 -> 1000000000000
C15: 0 | D15: 0 | E15: 0 | F15: =IF(N(C15)<=0,"",COUNTIF($L$9:$L$16,"<"&L15)+1) | H15: =IF(N(C15)<=0,"",IF(INDEX(Calc!BE:BE,363)>0.005,"30+ yrs",COUNTIF(Calc!BE3:BE362,">0.005")+1)) | I15: =IF(N(C15)<=0,"",IF(ISNUMBER(H15),EDATE($C$6,H15-1),"—")) | J15: =IF(N(C15)<=0,"",SUM(Calc!P3:P362)) | L15: =IF(N(C15)<=0,1000000000000,IF($C$4="Snowball",C15,-D15))+ROW()/1000000000 -> 1000000000000
C16: 0 | D16: 0 | E16: 0 | F16: =IF(N(C16)<=0,"",COUNTIF($L$9:$L$16,"<"&L16)+1) | H16: =IF(N(C16)<=0,"",IF(INDEX(Calc!BF:BF,363)>0.005,"30+ yrs",COUNTIF(Calc!BF3:BF362,">0.005")+1)) | I16: =IF(N(C16)<=0,"",IF(ISNUMBER(H16),EDATE($C$6,H16-1),"—")) | J16: =IF(N(C16)<=0,"",SUM(Calc!Q3:Q362)) | L16: =IF(N(C16)<=0,1000000000000,IF($C$4="Snowball",C16,-D16))+ROW()/1000000000 -> 1000000000000
B17: Totals | C17: =SUM(C9:C16) -> 29850 | D17: =SUM(E9:E16)+C5 -> 805 | E17: ← total paid / month | J17: =SUM(J9:J16) -> 4137.1782
B19: Your results
B20: Debt-free date | C20: =IF(Calc!BG362>0.005,"Over 30 years: raise your payment",EDATE(C6,COUNTIF(Calc!BG3:BG362,">0.005"))) -> 47604
B21: Months to debt-free | C21: =IF(Calc!BG362>0.005,"360+",COUNTIF(Calc!BG3:BG362,">0.005")+1) -> 43
B22: Total interest you'll pay | C22: =J17 -> 4137.1782
B23: Paid first | C23: =IFERROR(INDEX(B9:B16,MATCH(1,F9:F16,0)),"") -> Credit card A
B25: Rows highlighted green are the debt to attack first. Try switching the method and changing the extra payment to see how your date moves.
B26: If a minimum payment doesn't cover the monthly interest, that debt will never shrink. Check 'Paid off in' for '30+ yrs'.

Sheet Calc
A1: Month-by-month engine for the Debt Payoff tab. Don't edit. | AH1: =IF('Debt Payoff'!F9="",99,'Debt Payoff'!F9) -> 1 | AI1: =IF('Debt Payoff'!F10="",99,'Debt Payoff'!F10) -> 2 | AJ1: =IF('Debt Payoff'!F11="",99,'Debt Payoff'!F11) -> 3 | AK1: =IF('Debt Payoff'!F12="",99,'Debt Payoff'!F12) -> 4 | AL1: =IF('Debt Payoff'!F13="",99,'Debt Payoff'!F13) -> 99 | AM1: =IF('Debt Payoff'!F14="",99,'Debt Payoff'!F14) -> 99 | AN1: =IF('Debt Payoff'!F15="",99,'Debt Payoff'!F15) -> 99 | AO1: =IF('Debt Payoff'!F16="",99,'Debt Payoff'!F16) -> 99
A2: Month | B2: Start 1 | C2: Start 2 | D2: Start 3 | E2: Start 4 | F2: Start 5 | G2: Start 6 | H2: Start 7 | I2: Start 8 | J2: Interest 1 | K2: Interest 2 | L2: Interest 3 | M2: Interest 4 | N2: Interest 5 | O2: Interest 6 | P2: Interest 7 | Q2: Interest 8 | R2: Owed 1 | S2: Owed 2 | T2: Owed 3 | U2: Owed 4 | V2: Owed 5 | W2: Owed 6 | X2: Owed 7 | Y2: Owed 8 | Z2: MinPay 1 | AA2: MinPay 2 | AB2: MinPay 3 | AC2: MinPay 4 | AD2: MinPay 5 | AE2: MinPay 6 | AF2: MinPay 7 | AG2: MinPay 8 | AH2: Remain 1 | AI2: Remain 2 | AJ2: Remain 3 | AK2: Remain 4 | AL2: Remain 5 | AM2: Remain 6 | AN2: Remain 7 | AO2: Remain 8 | AP2: Pool | AQ2: Extra 1 | AR2: Extra 2 | AS2: Extra 3 | AT2: Extra 4 | AU2: Extra 5 | AV2: Extra 6 | AW2: Extra 7 | AX2: Extra 8 | AY2: End 1 | AZ2: End 2 | BA2: End 3 | BB2: End 4 | BC2: End 5 | BD2: End 6 | BE2: End 7 | BF2: End 8 | BG2: Total end bal
A3: 1 | B3: =N('Debt Payoff'!C9) -> 4200 | C3: =N('Debt Payoff'!C10) -> 1350 | D3: =N('Debt Payoff'!C11) -> 9800 | E3: =N('Debt Payoff'!C12) -> 14500 | F3: =N('Debt Payoff'!C13) -> 0 | G3: =N('Debt Payoff'!C14) -> 0 | H3: =N('Debt Payoff'!C15) -> 0 | I3: =N('Debt Payoff'!C16) -> 0 | J3: =B3*N('Debt Payoff'!D9)/12 -> 85.715 | K3: =C3*N('Debt Payoff'!D10)/12 -> 22.48875 | L3: =D3*N('Debt Payoff'!D11)/12 -> 56.35 | M3: =E3*N('Debt Payoff'!D12)/12 -> 66.458333 | N3: =F3*N('Debt Payoff'!D13)/12 -> 0 | O3: =G3*N('Debt Payoff'!D14)/12 -> 0 | P3: =H3*N('Debt Payoff'!D15)/12 -> 0 | Q3: =I3*N('Debt Payoff'!D16)/12 -> 0 | R3: =B3+J3 -> 4285.715 | S3: =C3+K3 -> 1372.4887 | T3: =D3+L3 -> 9856.35 | U3: =E3+M3 -> 14566.458 | V3: =F3+N3 -> 0 | W3: =G3+O3 -> 0 | X3: =H3+P3 -> 0 | Y3: =I3+Q3 -> 0 | Z3: =MIN(R3,N('Debt Payoff'!E9)) -> 120 | AA3: =MIN(S3,N('Debt Payoff'!E10)) -> 40 | AB3: =MIN(T3,N('Debt Payoff'!E11)) -> 285 | AC3: =MIN(U3,N('Debt Payoff'!E12)) -> 160 | AD3: =MIN(V3,N('Debt Payoff'!E13)) -> 0 | AE3: =MIN(W3,N('Debt Payoff'!E14)) -> 0 | AF3: =MIN(X3,N('Debt Payoff'!E15)) -> 0 | AG3: =MIN(Y3,N('Debt Payoff'!E16)) -> 0 | AH3: =R3-Z3 -> 4165.715 | AI3: =S3-AA3 -> 1332.4887 | AJ3: =T3-AB3 -> 9571.35 | AK3: =U3-AC3 -> 14406.458 | AL3: =V3-AD3 -> 0 | AM3: =W3-AE3 -> 0 | AN3: =X3-AF3 -> 0 | AO3: =Y3-AG3 -> 0 | AP3: =MAX(0,'Debt Payoff'!$D$17-SUM(Z3:AG3)) -> 200 | AQ3: =MIN(AH3,MAX(0,$AP3-SUMPRODUCT(($AH$1:$AO$1<AH$1)*$AH3:$AO3))) -> 200 | AR3: =MIN(AI3,MAX(0,$AP3-SUMPRODUCT(($AH$1:$AO$1<AI$1)*$AH3:$AO3))) -> 0 | AS3: =MIN(AJ3,MAX(0,$AP3-SUMPRODUCT(($AH$1:$AO$1<AJ$1)*$AH3:$AO3))) -> 0 | AT3: =MIN(AK3,MAX(0,$AP3-SUMPRODUCT(($AH$1:$AO$1<AK$1)*$AH3:$AO3))) -> 0 | AU3: =MIN(AL3,MAX(0,$AP3-SUMPRODUCT(($AH$1:$AO$1<AL$1)*$AH3:$AO3))) -> 0 | AV3: =MIN(AM3,MAX(0,$AP3-SUMPRODUCT(($AH$1:$AO$1<AM$1)*$AH3:$AO3))) -> 0 | AW3: =MIN(AN3,MAX(0,$AP3-SUMPRODUCT(($AH$1:$AO$1<AN$1)*$AH3:$AO3))) -> 0 | AX3: =MIN(AO3,MAX(0,$AP3-SUMPRODUCT(($AH$1:$AO$1<AO$1)*$AH3:$AO3))) -> 0 | AY3: =ROUND(AH3-AQ3,2) -> 3965.72 | AZ3: =ROUND(AI3-AR3,2) -> 1332.49 | BA3: =ROUND(AJ3-AS3,2) -> 9571.35 | BB3: =ROUND(AK3-AT3,2) -> 14406.46 | BC3: =ROUND(AL3-AU3,2) -> 0 | BD3: =ROUND(AM3-AV3,2) -> 0 | BE3: =ROUND(AN3-AW3,2) -> 0 | BF3: =ROUND(AO3-AX3,2) -> 0 | BG3: =SUM(AY3:BF3) -> 29276.02
A4: 2 | B4: =AY3 -> 3965.72 | C4: =AZ3 -> 1332.49 | D4: =BA3 -> 9571.35 | E4: =BB3 -> 14406.46 | F4: =BC3 -> 0 | G4: =BD3 -> 0 | H4: =BE3 -> 0 | I4: =BF3 -> 0 | J4: =B4*N('Debt Payoff'!D9)/12 -> 80.933736 | K4: =C4*N('Debt Payoff'!D10)/12 -> 22.197063 | L4: =D4*N('Debt Payoff'!D11)/12 -> 55.035263 | M4: =E4*N('Debt Payoff'!D12)/12 -> 66.029608 | N4: =F4*N('Debt Payoff'!D13)/12 -> 0 | O4: =G4*N('Debt Payoff'!D14)/12 -> 0 | P4: =H4*N('Debt Payoff'!D15)/12 -> 0 | Q4: =I4*N('Debt Payoff'!D16)/12 -> 0 | R4: =B4+J4 -> 4046.6537 | S4: =C4+K4 -> 1354.6871 | T4: =D4+L4 -> 9626.3853 | U4: =E4+M4 -> 14472.49 | V4: =F4+N4 -> 0 | W4: =G4+O4 -> 0 | X4: =H4+P4 -> 0 | Y4: =I4+Q4 -> 0 | Z4: =MIN(R4,N('Debt Payoff'!E9)) -> 120 | AA4: =MIN(S4,N('Debt Payoff'!E10)) -> 40 | AB4: =MIN(T4,N('Debt Payoff'!E11)) -> 285 | AC4: =MIN(U4,N('Debt Payoff'!E12)) -> 160 | AD4: =MIN(V4,N('Debt Payoff'!E13)) -> 0 | AE4: =MIN(W4,N('Debt Payoff'!E14)) -> 0 | AF4: =MIN(X4,N('Debt Payoff'!E15)) -> 0 | AG4: =MIN(Y4,N('Debt Payoff'!E16)) -> 0 | AH4: =R4-Z4 -> 3926.6537 | AI4: =S4-AA4 -> 1314.6871 | AJ4: =T4-AB4 -> 9341.3853 | AK4: =U4-AC4 -> 14312.49 | AL4: =V4-AD4 -> 0 | AM4: =W4-AE4 -> 0 | AN4: =X4-AF4 -> 0 | AO4: =Y4-AG4 -> 0 | AP4: =MAX(0,'Debt Payoff'!$D$17-SUM(Z4:AG4)) -> 200 | AQ4: =MIN(AH4,MAX(0,$AP4-SUMPRODUCT(($AH$1:$AO$1<AH$1)*$AH4:$AO4))) -> 200 | AR4: =MIN(AI4,MAX(0,$AP4-SUMPRODUCT(($AH$1:$AO$1<AI$1)*$AH4:$AO4))) -> 0 | AS4: =MIN(AJ4,MAX(0,$AP4-SUMPRODUCT(($AH$1:$AO$1<AJ$1)*$AH4:$AO4))) -> 0 | AT4: =MIN(AK4,MAX(0,$AP4-SUMPRODUCT(($AH$1:$AO$1<AK$1)*$AH4:$AO4))) -> 0 | AU4: =MIN(AL4,MAX(0,$AP4-SUMPRODUCT(($AH$1:$AO$1<AL$1)*$AH4:$AO4))) -> 0 | AV4: =MIN(AM4,MAX(0,$AP4-SUMPRODUCT(($AH$1:$AO$1<AM$1)*$AH4:$AO4))) -> 0 | AW4: =MIN(AN4,MAX(0,$AP4-SUMPRODUCT(($AH$1:$AO$1<AN$1)*$AH4:$AO4))) -> 0 | AX4: =MIN(AO4,MAX(0,$AP4-SUMPRODUCT(($AH$1:$AO$1<AO$1)*$AH4:$AO4))) -> 0 | AY4: =ROUND(AH4-AQ4,2) -> 3726.65 | AZ4: =ROUND(AI4-AR4,2) -> 1314.69 | BA4: =ROUND(AJ4-AS4,2) -> 9341.39 | BB4: =ROUND(AK4-AT4,2) -> 14312.49 | BC4: =ROUND(AL4-AU4,2) -> 0 | BD4: =ROUND(AM4-AV4,2) -> 0 | BE4: =ROUND(AN4-AW4,2) -> 0 | BF4: =ROUND(AO4-AX4,2) -> 0 | BG4: =SUM(AY4:BF4) -> 28695.22
A5: 3 | B5: =AY4 -> 3726.65 | C5: =AZ4 -> 1314.69 | D5: =BA4 -> 9341.39 | E5: =BB4 -> 14312.49 | F5: =BC4 -> 0 | G5: =BD4 -> 0 | H5: =BE4 -> 0 | I5: =BF4 -> 0 | J5: =B5*N('Debt Payoff'!D9)/12 -> 76.054715 | K5: =C5*N('Debt Payoff'!D10)/12 -> 21.900544 | L5: =D5*N('Debt Payoff'!D11)/12 -> 53.712992 | M5: =E5*N('Debt Payoff'!D12)/12 -> 65.598912 | N5: =F5*N('Debt Payoff'!D13)/12 -> 0 | O5: =G5*N('Debt Payoff'!D14)/12 -> 0 | P5: =H5*N('Debt Payoff'!D15)/12 -> 0 | Q5: =I5*N('Debt Payoff'!D16)/12 -> 0 | R5: =B5+J5 -> 3802.7047 | S5: =C5+K5 -> 1336.5905 | T5: =D5+L5 -> 9395.103 | U5: =E5+M5 -> 14378.089 | V5: =F5+N5 -> 0 | W5: =G5+O5 -> 0 | X5: =H5+P5 -> 0 | Y5: =I5+Q5 -> 0 | Z5: =MIN(R5,N('Debt Payoff'!E9)) -> 120 | AA5: =MIN(S5,N('Debt Payoff'!E10)) -> 40 | AB5: =MIN(T5,N('Debt Payoff'!E11)) -> 285 | AC5: =MIN(U5,N('Debt Payoff'!E12)) -> 160 | AD5: =MIN(V5,N('Debt Payoff'!E13)) -> 0 | AE5: =MIN(W5,N('Debt Payoff'!E14)) -> 0 | AF5: =MIN(X5,N('Debt Payoff'!E15)) -> 0 | AG5: =MIN(Y5,N('Debt Payoff'!E16)) -> 0 | AH5: =R5-Z5 -> 3682.7047 | AI5: =S5-AA5 -> 1296.5905 | AJ5: =T5-AB5 -> 9110.103 | AK5: =U5-AC5 -> 14218.089 | AL5: =V5-AD5 -> 0 | AM5: =W5-AE5 -> 0 | AN5: =X5-AF5 -> 0 | AO5: =Y5-AG5 -> 0 | AP5: =MAX(0,'Debt Payoff'!$D$17-SUM(Z5:AG5)) -> 200 | AQ5: =MIN(AH5,MAX(0,$AP5-SUMPRODUCT(($AH$1:$AO$1<AH$1)*$AH5:$AO5))) -> 200 | AR5: =MIN(AI5,MAX(0,$AP5-SUMPRODUCT(($AH$1:$AO$1<AI$1)*$AH5:$AO5))) -> 0 | AS5: =MIN(AJ5,MAX(0,$AP5-SUMPRODUCT(($AH$1:$AO$1<AJ$1)*$AH5:$AO5))) -> 0 | AT5: =MIN(AK5,MAX(0,$AP5-SUMPRODUCT(($AH$1:$AO$1<AK$1)*$AH5:$AO5))) -> 0 | AU5: =MIN(AL5,MAX(0,$AP5-SUMPRODUCT(($AH$1:$AO$1<AL$1)*$AH5:$AO5))) -> 0 | AV5: =MIN(AM5,MAX(0,$AP5-SUMPRODUCT(($AH$1:$AO$1<AM$1)*$AH5:$AO5))) -> 0 | AW5: =MIN(AN5,MAX(0,$AP5-SUMPRODUCT(($AH$1:$AO$1<AN$1)*$AH5:$AO5))) -> 0 | AX5: =MIN(AO5,MAX(0,$AP5-SUMPRODUCT(($AH$1:$AO$1<AO$1)*$AH5:$AO5))) -> 0 | AY5: =ROUND(AH5-AQ5,2) -> 3482.7 | AZ5: =ROUND(AI5-AR5,2) -> 1296.59 | BA5: =ROUND(AJ5-AS5,2) -> 9110.1 | BB5: =ROUND(AK5-AT5,2) -> 14218.09 | BC5: =ROUND(AL5-AU5,2) -> 0 | BD5: =ROUND(AM5-AV5,2) -> 0 | BE5: =ROUND(AN5-AW5,2) -> 0 | BF5: =ROUND(AO5-AX5,2) -> 0 | BG5: =SUM(AY5:BF5) -> 28107.48
A6: 4 | B6: =AY5 -> 3482.7 | C6: =AZ5 -> 1296.59 | D6: =BA5 -> 9110.1 | E6: =BB5 -> 14218.09 | F6: =BC5 -> 0 | G6: =BD5 -> 0 | H6: =BE5 -> 0 | I6: =BF5 -> 0 | J6: =B6*N('Debt Payoff'!D9)/12 -> 71.076103 | K6: =C6*N('Debt Payoff'!D10)/12 -> 21.599028 | L6: =D6*N('Debt Payoff'!D11)/12 -> 52.383075 | M6: =E6*N('Debt Payoff'!D12)/12 -> 65.166246 | N6: =F6*N('Debt Payoff'!D13)/12 -> 0 | O6: =G6*N('Debt Payoff'!D14)/12 -> 0 | P6: =H6*N('Debt Payoff'!D15)/12 -> 0 | Q6: =I6*N('Debt Payoff'!D16)/12 -> 0 | R6: =B6+J6 -> 3553.7761 | S6: =C6+K6 -> 1318.189 | T6: =D6+L6 -> 9162.4831 | U6: =E6+M6 -> 14283.256 | V6: =F6+N6 -> 0 | W6: =G6+O6 -> 0 | X6: =H6+P6 -> 0 | Y6: =I6+Q6 -> 0 | Z6: =MIN(R6,N('Debt Payoff'!E9)) -> 120 | AA6: =MIN(S6,N('Debt Payoff'!E10)) -> 40 | AB6: =MIN(T6,N('Debt Payoff'!E11)) -> 285 | AC6: =MIN(U6,N('Debt Payoff'!E12)) -> 160 | AD6: =MIN(V6,N('Debt Payoff'!E13)) -> 0 | AE6: =MIN(W6,N('Debt Payoff'!E14)) -> 0 | AF6: =MIN(X6,N('Debt Payoff'!E15)) -> 0 | AG6: =MIN(Y6,N('Debt Payoff'!E16)) -> 0 | AH6: =R6-Z6 -> 3433.7761 | AI6: =S6-AA6 -> 1278.189 | AJ6: =T6-AB6 -> 8877.4831 | AK6: =U6-AC6 -> 14123.256 | AL6: =V6-AD6 -> 0 | AM6: =W6-AE6 -> 0 | AN6: =X6-AF6 -> 0 | AO6: =Y6-AG6 -> 0 | AP6: =MAX(0,'Debt Payoff'!$D$17-SUM(Z6:AG6)) -> 200 | AQ6: =MIN(AH6,MAX(0,$AP6-SUMPRODUCT(($AH$1:$AO$1<AH$1)*$AH6:$AO6))) -> 200 | AR6: =MIN(AI6,MAX(0,$AP6-SUMPRODUCT(($AH$1:$AO$1<AI$1)*$AH6:$AO6))) -> 0 | AS6: =MIN(AJ6,MAX(0,$AP6-SUMPRODUCT(($AH$1:$AO$1<AJ$1)*$AH6:$AO6))) -> 0 | AT6: =MIN(AK6,MAX(0,$AP6-SUMPRODUCT(($AH$1:$AO$1<AK$1)*$AH6:$AO6))) -> 0 | AU6: =MIN(AL6,MAX(0,$AP6-SUMPRODUCT(($AH$1:$AO$1<AL$1)*$AH6:$AO6))) -> 0 | AV6: =MIN(AM6,MAX(0,$AP6-SUMPRODUCT(($AH$1:$AO$1<AM$1)*$AH6:$AO6))) -> 0 | AW6: =MIN(AN6,MAX(0,$AP6-SUMPRODUCT(($AH$1:$AO$1<AN$1)*$AH6:$AO6))) -> 0 | AX6: =MIN(AO6,MAX(0,$AP6-SUMPRODUCT(($AH$1:$AO$1<AO$1)*$AH6:$AO6))) -> 0 | AY6: =ROUND(AH6-AQ6,2) -> 3233.78 | AZ6: =ROUND(AI6-AR6,2) -> 1278.19 | BA6: =ROUND(AJ6-AS6,2) -> 8877.48 | BB6: =ROUND(AK6-AT6,2) -> 14123.26 | BC6: =ROUND(AL6-AU6,2) -> 0 | BD6: =ROUND(AM6-AV6,2) -> 0 | BE6: =ROUND(AN6-AW6,2) -> 0 | BF6: =ROUND(AO6-AX6,2) -> 0 | BG6: =SUM(AY6:BF6) -> 27512.71
A7: 5 | B7: =AY6 -> 3233.78 | C7: =AZ6 -> 1278.19 | D7: =BA6 -> 8877.48 | E7: =BB6 -> 14123.26 | F7: =BC6 -> 0 | G7: =BD6 -> 0 | H7: =BE6 -> 0 | I7: =BF6 -> 0 | J7: =B7*N('Debt Payoff'!D9)/12 -> 65.99606 | K7: =C7*N('Debt Payoff'!D10)/12 -> 21.292515 | L7: =D7*N('Debt Payoff'!D11)/12 -> 51.04551 | M7: =E7*N('Debt Payoff'!D12)/12 -> 64.731608 | N7: =F7*N('Debt Payoff'!D13)/12 -> 0 | O7: =G7*N('Debt Payoff'!D14)/12 -> 0 | P7: =H7*N('Debt Payoff'!D15)/12 -> 0 | Q7: =I7*N('Debt Payoff'!D16)/12 -> 0 | R7: =B7+J7 -> 3299.7761 | S7: =C7+K7 -> 1299.4825 | T7: =D7+L7 -> 8928.5255 | U7: =E7+M7 -> 14187.992 | V7: =F7+N7 -> 0 | W7: =G7+O7 -> 0 | X7: =H7+P7 -> 0 | Y7: =I7+Q7 -> 0 | Z7: =MIN(R7,N('Debt Payoff'!E9)) -> 120 | AA7: =MIN(S7,N('Debt Payoff'!E10)) -> 40 | AB7: =MIN(T7,N('Debt Payoff'!E11)) -> 285 | AC7: =MIN(U7,N('Debt Payoff'!E12)) -> 160 | AD7: =MIN(V7,N('Debt Payoff'!E13)) -> 0 | AE7: =MIN(W7,N('Debt Payoff'!E14)) -> 0 | AF7: =MIN(X7,N('Debt Payoff'!E15)) -> 0 | AG7: =MIN(Y7,N('Debt Payoff'!E16)) -> 0 | AH7: =R7-Z7 -> 3179.7761 | AI7: =S7-AA7 -> 1259.4825 | AJ7: =T7-AB7 -> 8643.5255 | AK7: =U7-AC7 -> 14027.992 | AL7: =V7-AD7 -> 0 | AM7: =W7-AE7 -> 0 | AN7: =X7-AF7 -> 0 | AO7: =Y7-AG7 -> 0 | AP7: =MAX(0,'Debt Payoff'!$D$17-SUM(Z7:AG7)) -> 200 | AQ7: =MIN(AH7,MAX(0,$AP7-SUMPRODUCT(($AH$1:$AO$1<AH$1)*$AH7:$AO7))) -> 200 | AR7: =MIN(AI7,MAX(0,$AP7-SUMPRODUCT(($AH$1:$AO$1<AI$1)*$AH7:$AO7))) -> 0 | AS7: =MIN(AJ7,MAX(0,$AP7-SUMPRODUCT(($AH$1:$AO$1<AJ$1)*$AH7:$AO7))) -> 0 | AT7: =MIN(AK7,MAX(0,$AP7-SUMPRODUCT(($AH$1:$AO$1<AK$1)*$AH7:$AO7))) -> 0 | AU7: =MIN(AL7,MAX(0,$AP7-SUMPRODUCT(($AH$1:$AO$1<AL$1)*$AH7:$AO7))) -> 0 | AV7: =MIN(AM7,MAX(0,$AP7-SUMPRODUCT(($AH$1:$AO$1<AM$1)*$AH7:$AO7))) -> 0 | AW7: =MIN(AN7,MAX(0,$AP7-SUMPRODUCT(($AH$1:$AO$1<AN$1)*$AH7:$AO7))) -> 0 | AX7: =MIN(AO7,MAX(0,$AP7-SUMPRODUCT(($AH$1:$AO$1<AO$1)*$AH7:$AO7))) -> 0 | AY7: =ROUND(AH7-AQ7,2) -> 2979.78 | AZ7: =ROUND(AI7-AR7,2) -> 1259.48 | BA7: =ROUND(AJ7-AS7,2) -> 8643.53 | BB7: =ROUND(AK7-AT7,2) -> 14027.99 | BC7: =ROUND(AL7-AU7,2) -> 0 | BD7: =ROUND(AM7-AV7,2) -> 0 | BE7: =ROUND(AN7-AW7,2) -> 0 | BF7: =ROUND(AO7-AX7,2) -> 0 | BG7: =SUM(AY7:BF7) -> 26910.78
A8: 6 | B8: =AY7 -> 2979.78 | C8: =AZ7 -> 1259.48 | D8: =BA7 -> 8643.53 | E8: =BB7 -> 14027.99 | F8: =BC7 -> 0 | G8: =BD7 -> 0 | H8: =BE7 -> 0 | I8: =BF7 -> 0 | J8: =B8*N('Debt Payoff'!D9)/12 -> 60.812343 | K8: =C8*N('Debt Payoff'!D10)/12 -> 20.980838 | L8: =D8*N('Debt Payoff'!D11)/12 -> 49.700297 | M8: =E8*N('Debt Payoff'!D12)/12 -> 64.294954 | N8: =F8*N('Debt Payoff'!D13)/12 -> 0 | O8: =G8*N('Debt Payoff'!D14)/12 -> 0 | P8: =H8*N('Debt Payoff'!D15)/12 -> 0 | Q8: =I8*N('Debt Payoff'!D16)/12 -> 0 | R8: =B8+J8 -> 3040.5923 | S8: =C8+K8 -> 1280.4608 | T8: =D8+L8 -> 8693.2303 | U8: =E8+M8 -> 14092.285 | V8: =F8+N8 -> 0 | W8: =G8+O8 -> 0 | X8: =H8+P8 -> 0 | Y8: =I8+Q8 -> 0 | Z8: =MIN(R8,N('Debt Payoff'!E9)) -> 120 | AA8: =MIN(S8,N('Debt Payoff'!E10)) -> 40 | AB8: =MIN(T8,N('Debt Payoff'!E11)) -> 285 | AC8: =MIN(U8,N('Debt Payoff'!E12)) -> 160 | AD8: =MIN(V8,N('Debt Payoff'!E13)) -> 0 | AE8: =MIN(W8,N('Debt Payoff'!E14)) -> 0 | AF8: =MIN(X8,N('Debt Payoff'!E15)) -> 0 | AG8: =MIN(Y8,N('Debt Payoff'!E16)) -> 0 | AH8: =R8-Z8 -> 2920.5923 | AI8: =S8-AA8 -> 1240.4608 | AJ8: =T8-AB8 -> 8408.2303 | AK8: =U8-AC8 -> 13932.285 | AL8: =V8-AD8 -> 0 | AM8: =W8-AE8 -> 0 | AN8: =X8-AF8 -> 0 | AO8: =Y8-AG8 -> 0 | AP8: =MAX(0,'Debt Payoff'!$D$17-SUM(Z8:AG8)) -> 200 | AQ8: =MIN(AH8,MAX(0,$AP8-SUMPRODUCT(($AH$1:$AO$1<AH$1)*$AH8:$AO8))) -> 200 | AR8: =MIN(AI8,MAX(0,$AP8-SUMPRODUCT(($AH$1:$AO$1<AI$1)*$AH8:$AO8))) -> 0 | AS8: =MIN(AJ8,MAX(0,$AP8-SUMPRODUCT(($AH$1:$AO$1<AJ$1)*$AH8:$AO8))) -> 0 | AT8: =MIN(AK8,MAX(0,$AP8-SUMPRODUCT(($AH$1:$AO$1<AK$1)*$AH8:$AO8))) -> 0 | AU8: =MIN(AL8,MAX(0,$AP8-SUMPRODUCT(($AH$1:$AO$1<AL$1)*$AH8:$AO8))) -> 0 | AV8: =MIN(AM8,MAX(0,$AP8-SUMPRODUCT(($AH$1:$AO$1<AM$1)*$AH8:$AO8))) -> 0 | AW8: =MIN(AN8,MAX(0,$AP8-SUMPRODUCT(($AH$1:$AO$1<AN$1)*$AH8:$AO8))) -> 0 | AX8: =MIN(AO8,MAX(0,$AP8-SUMPRODUCT(($AH$1:$AO$1<AO$1)*$AH8:$AO8))) -> 0 | AY8: =ROUND(AH8-AQ8,2) -> 2720.59 | AZ8: =ROUND(AI8-AR8,2) -> 1240.46 | BA8: =ROUND(AJ8-AS8,2) -> 8408.23 | BB8: =ROUND(AK8-AT8,2) -> 13932.28 | BC8: =ROUND(AL8-AU8,2) -> 0 | BD8: =ROUND(AM8-AV8,2) -> 0 | BE8: =ROUND(AN8-AW8,2) -> 0 | BF8: =ROUND(AO8-AX8,2) -> 0 | BG8: =SUM(AY8:BF8) -> 26301.56
A9: 7 | B9: =AY8 -> 2720.59 | C9: =AZ8 -> 1240.46 | D9: =BA8 -> 8408.23 | E9: =BB8 -> 13932.28 | F9: =BC8 -> 0 | G9: =BD8 -> 0 | H9: =BE8 -> 0 | I9: =BF8 -> 0 | J9: =B9*N('Debt Payoff'!D9)/12 -> 55.522708 | K9: =C9*N('Debt Payoff'!D10)/12 -> 20.663996 | L9: =D9*N('Debt Payoff'!D11)/12 -> 48.347322 | M9: =E9*N('Debt Payoff'!D12)/12 -> 63.856283 | N9: =F9*N('Debt Payoff'!D13)/12 -> 0 | O9: =G9*N('Debt Payoff'!D14)/12 -> 0 | P9: =H9*N('Debt Payoff'!D15)/12 -> 0 | Q9: =I9*N('Debt Payoff'!D16)/12 -> 0 | R9: =B9+J9 -> 2776.1127 | S9: =C9+K9 -> 1261.124 | T9: =D9+L9 -> 8456.5773 | U9: =E9+M9 -> 13996.136 | V9: =F9+N9 -> 0 | W9: =G9+O9 -> 0 | X9: =H9+P9 -> 0 | Y9: =I9+Q9 -> 0 | Z9: =MIN(R9,N('Debt Payoff'!E9)) -> 120 | AA9: =MIN(S9,N('Debt Payoff'!E10)) -> 40 | AB9: =MIN(T9,N('Debt Payoff'!E11)) -> 285 | AC9: =MIN(U9,N('Debt Payoff'!E12)) -> 160 | AD9: =MIN(V9,N('Debt Payoff'!E13)) -> 0 | AE9: =MIN(W9,N('Debt Payoff'!E14)) -> 0 | AF9: =MIN(X9,N('Debt Payoff'!E15)) -> 0 | AG9: =MIN(Y9,N('Debt Payoff'!E16)) -> 0 | AH9: =R9-Z9 -> 2656.1127 | AI9: =S9-AA9 -> 1221.124 | AJ9: =T9-AB9 -> 8171.5773 | AK9: =U9-AC9 -> 13836.136 | AL9: =V9-AD9 -> 0 | AM9: =W9-AE9 -> 0 | AN9: =X9-AF9 -> 0 | AO9: =Y9-AG9 -> 0 | AP9: =MAX(0,'Debt Payoff'!$D$17-SUM(Z9:AG9)) -> 200 | AQ9: =MIN(AH9,MAX(0,$AP9-SUMPRODUCT(($AH$1:$AO$1<AH$1)*$AH9:$AO9))) -> 200 | AR9: =MIN(AI9,MAX(0,$AP9-SUMPRODUCT(($AH$1:$AO$1<AI$1)*$AH9:$AO9))) -> 0 | AS9: =MIN(AJ9,MAX(0,$AP9-SUMPRODUCT(($AH$1:$AO$1<AJ$1)*$AH9:$AO9))) -> 0 | AT9: =MIN(AK9,MAX(0,$AP9-SUMPRODUCT(($AH$1:$AO$1<AK$1)*$AH9:$AO9))) -> 0 | AU9: =MIN(AL9,MAX(0,$AP9-SUMPRODUCT(($AH$1:$AO$1<AL$1)*$AH9:$AO9))) -> 0 | AV9: =MIN(AM9,MAX(0,$AP9-SUMPRODUCT(($AH$1:$AO$1<AM$1)*$AH9:$AO9))) -> 0 | AW9: =MIN(AN9,MAX(0,$AP9-SUMPRODUCT(($AH$1:$AO$1<AN$1)*$AH9:$AO9))) -> 0 | AX9: =MIN(AO9,MAX(0,$AP9-SUMPRODUCT(($AH$1:$AO$1<AO$1)*$AH9:$AO9))) -> 0 | AY9: =ROUND(AH9-AQ9,2) -> 2456.11 | AZ9: =ROUND(AI9-AR9,2) -> 1221.12 | BA9: =ROUND(AJ9-AS9,2) -> 8171.58 | BB9: =ROUND(AK9-AT9,2) -> 13836.14 | BC9: =ROUND(AL9-AU9,2) -> 0 | BD9: =ROUND(AM9-AV9,2) -> 0 | BE9: =ROUND(AN9-AW9,2) -> 0 | BF9: =ROUND(AO9-AX9,2) -> 0 | BG9: =SUM(AY9:BF9) -> 25684.95
A10: 8 | B10: =AY9 -> 2456.11 | C10: =AZ9 -> 1221.12 | D10: =BA9 -> 8171.58 | E10: =BB9 -> 13836.14 | F10: =BC9 -> 0 | G10: =BD9 -> 0 | H10: =BE9 -> 0 | I10: =BF9 -> 0 | J10: =B10*N('Debt Payoff'!D9)/12 -> 50.125112 | K10: =C10*N('Debt Payoff'!D10)/12 -> 20.341824 | L10: =D10*N('Debt Payoff'!D11)/12 -> 46.986585 | M10: =E10*N('Debt Payoff'!D12)/12 -> 63.415642 | N10: =F10*N('Debt Payoff'!D13)/12 -> 0 | O10: =G10*N('Debt Payoff'!D14)/12 -> 0 | P10: =H10*N('Debt Payoff'!D15)/12 -> 0 | Q10: =I10*N('Debt Payoff'!D16)/12 -> 0 | R10: =B10+J10 -> 2506.2351 | S10: =C10+K10 -> 1241.4618 | T10: =D10+L10 -> 8218.5666 | U10: =E10+M10 -> 13899.556 | V10: =F10+N10 -> 0 | W10: =G10+O10 -> 0 | X10: =H10+P10 -> 0 | Y10: =I10+Q10 -> 0 | Z10: =MIN(R10,N('Debt Payoff'!E9)) -> 120 | AA10: =MIN(S10,N('Debt Payoff'!E10)) -> 40 | AB10: =MIN(T10,N('Debt Payoff'!E11)) -> 285 | AC10: =MIN(U10,N('Debt Payoff'!E12)) -> 160 | AD10: =MIN(V10,N('Debt Payoff'!E13)) -> 0 | AE10: =MIN(W10,N('Debt Payoff'!E14)) -> 0 | AF10: =MIN(X10,N('Debt Payoff'!E15)) -> 0 | AG10: =MIN(Y10,N('Debt Payoff'!E16)) -> 0 | AH10: =R10-Z10 -> 2386.2351 | AI10: =S10-AA10 -> 1201.4618 | AJ10: =T10-AB10 -> 7933.5666 | AK10: =U10-AC10 -> 13739.556 | AL10: =V10-AD10 -> 0 | AM10: =W10-AE10 -> 0 | AN10: =X10-AF10 -> 0 | AO10: =Y10-AG10 -> 0 | AP10: =MAX(0,'Debt Payoff'!$D$17-SUM(Z10:AG10)) -> 200 | AQ10: =MIN(AH10,MAX(0,$AP10-SUMPRODUCT(($AH$1:$AO$1<AH$1)*$AH10:$AO10))) -> 200 | AR10: =MIN(AI10,MAX(0,$AP10-SUMPRODUCT(($AH$1:$AO$1<AI$1)*$AH10:$AO10))) -> 0 | AS10: =MIN(AJ10,MAX(0,$AP10-SUMPRODUCT(($AH$1:$AO$1<AJ$1)*$AH10:$AO10))) -> 0 | AT10: =MIN(AK10,MAX(0,$AP10-SUMPRODUCT(($AH$1:$AO$1<AK$1)*$AH10:$AO10))) -> 0 | AU10: =MIN(AL10,MAX(0,$AP10-SUMPRODUCT(($AH$1:$AO$1<AL$1)*$AH10:$AO10))) -> 0 | AV10: =MIN(AM10,MAX(0,$AP10-SUMPRODUCT(($AH$1:$AO$1<AM$1)*$AH10:$AO10))) -> 0 | AW10: =MIN(AN10,MAX(0,$AP10-SUMPRODUCT(($AH$1:$AO$1<AN$1)*$AH10:$AO10))) -> 0 | AX10: =MIN(AO10,MAX(0,$AP10-SUMPRODUCT(($AH$1:$AO$1<AO$1)*$AH10:$AO10))) -> 0 | AY10: =ROUND(AH10-AQ10,2) -> 2186.24 | AZ10: =ROUND(AI10-AR10,2) -> 1201.46 | BA10: =ROUND(AJ10-AS10,2) -> 7933.57 | BB10: =ROUND(AK10-AT10,2) -> 13739.56 | BC10: =ROUND(AL10-AU10,2) -> 0 | BD10: =ROUND(AM10-AV10,2) -> 0 | BE10: =ROUND(AN10-AW10,2) -> 0 | BF10: =ROUND(AO10-AX10,2) -> 0 | BG10: =SUM(AY10:BF10) -> 25060.83
A11: 9 | B11: =AY10 -> 2186.24 | C11: =AZ10 -> 1201.46 | D11: =BA10 -> 7933.57 | E11: =BB10 -> 13739.56 | F11: =BC10 -> 0 | G11: =BD10 -> 0 | H11: =BE10 -> 0 | I11: =BF10 -> 0 | J11: =B11*N('Debt Payoff'!D9)/12 -> 44.617515 | K11: =C11*N('Debt Payoff'!D10)/12 -> 20.014321 | L11: =D11*N('Debt Payoff'!D11)/12 -> 45.618027 | M11: =E11*N('Debt Payoff'!D12)/12 -> 62.972983 | N11: =F11*N('Debt Payoff'!D13)/12 -> 0 | O11: =G11*N('Debt Payoff'!D14)/12 -> 0 | P11: =H11*N('Debt Payoff'!D15)/12 -> 0 | Q11: =I11*N('Debt Payoff'!D16)/12 -> 0 | R11: =B11+J11 -> 2230.8575 | S11: =C11+K11 -> 1221.4743 | T11: =D11+L11 -> 7979.188 | U11: =E11+M11 -> 13802.533 | V11: =F11+N11 -> 0 | W11: =G11+O11 -> 0 | X11: =H11+P11 -> 0 | Y11: =I11+Q11 -> 0 | Z11: =MIN(R11,N('Debt Payoff'!E9)) -> 120 | AA11: =MIN(S11,N('Debt Payoff'!E10)) -> 40 | AB11: =MIN(T11,N('Debt Payoff'!E11)) -> 285 | AC11: =MIN(U11,N('Debt Payoff'!E12)) -> 160 | AD11: =MIN(V11,N('Debt Payoff'!E13)) -> 0 | AE11: =MIN(W11,N('Debt Payoff'!E14)) -> 0 | AF11: =MIN(X11,N('Debt Payoff'!E15)) -> 0 | AG11: =MIN(Y11,N('Debt Payoff'!E16)) -> 0 | AH11: =R11-Z11 -> 2110.8575 | AI11: =S11-AA11 -> 1181.4743 | AJ11: =T11-AB11 -> 7694.188 | AK11: =U11-AC11 -> 13642.533 | AL11: =V11-AD11 -> 0 | AM11: =W11-AE11 -> 0 | AN11: =X11-AF11 -> 0 | AO11: =Y11-AG11 -> 0 | AP11: =MAX(0,'Debt Payoff'!$D$17-SUM(Z11:AG11)) -> 200 | AQ11: =MIN(AH11,MAX(0,$AP11-SUMPRODUCT(($AH$1:$AO$1<AH$1)*$AH11:$AO11))) -> 200 | AR11: =MIN(AI11,MAX(0,$AP11-SUMPRODUCT(($AH$1:$AO$1<AI$1)*$AH11:$AO11))) -> 0 | AS11: =MIN(AJ11,MAX(0,$AP11-SUMPRODUCT(($AH$1:$AO$1<AJ$1)*$AH11:$AO11))) -> 0 | AT11: =MIN(AK11,MAX(0,$AP11-SUMPRODUCT(($AH$1:$AO$1<AK$1)*$AH11:$AO11))) -> 0 | AU11: =MIN(AL11,MAX(0,$AP11-SUMPRODUCT(($AH$1:$AO$1<AL$1)*$AH11:$AO11))) -> 0 | AV11: =MIN(AM11,MAX(0,$AP11-SUMPRODUCT(($AH$1:$AO$1<AM$1)*$AH11:$AO11))) -> 0 | AW11: =MIN(AN11,MAX(0,$AP11-SUMPRODUCT(($AH$1:$AO$1<AN$1)*$AH11:$AO11))) -> 0 | AX11: =MIN(AO11,MAX(0,$AP11-SUMPRODUCT(($AH$1:$AO$1<AO$1)*$AH11:$AO11))) -> 0 | AY11: =ROUND(AH11-AQ11,2) -> 1910.86 | AZ11: =ROUND(AI11-AR11,2) -> 1181.47 | BA11: =ROUND(AJ11-AS11,2) -> 7694.19 | BB11: =ROUND(AK11-AT11,2) -> 13642.53 | BC11: =ROUND(AL11-AU11,2) -> 0 | BD11: =ROUND(AM11-AV11,2) -> 0 | BE11: =ROUND(AN11-AW11,2) -> 0 | BF11: =ROUND(AO11-AX11,2) -> 0 | BG11: =SUM(AY11:BF11) -> 24429.05
A12: 10 | B12: =AY11 -> 1910.86 | C12: =AZ11 -> 1181.47 | D12: =BA11 -> 7694.19 | E12: =BB11 -> 13642.53 | F12: =BC11 -> 0 | G12: =BD11 -> 0 | H12: =BE11 -> 0 | I12: =BF11 -> 0 | J12: =B12*N('Debt Payoff'!D9)/12 -> 38.997468 | K12: =C12*N('Debt Payoff'!D10)/12 -> 19.681321 | L12: =D12*N('Debt Payoff'!D11)/12 -> 44.241593 | M12: =E12*N('Debt Payoff'!D12)/12 -> 62.528262 | N12: =F12*N('Debt Payoff'!D13)/12 -> 0 | O12: =G12*N('Debt Payoff'!D14)/12 -> 0 | P12: =H12*N('Debt Payoff'!D15)/12 -> 0 | Q12: =I12*N('Debt Payoff'!D16)/12 -> 0 | R12: =B12+J12 -> 1949.8575 | S12: =C12+K12 -> 1201.1513 | T12: =D12+L12 -> 7738.4316 | U12: =E12+M12 -> 13705.058 | V12: =F12+N12 -> 0 | W12: =G12+O12 -> 0 | X12: =H12+P12 -> 0 | Y12: =I12+Q12 -> 0 | Z12: =MIN(R12,N('Debt Payoff'!E9)) -> 120 | AA12: =MIN(S12,N('Debt Payoff'!E10)) -> 40 | AB12: =MIN(T12,N('Debt Payoff'!E11)) -> 285 | AC12: =MIN(U12,N('Debt Payoff'!E12)) -> 160 | AD12: =MIN(V12,N('Debt Payoff'!E13)) -> 0 | AE12: =MIN(W12,N('Debt Payoff'!E14)) -> 0 | AF12: =MIN(X12,N('Debt Payoff'!E15)) -> 0 | AG12: =MIN(Y12,N('Debt Payoff'!E16)) -> 0 | AH12: =R12-Z12 -> 1829.8575 | AI12: =S12-AA12 -> 1161.1513 | AJ12: =T12-AB12 -> 7453.4316 | AK12: =U12-AC12 -> 13545.058 | AL12: =V12-AD12 -> 0 | AM12: =W12-AE12 -> 0 | AN12: =X12-AF12 -> 0 | AO12: =Y12-AG12 -> 0 | AP12: =MAX(0,'Debt Payoff'!$D$17-SUM(Z12:AG12)) -> 200 | AQ12: =MIN(AH12,MAX(0,$AP12-SUMPRODUCT(($AH$1:$AO$1<AH$1)*$AH12:$AO12))) -> 200 | AR12: =MIN(AI12,MAX(0,$AP12-SUMPRODUCT(($AH$1:$AO$1<AI$1)*$AH12:$AO12))) -> 0 | AS12: =MIN(AJ12,MAX(0,$AP12-SUMPRODUCT(($AH$1:$AO$1<AJ$1)*$AH12:$AO12))) -> 0 | AT12: =MIN(AK12,MAX(0,$AP12-SUMPRODUCT(($AH$1:$AO$1<AK$1)*$AH12:$AO12))) -> 0 | AU12: =MIN(AL12,MAX(0,$AP12-SUMPRODUCT(($AH$1:$AO$1<AL$1)*$AH12:$AO12))) -> 0 | AV12: =MIN(AM12,MAX(0,$AP12-SUMPRODUCT(($AH$1:$AO$1<AM$1)*$AH12:$AO12))) -> 0 | AW12: =MIN(AN12,MAX(0,$AP12-SUMPRODUCT(($AH$1:$AO$1<AN$1)*$AH12:$AO12))) -> 0 | AX12: =MIN(AO12,MAX(0,$AP12-SUMPRODUCT(($AH$1:$AO$1<AO$1)*$AH12:$AO12))) -> 0 | AY12: =ROUND(AH12-AQ12,2) -> 1629.86 | AZ12: =ROUND(AI12-AR12,2) -> 1161.15 | BA12: =ROUND(AJ12-AS12,2) -> 7453.43 | BB12: =ROUND(AK12-AT12,2) -> 13545.06 | BC12: =ROUND(AL12-AU12,2) -> 0 | BD12: =ROUND(AM12-AV12,2) -> 0 | BE12: =ROUND(AN12-AW12,2) -> 0 | BF12: =ROUND(AO12-AX12,2) -> 0 | BG12: =SUM(AY12:BF12) -> 23789.5
A13: 11 | B13: =AY12 -> 1629.86 | C13: =AZ12 -> 1161.15 | D13: =BA12 -> 7453.43 | E13: =BB12 -> 13545.06 | F13: =BC12 -> 0 | G13: =BD12 -> 0 | H13: =BE12 -> 0 | I13: =BF12 -> 0 | J13: =B13*N('Debt Payoff'!D9)/12 -> 33.262726 | K13: =C13*N('Debt Payoff'!D10)/12 -> 19.342824 | L13: =D13*N('Debt Payoff'!D11)/12 -> 42.857222 | M13: =E13*N('Debt Payoff'!D12)/12 -> 62.081525 | N13: =F13*N('Debt Payoff'!D13)/12 -> 0 | O13: =G13*N('Debt Payoff'!D14)/12 -> 0 | P13: =H13*N('Debt Payoff'!D15)/12 -> 0 | Q13: =I13*N('Debt Payoff'!D16)/12 -> 0 | R13: =B13+J13 -> 1663.1227 | S13: =C13+K13 -> 1180.4928 | T13: =D13+L13 -> 7496.2872 | U13: =E13+M13 -> 13607.142 | V13: =F13+N13 -> 0 | W13: =G13+O13 -> 0 | X13: =H13+P13 -> 0 | Y13: =I13+Q13 -> 0 | Z13: =MIN(R13,N('Debt Payoff'!E9)) -> 120 | AA13: =MIN(S13,N('Debt Payoff'!E10)) -> 40 | AB13: =MIN(T13,N('Debt Payoff'!E11)) -> 285 | AC13: =MIN(U13,N('Debt Payoff'!E12)) -> 160 | AD13: =MIN(V13,N('Debt Payoff'!E13)) -> 0 | AE13: =MIN(W13,N('Debt Payoff'!E14)) -> 0 | AF13: =MIN(X13,N('Debt Payoff'!E15)) -> 0 | AG13: =MIN(Y13,N('Debt Payoff'!E16)) -> 0 | AH13: =R13-Z13 -> 1543.1227 | AI13: =S13-AA13 -> 1140.4928 | AJ13: =T13-AB13 -> 7211.2872 | AK13: =U13-AC13 -> 13447.142 | AL13: =V13-AD13 -> 0 | AM13: =W13-AE13 -> 0 | AN13: =X13-AF13 -> 0 | AO13: =Y13-AG13 -> 0 | AP13: =MAX(0,'Debt Payoff'!$D$17-SUM(Z13:AG13)) -> 200 | AQ13: =MIN(AH13,MAX(0,$AP13-SUMPRODUCT(($AH$1:$AO$1<AH$1)*$AH13:$AO13))) -> 200 | AR13: =MIN(AI13,MAX(0,$AP13-SUMPRODUCT(($AH$1:$AO$1<AI$1)*$AH13:$AO13))) -> 0 | AS13: =MIN(AJ13,MAX(0,$AP13-SUMPRODUCT(($AH$1:$AO$1<AJ$1)*$AH13:$AO13))) -> 0 | AT13: =MIN(AK13,MAX(0,$AP13-SUMPRODUCT(($AH$1:$AO$1<AK$1)*$AH13:$AO13))) -> 0 | AU13: =MIN(AL13,MAX(0,$AP13-SUMPRODUCT(($AH$1:$AO$1<AL$1)*$AH13:$AO13))) -> 0 | AV13: =MIN(AM13,MAX(0,$AP13-SUMPRODUCT(($AH$1:$AO$1<AM$1)*$AH13:$AO13))) -> 0 | AW13: =MIN(AN13,MAX(0,$AP13-SUMPRODUCT(($AH$1:$AO$1<AN$1)*$AH13:$AO13))) -> 0 | AX13: =MIN(AO13,MAX(0,$AP13-SUMPRODUCT(($AH$1:$AO$1<AO$1)*$AH13:$AO13))) -> 0 | AY13: =ROUND(AH13-AQ13,2) -> 1343.12 | AZ13: =ROUND(AI13-AR13,2) -> 1140.49 | BA13: =ROUND(AJ13-AS13,2) -> 7211.29 | BB13: =ROUND(AK13-AT13,2) -> 13447.14 | BC13: =ROUND(AL13-AU13,2) -> 0 | BD13: =ROUND(AM13-AV13,2) -> 0 | BE13: =ROUND(AN13-AW13,2) -> 0 | BF13: =ROUND(AO13-AX13,2) -> 0 | BG13: =SUM(AY13:BF13) -> 23142.04
A14: 12 | B14: =AY13 -> 1343.12 | C14: =AZ13 -> 1140.49 | D14: =BA13 -> 7211.29 | E14: =BB13 -> 13447.14 | F14: =BC13 -> 0 | G14: =BD13 -> 0 | H14: =BE13 -> 0 | I14: =BF13 -> 0 | J14: =B14*N('Debt Payoff'!D9)/12 -> 27.410841 | K14: =C14*N('Debt Payoff'!D10)/12 -> 18.998663 | L14: =D14*N('Debt Payoff'!D11)/12 -> 41.464917 | M14: =E14*N('Debt Payoff'!D12)/12 -> 61.632725 | N14: =F14*N('Debt Payoff'!D13)/12 -> 0 | O14: =G14*N('Debt Payoff'!D14)/12 -> 0 | P14: =H14*N('Debt Payoff'!D15)/12 -> 0 | Q14: =I14*N('Debt Payoff'!D16)/12 -> 0 | R14: =B14+J14 -> 1370.5308 | S14: =C14+K14 -> 1159.4887 | T14: =D14+L14 -> 7252.7549 | U14: =E14+M14 -> 13508.773 | V14: =F14+N14 -> 0 | W14: =G14+O14 -> 0 | X14: =H14+P14 -> 0 | Y14: =I14+Q14 -> 0 | Z14: =MIN(R14,N('Debt Payoff'!E9)) -> 120 | AA14: =MIN(S14,N('Debt Payoff'!E10)) -> 40 | AB14: =MIN(T14,N('Debt Payoff'!E11)) -> 285 | AC14: =MIN(U14,N('Debt Payoff'!E12)) -> 160 | AD14: =MIN(V14,N('Debt Payoff'!E13)) -> 0 | AE14: =MIN(W14,N('Debt Payoff'!E14)) -> 0 | AF14: =MIN(X14,N('Debt Payoff'!E15)) -> 0 | AG14: =MIN(Y14,N('Debt Payoff'!E16)) -> 0 | AH14: =R14-Z14 -> 1250.5308 | AI14: =S14-AA14 -> 1119.4887 | AJ14: =T14-AB14 -> 6967.7549 | AK14: =U14-AC14 -> 13348.773 | AL14: =V14-AD14 -> 0 | AM14: =W14-AE14 -> 0 | AN14: =X14-AF14 -> 0 | AO14: =Y14-AG14 -> 0 | AP14: =MAX(0,'Debt Payoff'!$D$17-SUM(Z14:AG14)) -> 200 | AQ14: =MIN(AH14,MAX(0,$AP14-SUMPRODUCT(($AH$1:$AO$1<AH$1)*$AH14:$AO14))) -> 200 | AR14: =MIN(AI14,MAX(0,$AP14-SUMPRODUCT(($AH$1:$AO$1<AI$1)*$AH14:$AO14))) -> 0 | AS14: =MIN(AJ14,MAX(0,$AP14-SUMPRODUCT(($AH$1:$AO$1<AJ$1)*$AH14:$AO14))) -> 0 | AT14: =MIN(AK14,MAX(0,$AP14-SUMPRODUCT(($AH$1:$AO$1<AK$1)*$AH14:$AO14))) -> 0 | AU14: =MIN(AL14,MAX(0,$AP14-SUMPRODUCT(($AH$1:$AO$1<AL$1)*$AH14:$AO14))) -> 0 | AV14: =MIN(AM14,MAX(0,$AP14-SUMPRODUCT(($AH$1:$AO$1<AM$1)*$AH14:$AO14))) -> 0 | AW14: =MIN(AN14,MAX(0,$AP14-SUMPRODUCT(($AH$1:$AO$1<AN$1)*$AH14:$AO14))) -> 0 | AX14: =MIN(AO14,MAX(0,$AP14-SUMPRODUCT(($AH$1:$AO$1<AO$1)*$AH14:$AO14))) -> 0 | AY14: =ROUND(AH14-AQ14,2) -> 1050.53 | AZ14: =ROUND(AI14-AR14,2) -> 1119.49 | BA14: =ROUND(AJ14-AS14,2) -> 6967.75 | BB14: =ROUND(AK14-AT14,2) -> 13348.77 | BC14: =ROUND(AL14-AU14,2) -> 0 | BD14: =ROUND(AM14-AV14,2) -> 0 | BE14: =ROUND(AN14-AW14,2) -> 0 | BF14: =ROUND(AO14-AX14,2) -> 0 | BG14: =SUM(AY14:BF14) -> 22486.54
A15: 13 | B15: =AY14 -> 1050.53 | C15: =AZ14 -> 1119.49 | D15: =BA14 -> 6967.75 | E15: =BB14 -> 13348.77 | F15: =BC14 -> 0 | G15: =BD14 -> 0 | H15: =BE14 -> 0 | I15: =BF14 -> 0 | J15: =B15*N('Debt Payoff'!D9)/12 -> 21.439566 | K15: =C15*N('Debt Payoff'!D10)/12 -> 18.648838 | L15: =D15*N('Debt Payoff'!D11)/12 -> 40.064563 | M15: =E15*N('Debt Payoff'!D12)/12 -> 61.181863 | N15: =F15*N('Debt Payoff'!D13)/12 -> 0 | O15: =G15*N('Debt Payoff'!D14)/12 -> 0 | P15: =H15*N('Debt Payoff'!D15)/12 -> 0 | Q15: =I15*N('Debt Payoff'!D16)/12 -> 0 | R15: =B15+J15 -> 1071.9696 | S15: =C15+K15 -> 1138.1388 | T15: =D15+L15 -> 7007.8146 | U15: =E15+M15 -> 13409.952 | V15: =F15+N15 -> 0 | W15: =G15+O15 -> 0 | X15: =H15+P15 -> 0 | Y15: =I15+Q15 -> 0 | Z15: =MIN(R15,N('Debt Payoff'!E9)) -> 120 | AA15: =MIN(S15,N('Debt Payoff'!E10)) -> 40 | AB15: =MIN(T15,N('Debt Payoff'!E11)) -> 285 | AC15: =MIN(U15,N('Debt Payoff'!E12)) -> 160 | AD15: =MIN(V15,N('Debt Payoff'!E13)) -> 0 | AE15: =MIN(W15,N('Debt Payoff'!E14)) -> 0 | AF15: =MIN(X15,N('Debt Payoff'!E15)) -> 0 | AG15: =MIN(Y15,N('Debt Payoff'!E16)) -> 0 | AH15: =R15-Z15 -> 951.96957 | AI15: =S15-AA15 -> 1098.1388 | AJ15: =T15-AB15 -> 6722.8146 | AK15: =U15-AC15 -> 13249.952 | AL15: =V15-AD15 -> 0 | AM15: =W15-AE15 -> 0 | AN15: =X15-AF15 -> 0 | AO15: =Y15-AG15 -> 0 | AP15: =MAX(0,'Debt Payoff'!$D$17-SUM(Z15:AG15)) -> 200 | AQ15: =MIN(AH15,MAX(0,$AP15-SUMPRODUCT(($AH$1:$AO$1<AH$1)*$AH15:$AO15))) -> 200 | AR15: =MIN(AI15,MAX(0,$AP15-SUMPRODUCT(($AH$1:$AO$1<AI$1)*$AH15:$AO15))) -> 0 | AS15: =MIN(AJ15,MAX(0,$AP15-SUMPRODUCT(($AH$1:$AO$1<AJ$1)*$AH15:$AO15))) -> 0 | AT15: =MIN(AK15,MAX(0,$AP15-SUMPRODUCT(($AH$1:$AO$1<AK$1)*$AH15:$AO15))) -> 0 | AU15: =MIN(AL15,MAX(0,$AP15-SUMPRODUCT(($AH$1:$AO$1<AL$1)*$AH15:$AO15))) -> 0 | AV15: =MIN(AM15,MAX(0,$AP15-SUMPRODUCT(($AH$1:$AO$1<AM$1)*$AH15:$AO15))) -> 0 | AW15: =MIN(AN15,MAX(0,$AP15-SUMPRODUCT(($AH$1:$AO$1<AN$1)*$AH15:$AO15))) -> 0 | AX15: =MIN(AO15,MAX(0,$AP15-SUMPRODUCT(($AH$1:$AO$1<AO$1)*$AH15:$AO15))) -> 0 | AY15: =ROUND(AH15-AQ15,2) -> 751.97 | AZ15: =ROUND(AI15-AR15,2) -> 1098.14 | BA15: =ROUND(AJ15-AS15,2) -> 6722.81 | BB15: =ROUND(AK15-AT15,2) -> 13249.95 | BC15: =ROUND(AL15-AU15,2) -> 0 | BD15: =ROUND(AM15-AV15,2) -> 0 | BE15: =ROUND(AN15-AW15,2) -> 0 | BF15: =ROUND(AO15-AX15,2) -> 0 | BG15: =SUM(AY15:BF15) -> 21822.87
A16: 14 | B16: =AY15 -> 751.97 | C16: =AZ15 -> 1098.14 | D16: =BA15 -> 6722.81 | E16: =BB15 -> 13249.95 | F16: =BC15 -> 0 | G16: =BD15 -> 0 | H16: =BE15 -> 0 | I16: =BF15 -> 0 | J16: =B16*N('Debt Payoff'!D9)/12 -> 15.346454 | K16: =C16*N('Debt Payoff'!D10)/12 -> 18.293182 | L16: =D16*N('Debt Payoff'!D11)/12 -> 38.656157 | M16: =E16*N('Debt Payoff'!D12)/12 -> 60.728938 | N16: =F16*N('Debt Payoff'!D13)/12 -> 0 | O16: =G16*N('Debt Payoff'!D14)/12 -> 0 | P16: =H16*N('Debt Payoff'!D15)/12 -> 0 | Q16: =I16*N('Debt Payoff'!D16)/12 -> 0 | R16: =B16+J16 -> 767.31645 | S16: =C16+K16 -> 1116.4332 | T16: =D16+L16 -> 6761.4662 | U16: =E16+M16 -> 13310.679 | V16: =F16+N16 -> 0 | W16: =G16+O16 -> 0 | X16: =H16+P16 -> 0 | Y16: =I16+Q16 -> 0 | Z16: =MIN(R16,N('Debt Payoff'!E9)) -> 120 | AA16: =MIN(S16,N('Debt Payoff'!E10)) -> 40 | AB16: =MIN(T16,N('Debt Payoff'!E11)) -> 285 | AC16: =MIN(U16,N('Debt Payoff'!E12)) -> 160 | AD16: =MIN(V16,N('Debt Payoff'!E13)) -> 0 | AE16: =MIN(W16,N('Debt Payoff'!E14)) -> 0 | AF16: =MIN(X16,N('Debt Payoff'!E15)) -> 0 | AG16: =MIN(Y16,N('Debt Payoff'!E16)) -> 0 | AH16: =R16-Z16 -> 647.31645 | AI16: =S16-AA16 -> 1076.4332 | AJ16: =T16-AB16 -> 6476.4662 | AK16: =U16-AC16 -> 13150.679 | AL16: =V16-AD16 -> 0 | AM16: =W16-AE16 -> 0 | AN16: =X16-AF16 -> 0 | AO16: =Y16-AG16 -> 0 | AP16: =MAX(0,'Debt Payoff'!$D$17-SUM(Z16:AG16)) -> 200 | AQ16: =MIN(AH16,MAX(0,$AP16-SUMPRODUCT(($AH$1:$AO$1<AH$1)*$AH16:$AO16))) -> 200 | AR16: =MIN(AI16,MAX(0,$AP16-SUMPRODUCT(($AH$1:$AO$1<AI$1)*$AH16:$AO16))) -> 0 | AS16: =MIN(AJ16,MAX(0,$AP16-SUMPRODUCT(($AH$1:$AO$1<AJ$1)*$AH16:$AO16))) -> 0 | AT16: =MIN(AK16,MAX(0,$AP16-SUMPRODUCT(($AH$1:$AO$1<AK$1)*$AH16:$AO16))) -> 0 | AU16: =MIN(AL16,MAX(0,$AP16-SUMPRODUCT(($AH$1:$AO$1<AL$1)*$AH16:$AO16))) -> 0 | AV16: =MIN(AM16,MAX(0,$AP16-SUMPRODUCT(($AH$1:$AO$1<AM$1)*$AH16:$AO16))) -> 0 | AW16: =MIN(AN16,MAX(0,$AP16-SUMPRODUCT(($AH$1:$AO$1<AN$1)*$AH16:$AO16))) -> 0 | AX16: =MIN(AO16,MAX(0,$AP16-SUMPRODUCT(($AH$1:$AO$1<AO$1)*$AH16:$AO16))) -> 0 | AY16: =ROUND(AH16-AQ16,2) -> 447.32 | AZ16: =ROUND(AI16-AR16,2) -> 1076.43 | BA16: =ROUND(AJ16-AS16,2) -> 6476.47 | BB16: =ROUND(AK16-AT16,2) -> 13150.68 | BC16: =ROUND(AL16-AU16,2) -> 0 | BD16: =ROUND(AM16-AV16,2) -> 0 | BE16: =ROUND(AN16-AW16,2) -> 0 | BF16: =ROUND(AO16-AX16,2) -> 0 | BG16: =SUM(AY16:BF16) -> 21150.9
A17: 15 | B17: =AY16 -> 447.32 | C17: =AZ16 -> 1076.43 | D17: =BA16 -> 6476.47 | E17: =BB16 -> 13150.68 | F17: =BC16 -> 0 | G17: =BD16 -> 0 | H17: =BE16 -> 0 | I17: =BF16 -> 0 | J17: =B17*N('Debt Payoff'!D9)/12 -> 9.1290557 | K17: =C17*N('Debt Payoff'!D10)/12 -> 17.93153 | L17: =D17*N('Debt Payoff'!D11)/12 -> 37.239702 | M17: =E17*N('Debt Payoff'!D12)/12 -> 60.27395 | N17: =F17*N('Debt Payoff'!D13)/12 -> 0 | O17: =G17*N('Debt Payoff'!D14)/12 -> 0 | P17: =H17*N('Debt Payoff'!D15)/12 -> 0 | Q17: =I17*N('Debt Payoff'!D16)/12 -> 0 | R17: =B17+J17 -> 456.44906 | S17: =C17+K17 -> 1094.3615 | T17: =D17+L17 -> 6513.7097 | U17: =E17+M17 -> 13210.954 | V17: =F17+N17 -> 0 | W17: =G17+O17 -> 0 | X17: =H17+P17 -> 0 | Y17: =I17+Q17 -> 0 | Z17: =MIN(R17,N('Debt Payoff'!E9)) -> 120 | AA17: =MIN(S17,N('Debt Payoff'!E10)) -> 40 | AB17: =MIN(T17,N('Debt Payoff'!E11)) -> 285 | AC17: =MIN(U17,N('Debt Payoff'!E12)) -> 160 | AD17: =MIN(V17,N('Debt Payoff'!E13)) -> 0 | AE17: =MIN(W17,N('Debt Payoff'!E14)) -> 0 | AF17: =MIN(X17,N('Debt Payoff'!E15)) -> 0 | AG17: =MIN(Y17,N('Debt Payoff'!E16)) -> 0 | AH17: =R17-Z17 -> 336.44906 | AI17: =S17-AA17 -> 1054.3615 | AJ17: =T17-AB17 -> 6228.7097 | AK17: =U17-AC17 -> 13050.954 | AL17: =V17-AD17 -> 0 | AM17: =W17-AE17 -> 0 | AN17: =X17-AF17 -> 0 | AO17: =Y17-AG17 -> 0 | AP17: =MAX(0,'Debt Payoff'!$D$17-SUM(Z17:AG17)) -> 200 | AQ17: =MIN(AH17,MAX(0,$AP17-SUMPRODUCT(($AH$1:$AO$1<AH$1)*$AH17:$AO17))) -> 200 | AR17: =MIN(AI17,MAX(0,$AP17-SUMPRODUCT(($AH$1:$AO$1<AI$1)*$AH17:$AO17))) -> 0 | AS17: =MIN(AJ17,MAX(0,$AP17-SUMPRODUCT(($AH$1:$AO$1<AJ$1)*$AH17:$AO17))) -> 0 | AT17: =MIN(AK17,MAX(0,$AP17-SUMPRODUCT(($AH$1:$AO$1<AK$1)*$AH17:$AO17))) -> 0 | AU17: =MIN(AL17,MAX(0,$AP17-SUMPRODUCT(($AH$1:$AO$1<AL$1)*$AH17:$AO17))) -> 0 | AV17: =MIN(AM17,MAX(0,$AP17-SUMPRODUCT(($AH$1:$AO$1<AM$1)*$AH17:$AO17))) -> 0 | AW17: =MIN(AN17,MAX(0,$AP17-SUMPRODUCT(($AH$1:$AO$1<AN$1)*$AH17:$AO17))) -> 0 | AX17: =MIN(AO17,MAX(0,$AP17-SUMPRODUCT(($AH$1:$AO$1<AO$1)*$AH17:$AO17))) -> 0 | AY17: =ROUND(AH17-AQ17,2) -> 136.45 | AZ17: =ROUND(AI17-AR17,2) -> 1054.36 | BA17: =ROUND(AJ17-AS17,2) -> 6228.71 | BB17: =ROUND(AK17-AT17,2) -> 13050.95 | BC17: =ROUND(AL17-AU17,2) -> 0 | BD17: =ROUND(AM17-AV17,2) -> 0 | BE17: =ROUND(AN17-AW17,2) -> 0 | BF17: =ROUND(AO17-AX17,2) -> 0 | BG17: =SUM(AY17:BF17) -> 20470.47
A18: 16 | B18: =AY17 -> 136.45 | C18: =AZ17 -> 1054.36 | D18: =BA17 -> 6228.71 | E18: =BB17 -> 13050.95 | F18: =BC17 -> 0 | G18: =BD17 -> 0 | H18: =BE17 -> 0 | I18: =BF17 -> 0 | J18: =B18*N('Debt Payoff'!D9)/12 -> 2.7847171 | K18: =C18*N('Debt Payoff'!D10)/12 -> 17.56388 | L18: =D18*N('Debt Payoff'!D11)/12 -> 35.815083 | M18: =E18*N('Debt Payoff'!D12)/12 -> 59.816854 | N18: =F18*N('Debt Payoff'!D13)/12 -> 0 | O18: =G18*N('Debt Payoff'!D14)/12 -> 0 | P18: =H18*N('Debt Payoff'!D15)/12 -> 0 | Q18: =I18*N('Debt Payoff'!D16)/12 -> 0 | R18: =B18+J18 -> 139.23472 | S18: =C18+K18 -> 1071.9239 | T18: =D18+L18 -> 6264.5251 | U18: =E18+M18 -> 13110.767 | V18: =F18+N18 -> 0 | W18: =G18+O18 -> 0 | X18: =H18+P18 -> 0 | Y18: =I18+Q18 -> 0 | Z18: =MIN(R18,N('Debt Payoff'!E9)) -> 120 | AA18: =MIN(S18,N('Debt Payoff'!E10)) -> 40 | AB18: =MIN(T18,N('Debt Payoff'!E11)) -> 285 | AC18: =MIN(U18,N('Debt Payoff'!E12)) -> 160 | AD18: =MIN(V18,N('Debt Payoff'!E13)) -> 0 | AE18: =MIN(W18,N('Debt Payoff'!E14)) -> 0 | AF18: =MIN(X18,N('Debt Payoff'!E15)) -> 0 | AG18: =MIN(Y18,N('Debt Payoff'!E16)) -> 0 | AH18: =R18-Z18 -> 19.234717 | AI18: =S18-AA18 -> 1031.9239 | AJ18: =T18-AB18 -> 5979.5251 | AK18: =U18-AC18 -> 12950.767 | AL18: =V18-AD18 -> 0 | AM18: =W18-AE18 -> 0 | AN18: =X18-AF18 -> 0 | AO18: =Y18-AG18 -> 0 | AP18: =MAX(0,'Debt Payoff'!$D$17-SUM(Z18:AG18)) -> 200 | AQ18: =MIN(AH18,MAX(0,$AP18-SUMPRODUCT(($AH$1:$AO$1<AH$1)*$AH18:$AO18))) -> 19.234717 | AR18: =MIN(AI18,MAX(0,$AP18-SUMPRODUCT(($AH$1:$AO$1<AI$1)*$AH18:$AO18))) -> 180.76528 | AS18: =MIN(AJ18,MAX(0,$AP18-SUMPRODUCT(($AH$1:$AO$1<AJ$1)*$AH18:$AO18))) -> 0 | AT18: =MIN(AK18,MAX(0,$AP18-SUMPRODUCT(($AH$1:$AO$1<AK$1)*$AH18:$AO18))) -> 0 | AU18: =MIN(AL18,MAX(0,$AP18-SUMPRODUCT(($AH$1:$AO$1<AL$1)*$AH18:$AO18))) -> 0 | AV18: =MIN(AM18,MAX(0,$AP18-SUMPRODUCT(($AH$1:$AO$1<AM$1)*$AH18:$AO18))) -> 0 | AW18: =MIN(AN18,MAX(0,$AP18-SUMPRODUCT(($AH$1:$AO$1<AN$1)*$AH18:$AO18))) -> 0 | AX18: =MIN(AO18,MAX(0,$AP18-SUMPRODUCT(($AH$1:$AO$1<AO$1)*$AH18:$AO18))) -> 0 | AY18: =ROUND(AH18-AQ18,2) -> 0 | AZ18: =ROUND(AI18-AR18,2) -> 851.16 | BA18: =ROUND(AJ18-AS18,2) -> 5979.53 | BB18: =ROUND(AK18-AT18,2) -> 12950.77 | BC18: =ROUND(AL18-AU18,2) -> 0 | BD18: =ROUND(AM18-AV18,2) -> 0 | BE18: =ROUND(AN18-AW18,2) -> 0 | BF18: =ROUND(AO18-AX18,2) -> 0 | BG18: =SUM(AY18:BF18) -> 19781.46
A19: 17 | B19: =AY18 -> 0 | C19: =AZ18 -> 851.16 | D19: =BA18 -> 5979.53 | E19: =BB18 -> 12950.77 | F19: =BC18 -> 0 | G19: =BD18 -> 0 | H19: =BE18 -> 0 | I19: =BF18 -> 0 | J19: =B19*N('Debt Payoff'!D9)/12 -> 0 | K19: =C19*N('Debt Payoff'!D10)/12 -> 14.178907 | L19: =D19*N('Debt Payoff'!D11)/12 -> 34.382297 | M19: =E19*N('Debt Payoff'!D12)/12 -> 59.357696 | N19: =F19*N('Debt Payoff'!D13)/12 -> 0 | O19: =G19*N('Debt Payoff'!D14)/12 -> 0 | P19: =H19*N('Debt Payoff'!D15)/12 -> 0 | Q19: =I19*N('Debt Payoff'!D16)/12 -> 0 | R19: =B19+J19 -> 0 | S19: =C19+K19 -> 865.33891 | T19: =D19+L19 -> 6013.9123 | U19: =E19+M19 -> 13010.128 | V19: =F19+N19 -> 0 | W19: =G19+O19 -> 0 | X19: =H19+P19 -> 0 | Y19: =I19+Q19 -> 0 | Z19: =MIN(R19,N('Debt Payoff'!E9)) -> 0 | AA19: =MIN(S19,N('Debt Payoff'!E10)) -> 40 | AB19: =MIN(T19,N('Debt Payoff'!E11)) -> 285 | AC19: =MIN(U19,N('Debt Payoff'!E12)) -> 160 | AD19: =MIN(V19,N('Debt Payoff'!E13)) -> 0 | AE19: =MIN(W19,N('Debt Payoff'!E14)) -> 0 | AF19: =MIN(X19,N('Debt Payoff'!E15)) -> 0 | AG19: =MIN(Y19,N('Debt Payoff'!E16)) -> 0 | AH19: =R19-Z19 -> 0 | AI19: =S19-AA19 -> 825.33891 | AJ19: =T19-AB19 -> 5728.9123 | AK19: =U19-AC19 -> 12850.128 | AL19: =V19-AD19 -> 0 | AM19: =W19-AE19 -> 0 | AN19: =X19-AF19 -> 0 | AO19: =Y19-AG19 -> 0 | AP19: =MAX(0,'Debt Payoff'!$D$17-SUM(Z19:AG19)) -> 320 | AQ19: =MIN(AH19,MAX(0,$AP19-SUMPRODUCT(($AH$1:$AO$1<AH$1)*$AH19:$AO19))) -> 0 | AR19: =MIN(AI19,MAX(0,$AP19-SUMPRODUCT(($AH$1:$AO$1<AI$1)*$AH19:$AO19))) -> 320 | AS19: =MIN(AJ19,MAX(0,$AP19-SUMPRODUCT(($AH$1:$AO$1<AJ$1)*$AH19:$AO19))) -> 0 | AT19: =MIN(AK19,MAX(0,$AP19-SUMPRODUCT(($AH$1:$AO$1<AK$1)*$AH19:$AO19))) -> 0 | AU19: =MIN(AL19,MAX(0,$AP19-SUMPRODUCT(($AH$1:$AO$1<AL$1)*$AH19:$AO19))) -> 0 | AV19: =MIN(AM19,MAX(0,$AP19-SUMPRODUCT(($AH$1:$AO$1<AM$1)*$AH19:$AO19))) -> 0 | AW19: =MIN(AN19,MAX(0,$AP19-SUMPRODUCT(($AH$1:$AO$1<AN$1)*$AH19:$AO19))) -> 0 | AX19: =MIN(AO19,MAX(0,$AP19-SUMPRODUCT(($AH$1:$AO$1<AO$1)*$AH19:$AO19))) -> 0 | AY19: =ROUND(AH19-AQ19,2) -> 0 | AZ19: =ROUND(AI19-AR19,2) -> 505.34 | BA19: =ROUND(AJ19-AS19,2) -> 5728.91 | BB19: =ROUND(AK19-AT19,2) -> 12850.13 | BC19: =ROUND(AL19-AU19,2) -> 0 | BD19: =ROUND(AM19-AV19,2) -> 0 | BE19: =ROUND(AN19-AW19,2) -> 0 | BF19: =ROUND(AO19-AX19,2) -> 0 | BG19: =SUM(AY19:BF19) -> 19084.38
A20: 18 | B20: =AY19 -> 0 | C20: =AZ19 -> 505.34 | D20: =BA19 -> 5728.91 | E20: =BB19 -> 12850.13 | F20: =BC19 -> 0 | G20: =BD19 -> 0 | H20: =BE19 -> 0 | I20: =BF19 -> 0 | J20: =B20*N('Debt Payoff'!D9)/12 -> 0 | K20: =C20*N('Debt Payoff'!D10)/12 -> 8.4181222 | L20: =D20*N('Debt Payoff'!D11)/12 -> 32.941232 | M20: =E20*N('Debt Payoff'!D12)/12 -> 58.896429 | N20: =F20*N('Debt Payoff'!D13)/12 -> 0 | O20: =G20*N('Debt Payoff'!D14)/12 -> 0 | P20: =H20*N('Debt Payoff'!D15)/12 -> 0 | Q20: =I20*N('Debt Payoff'!D16)/12 -> 0 | R20: =B20+J20 -> 0 | S20: =C20+K20 -> 513.75812 | T20: =D20+L20 -> 5761.8512 | U20: =E20+M20 -> 12909.026 | V20: =F20+N20 -> 0 | W20: =G20+O20 -> 0 | X20: =H20+P20 -> 0 | Y20: =I20+Q20 -> 0 | Z20: =MIN(R20,N('Debt Payoff'!E9)) -> 0 | AA20: =MIN(S20,N('Debt Payoff'!E10)) -> 40 | AB20: =MIN(T20,N('Debt Payoff'!E11)) -> 285 | AC20: =MIN(U20,N('Debt Payoff'!E12)) -> 160 | AD20: =MIN(V20,N('Debt Payoff'!E13)) -> 0 | AE20: =MIN(W20,N('Debt Payoff'!E14)) -> 0 | AF20: =MIN(X20,N('Debt Payoff'!E15)) -> 0 | AG20: =MIN(Y20,N('Debt Payoff'!E16)) -> 0 | AH20: =R20-Z20 -> 0 | AI20: =S20-AA20 -> 473.75812 | AJ20: =T20-AB20 -> 5476.8512 | AK20: =U20-AC20 -> 12749.026 | AL20: =V20-AD20 -> 0 | AM20: =W20-AE20 -> 0 | AN20: =X20-AF20 -> 0 | AO20: =Y20-AG20 -> 0 | AP20: =MAX(0,'Debt Payoff'!$D$17-SUM(Z20:AG20)) -> 320 | AQ20: =MIN(AH20,MAX(0,$AP20-SUMPRODUCT(($AH$1:$AO$1<AH$1)*$AH20:$AO20))) -> 0 | AR20: =MIN(AI20,MAX(0,$AP20-SUMPRODUCT(($AH$1:$AO$1<AI$1)*$AH20:$AO20))) -> 320 | AS20: =MIN(AJ20,MAX(0,$AP20-SUMPRODUCT(($AH$1:$AO$1<AJ$1)*$AH20:$AO20))) -> 0 | AT20: =MIN(AK20,MAX(0,$AP20-SUMPRODUCT(($AH$1:$AO$1<AK$1)*$AH20:$AO20))) -> 0 | AU20: =MIN(AL20,MAX(0,$AP20-SUMPRODUCT(($AH$1:$AO$1<AL$1)*$AH20:$AO20))) -> 0 | AV20: =MIN(AM20,MAX(0,$AP20-SUMPRODUCT(($AH$1:$AO$1<AM$1)*$AH20:$AO20))) -> 0 | AW20: =MIN(AN20,MAX(0,$AP20-SUMPRODUCT(($AH$1:$AO$1<AN$1)*$AH20:$AO20))) -> 0 | AX20: =MIN(AO20,MAX(0,$AP20-SUMPRODUCT(($AH$1:$AO$1<AO$1)*$AH20:$AO20))) -> 0 | AY20: =ROUND(AH20-AQ20,2) -> 0 | AZ20: =ROUND(AI20-AR20,2) -> 153.76 | BA20: =ROUND(AJ20-AS20,2) -> 5476.85 | BB20: =ROUND(AK20-AT20,2) -> 12749.03 | BC20: =ROUND(AL20-AU20,2) -> 0 | BD20: =ROUND(AM20-AV20,2) -> 0 | BE20: =ROUND(AN20-AW20,2) -> 0 | BF20: =ROUND(AO20-AX20,2) -> 0 | BG20: =SUM(AY20:BF20) -> 18379.64
A21: 19 | B21: =AY20 -> 0 | C21: =AZ20 -> 153.76 | D21: =BA20 -> 5476.85 | E21: =BB20 -> 12749.03 | F21: =BC20 -> 0 | G21: =BD20 -> 0 | H21: =BE20 -> 0 | I21: =BF20 -> 0 | J21: =B21*N('Debt Payoff'!D9)/12 -> 0 | K21: =C21*N('Debt Payoff'!D10)/12 -> 2.5613853 | L21: =D21*N('Debt Payoff'!D11)/12 -> 31.491888 | M21: =E21*N('Debt Payoff'!D12)/12 -> 58.433054 | N21: =F21*N('Debt Payoff'!D13)/12 -> 0 | O21: =G21*N('Debt Payoff'!D14)/12 -> 0 | P21: =H21*N('Debt Payoff'!D15)/12 -> 0 | Q21: =I21*N('Debt Payoff'!D16)/12 -> 0 | R21: =B21+J21 -> 0 | S21: =C21+K21 -> 156.32139 | T21: =D21+L21 -> 5508.3419 | U21: =E21+M21 -> 12807.463 | V21: =F21+N21 -> 0 | W21: =G21+O21 -> 0 | X21: =H21+P21 -> 0 | Y21: =I21+Q21 -> 0 | Z21: =MIN(R21,N('Debt Payoff'!E9)) -> 0 | AA21: =MIN(S21,N('Debt Payoff'!E10)) -> 40 | AB21: =MIN(T21,N('Debt Payoff'!E11)) -> 285 | AC21: =MIN(U21,N('Debt Payoff'!E12)) -> 160 | AD21: =MIN(V21,N('Debt Payoff'!E13)) -> 0 | AE21: =MIN(W21,N('Debt Payoff'!E14)) -> 0 | AF21: =MIN(X21,N('Debt Payoff'!E15)) -> 0 | AG21: =MIN(Y21,N('Debt Payoff'!E16)) -> 0 | AH21: =R21-Z21 -> 0 | AI21: =S21-AA21 -> 116.32139 | AJ21: =T21-AB21 -> 5223.3419 | AK21: =U21-AC21 -> 12647.463 | AL21: =V21-AD21 -> 0 | AM21: =W21-AE21 -> 0 | AN21: =X21-AF21 -> 0 | AO21: =Y21-AG21 -> 0 | AP21: =MAX(0,'Debt Payoff'!$D$17-SUM(Z21:AG21)) -> 320 | AQ21: =MIN(AH21,MAX(0,$AP21-SUMPRODUCT(($AH$1:$AO$1<AH$1)*$AH21:$AO21))) -> 0 | AR21: =MIN(AI21,MAX(0,$AP21-SUMPRODUCT(($AH$1:$AO$1<AI$1)*$AH21:$AO21))) -> 116.32139 | AS21: =MIN(AJ21,MAX(0,$AP21-SUMPRODUCT(($AH$1:$AO$1<AJ$1)*$AH21:$AO21))) -> 203.67861 | AT21: =MIN(AK21,MAX(0,$AP21-SUMPRODUCT(($AH$1:$AO$1<AK$1)*$AH21:$AO21))) -> 0 | AU21: =MIN(AL21,MAX(0,$AP21-SUMPRODUCT(($AH$1:$AO$1<AL$1)*$AH21:$AO21))) -> 0 | AV21: =MIN(AM21,MAX(0,$AP21-SUMPRODUCT(($AH$1:$AO$1<AM$1)*$AH21:$AO21))) -> 0 | AW21: =MIN(AN21,MAX(0,$AP21-SUMPRODUCT(($AH$1:$AO$1<AN$1)*$AH21:$AO21))) -> 0 | AX21: =MIN(AO21,MAX(0,$AP21-SUMPRODUCT(($AH$1:$AO$1<AO$1)*$AH21:$AO21))) -> 0 | AY21: =ROUND(AH21-AQ21,2) -> 0 | AZ21: =ROUND(AI21-AR21,2) -> 0 | BA21: =ROUND(AJ21-AS21,2) -> 5019.66 | BB21: =ROUND(AK21-AT21,2) -> 12647.46 | BC21: =ROUND(AL21-AU21,2) -> 0 | BD21: =ROUND(AM21-AV21,2) -> 0 | BE21: =ROUND(AN21-AW21,2) -> 0 | BF21: =ROUND(AO21-AX21,2) -> 0 | BG21: =SUM(AY21:BF21) -> 17667.12
A22: 20 | B22: =AY21 -> 0 | C22: =AZ21 -> 0 | D22: =BA21 -> 5019.66 | E22: =BB21 -> 12647.46 | F22: =BC21 -> 0 | G22: =BD21 -> 0 | H22: =BE21 -> 0 | I22: =BF21 -> 0 | J22: =B22*N('Debt Payoff'!D9)/12 -> 0 | K22: =C22*N('Debt Payoff'!D10)/12 -> 0 | L22: =D22*N('Debt Payoff'!D11)/12 -> 28.863045 | M22: =E22*N('Debt Payoff'!D12)/12 -> 57.967525 | N22: =F22*N('Debt Payoff'!D13)/12 -> 0 | O22: =G22*N('Debt Payoff'!D14)/12 -> 0 | P22: =H22*N('Debt Payoff'!D15)/12 -> 0 | Q22: =I22*N('Debt Payoff'!D16)/12 -> 0 | R22: =B22+J22 -> 0 | S22: =C22+K22 -> 0 | T22: =D22+L22 -> 5048.523 | U22: =E22+M22 -> 12705.428 | V22: =F22+N22 -> 0 | W22: =G22+O22 -> 0 | X22: =H22+P22 -> 0 | Y22: =I22+Q22 -> 0 | Z22: =MIN(R22,N('Debt Payoff'!E9)) -> 0 | AA22: =MIN(S22,N('Debt Payoff'!E10)) -> 0 | AB22: =MIN(T22,N('Debt Payoff'!E11)) -> 285 | AC22: =MIN(U22,N('Debt Payoff'!E12)) -> 160 | AD22: =MIN(V22,N('Debt Payoff'!E13)) -> 0 | AE22: =MIN(W22,N('Debt Payoff'!E14)) -> 0 | AF22: =MIN(X22,N('Debt Payoff'!E15)) -> 0 | AG22: =MIN(Y22,N('Debt Payoff'!E16)) -> 0 | AH22: =R22-Z22 -> 0 | AI22: =S22-AA22 -> 0 | AJ22: =T22-AB22 -> 4763.523 | AK22: =U22-AC22 -> 12545.428 | AL22: =V22-AD22 -> 0 | AM22: =W22-AE22 -> 0 | AN22: =X22-AF22 -> 0 | AO22: =Y22-AG22 -> 0 | AP22: =MAX(0,'Debt Payoff'!$D$17-SUM(Z22:AG22)) -> 360 | AQ22: =MIN(AH22,MAX(0,$AP22-SUMPRODUCT(($AH$1:$AO$1<AH$1)*$AH22:$AO22))) -> 0 | AR22: =MIN(AI22,MAX(0,$AP22-SUMPRODUCT(($AH$1:$AO$1<AI$1)*$AH22:$AO22))) -> 0 | AS22: =MIN(AJ22,MAX(0,$AP22-SUMPRODUCT(($AH$1:$AO$1<AJ$1)*$AH22:$AO22))) -> 360 | AT22: =MIN(AK22,MAX(0,$AP22-SUMPRODUCT(($AH$1:$AO$1<AK$1)*$AH22:$AO22))) -> 0 | AU22: =MIN(AL22,MAX(0,$AP22-SUMPRODUCT(($AH$1:$AO$1<AL$1)*$AH22:$AO22))) -> 0 | AV22: =MIN(AM22,MAX(0,$AP22-SUMPRODUCT(($AH$1:$AO$1<AM$1)*$AH22:$AO22))) -> 0 | AW22: =MIN(AN22,MAX(0,$AP22-SUMPRODUCT(($AH$1:$AO$1<AN$1)*$AH22:$AO22))) -> 0 | AX22: =MIN(AO22,MAX(0,$AP22-SUMPRODUCT(($AH$1:$AO$1<AO$1)*$AH22:$AO22))) -> 0 | AY22: =ROUND(AH22-AQ22,2) -> 0 | AZ22: =ROUND(AI22-AR22,2) -> 0 | BA22: =ROUND(AJ22-AS22,2) -> 4403.52 | BB22: =ROUND(AK22-AT22,2) -> 12545.43 | BC22: =ROUND(AL22-AU22,2) -> 0 | BD22: =ROUND(AM22-AV22,2) -> 0 | BE22: =ROUND(AN22-AW22,2) -> 0 | BF22: =ROUND(AO22-AX22,2) -> 0 | BG22: =SUM(AY22:BF22) -> 16948.95
A23: 21 | B23: =AY22 -> 0 | C23: =AZ22 -> 0 | D23: =BA22 -> 4403.52 | E23: =BB22 -> 12545.43 | F23: =BC22 -> 0 | G23: =BD22 -> 0 | H23: =BE22 -> 0 | I23: =BF22 -> 0 | J23: =B23*N('Debt Payoff'!D9)/12 -> 0 | K23: =C23*N('Debt Payoff'!D10)/12 -> 0 | L23: =D23*N('Debt Payoff'!D11)/12 -> 25.32024 | M23: =E23*N('Debt Payoff'!D12)/12 -> 57.499887 | N23: =F23*N('Debt Payoff'!D13)/12 -> 0 | O23: =G23*N('Debt Payoff'!D14)/12 -> 0 | P23: =H23*N('Debt Payoff'!D15)/12 -> 0 | Q23: =I23*N('Debt Payoff'!D16)/12 -> 0 | R23: =B23+J23 -> 0 | S23: =C23+K23 -> 0 | T23: =D23+L23 -> 4428.8402 | U23: =E23+M23 -> 12602.93 | V23: =F23+N23 -> 0 | W23: =G23+O23 -> 0 | X23: =H23+P23 -> 0 | Y23: =I23+Q23 -> 0 | Z23: =MIN(R23,N('Debt Payoff'!E9)) -> 0 | AA23: =MIN(S23,N('Debt Payoff'!E10)) -> 0 | AB23: =MIN(T23,N('Debt Payoff'!E11)) -> 285 | AC23: =MIN(U23,N('Debt Payoff'!E12)) -> 160 | AD23: =MIN(V23,N('Debt Payoff'!E13)) -> 0 | AE23: =MIN(W23,N('Debt Payoff'!E14)) -> 0 | AF23: =MIN(X23,N('Debt Payoff'!E15)) -> 0 | AG23: =MIN(Y23,N('Debt Payoff'!E16)) -> 0 | AH23: =R23-Z23 -> 0 | AI23: =S23-AA23 -> 0 | AJ23: =T23-AB23 -> 4143.8402 | AK23: =U23-AC23 -> 12442.93 | AL23: =V23-AD23 -> 0 | AM23: =W23-AE23 -> 0 | AN23: =X23-AF23 -> 0 | AO23: =Y23-AG23 -> 0 | AP23: =MAX(0,'Debt Payoff'!$D$17-SUM(Z23:AG23)) -> 360 | AQ23: =MIN(AH23,MAX(0,$AP23-SUMPRODUCT(($AH$1:$AO$1<AH$1)*$AH23:$AO23))) -> 0 | AR23: =MIN(AI23,MAX(0,$AP23-SUMPRODUCT(($AH$1:$AO$1<AI$1)*$AH23:$AO23))) -> 0 | AS23: =MIN(AJ23,MAX(0,$AP23-SUMPRODUCT(($AH$1:$AO$1<AJ$1)*$AH23:$AO23))) -> 360 | AT23: =MIN(AK23,MAX(0,$AP23-SUMPRODUCT(($AH$1:$AO$1<AK$1)*$AH23:$AO23))) -> 0 | AU23: =MIN(AL23,MAX(0,$AP23-SUMPRODUCT(($AH$1:$AO$1<AL$1)*$AH23:$AO23))) -> 0 | AV23: =MIN(AM23,MAX(0,$AP23-SUMPRODUCT(($AH$1:$AO$1<AM$1)*$AH23:$AO23))) -> 0 | AW23: =MIN(AN23,MAX(0,$AP23-SUMPRODUCT(($AH$1:$AO$1<AN$1)*$AH23:$AO23))) -> 0 | AX23: =MIN(AO23,MAX(0,$AP23-SUMPRODUCT(($AH$1:$AO$1<AO$1)*$AH23:$AO23))) -> 0 | AY23: =ROUND(AH23-AQ23,2) -> 0 | AZ23: =ROUND(AI23-AR23,2) -> 0 | BA23: =ROUND(AJ23-AS23,2) -> 3783.84 | BB23: =ROUND(AK23-AT23,2) -> 12442.93 | BC23: =ROUND(AL23-AU23,2) -> 0 | BD23: =ROUND(AM23-AV23,2) -> 0 | BE23: =ROUND(AN23-AW23,2) -> 0 | BF23: =ROUND(AO23-AX23,2) -> 0 | BG23: =SUM(AY23:BF23) -> 16226.77
A24: 22 | B24: =AY23 -> 0 | C24: =AZ23 -> 0 | D24: =BA23 -> 3783.84 | E24: =BB23 -> 12442.93 | F24: =BC23 -> 0 | G24: =BD23 -> 0 | H24: =BE23 -> 0 | I24: =BF23 -> 0 | J24: =B24*N('Debt Payoff'!D9)/12 -> 0 | K24: =C24*N('Debt Payoff'!D10)/12 -> 0 | L24: =D24*N('Debt Payoff'!D11)/12 -> 21.75708 | M24: =E24*N('Debt Payoff'!D12)/12 -> 57.030096 | N24: =F24*N('Debt Payoff'!D13)/12 -> 0 | O24: =G24*N('Debt Payoff'!D14)/12 -> 0 | P24: =H24*N('Debt Payoff'!D15)/12 -> 0 | Q24: =I24*N('Debt Payoff'!D16)/12 -> 0 | R24: =B24+J24 -> 0 | S24: =C24+K24 -> 0 | T24: =D24+L24 -> 3805.5971 | U24: =E24+M24 -> 12499.96 | V24: =F24+N24 -> 0 | W24: =G24+O24 -> 0 | X24: =H24+P24 -> 0 | Y24: =I24+Q24 -> 0 | Z24: =MIN(R24,N('Debt Payoff'!E9)) -> 0 | AA24: =MIN(S24,N('Debt Payoff'!E10)) -> 0 | AB24: =MIN(T24,N('Debt Payoff'!E11)) -> 285 | AC24: =MIN(U24,N('Debt Payoff'!E12)) -> 160 | AD24: =MIN(V24,N('Debt Payoff'!E13)) -> 0 | AE24: =MIN(W24,N('Debt Payoff'!E14)) -> 0 | AF24: =MIN(X24,N('Debt Payoff'!E15)) -> 0 | AG24: =MIN(Y24,N('Debt Payoff'!E16)) -> 0 | AH24: =R24-Z24 -> 0 | AI24: =S24-AA24 -> 0 | AJ24: =T24-AB24 -> 3520.5971 | AK24: =U24-AC24 -> 12339.96 | AL24: =V24-AD24 -> 0 | AM24: =W24-AE24 -> 0 | AN24: =X24-AF24 -> 0 | AO24: =Y24-AG24 -> 0 | AP24: =MAX(0,'Debt Payoff'!$D$17-SUM(Z24:AG24)) -> 360 | AQ24: =MIN(AH24,MAX(0,$AP24-SUMPRODUCT(($AH$1:$AO$1<AH$1)*$AH24:$AO24))) -> 0 | AR24: =MIN(AI24,MAX(0,$AP24-SUMPRODUCT(($AH$1:$AO$1<AI$1)*$AH24:$AO24))) -> 0 | AS24: =MIN(AJ24,MAX(0,$AP24-SUMPRODUCT(($AH$1:$AO$1<AJ$1)*$AH24:$AO24))) -> 360 | AT24: =MIN(AK24,MAX(0,$AP24-SUMPRODUCT(($AH$1:$AO$1<AK$1)*$AH24:$AO24))) -> 0 | AU24: =MIN(AL24,MAX(0,$AP24-SUMPRODUCT(($AH$1:$AO$1<AL$1)*$AH24:$AO24))) -> 0 | AV24: =MIN(AM24,MAX(0,$AP24-SUMPRODUCT(($AH$1:$AO$1<AM$1)*$AH24:$AO24))) -> 0 | AW24: =MIN(AN24,MAX(0,$AP24-SUMPRODUCT(($AH$1:$AO$1<AN$1)*$AH24:$AO24))) -> 0 | AX24: =MIN(AO24,MAX(0,$AP24-SUMPRODUCT(($AH$1:$AO$1<AO$1)*$AH24:$AO24))) -> 0 | AY24: =ROUND(AH24-AQ24,2) -> 0 | AZ24: =ROUND(AI24-AR24,2) -> 0 | BA24: =ROUND(AJ24-AS24,2) -> 3160.6 | BB24: =ROUND(AK24-AT24,2) -> 12339.96 | BC24: =ROUND(AL24-AU24,2) -> 0 | BD24: =ROUND(AM24-AV24,2) -> 0 | BE24: =ROUND(AN24-AW24,2) -> 0 | BF24: =ROUND(AO24-AX24,2) -> 0 | BG24: =SUM(AY24:BF24) -> 15500.56
A25: 23 | B25: =AY24 -> 0 | C25: =AZ24 -> 0 | D25: =BA24 -> 3160.6 | E25: =BB24 -> 12339.96 | F25: =BC24 -> 0 | G25: =BD24 -> 0 | H25: =BE24 -> 0 | I25: =BF24 -> 0 | J25: =B25*N('Debt Payoff'!D9)/12 -> 0 | K25: =C25*N('Debt Payoff'!D10)/12 -> 0 | L25: =D25*N('Debt Payoff'!D11)/12 -> 18.17345 | M25: =E25*N('Debt Payoff'!D12)/12 -> 56.55815 | N25: =F25*N('Debt Payoff'!D13)/12 -> 0 | O25: =G25*N('Debt Payoff'!D14)/12 -> 0 | P25: =H25*N('Debt Payoff'!D15)/12 -> 0 | Q25: =I25*N('Debt Payoff'!D16)/12 -> 0 | R25: =B25+J25 -> 0 | S25: =C25+K25 -> 0 | T25: =D25+L25 -> 3178.7735 | U25: =E25+M25 -> 12396.518 | V25: =F25+N25 -> 0 | W25: =G25+O25 -> 0 | X25: =H25+P25 -> 0 | Y25: =I25+Q25 -> 0 | Z25: =MIN(R25,N('Debt Payoff'!E9)) -> 0 | AA25: =MIN(S25,N('Debt Payoff'!E10)) -> 0 | AB25: =MIN(T25,N('Debt Payoff'!E11)) -> 285 | AC25: =MIN(U25,N('Debt Payoff'!E12)) -> 160 | AD25: =MIN(V25,N('Debt Payoff'!E13)) -> 0 | AE25: =MIN(W25,N('Debt Payoff'!E14)) -> 0 | AF25: =MIN(X25,N('Debt Payoff'!E15)) -> 0 | AG25: =MIN(Y25,N('Debt Payoff'!E16)) -> 0 | AH25: =R25-Z25 -> 0 | AI25: =S25-AA25 -> 0 | AJ25: =T25-AB25 -> 2893.7735 | AK25: =U25-AC25 -> 12236.518 | AL25: =V25-AD25 -> 0 | AM25: =W25-AE25 -> 0 | AN25: =X25-AF25 -> 0 | AO25: =Y25-AG25 -> 0 | AP25: =MAX(0,'Debt Payoff'!$D$17-SUM(Z25:AG25)) -> 360 | AQ25: =MIN(AH25,MAX(0,$AP25-SUMPRODUCT(($AH$1:$AO$1<AH$1)*$AH25:$AO25))) -> 0 | AR25: =MIN(AI25,MAX(0,$AP25-SUMPRODUCT(($AH$1:$AO$1<AI$1)*$AH25:$AO25))) -> 0 | AS25: =MIN(AJ25,MAX(0,$AP25-SUMPRODUCT(($AH$1:$AO$1<AJ$1)*$AH25:$AO25))) -> 360 | AT25: =MIN(AK25,MAX(0,$AP25-SUMPRODUCT(($AH$1:$AO$1<AK$1)*$AH25:$AO25))) -> 0 | AU25: =MIN(AL25,MAX(0,$AP25-SUMPRODUCT(($AH$1:$AO$1<AL$1)*$AH25:$AO25))) -> 0 | AV25: =MIN(AM25,MAX(0,$AP25-SUMPRODUCT(($AH$1:$AO$1<AM$1)*$AH25:$AO25))) -> 0 | AW25: =MIN(AN25,MAX(0,$AP25-SUMPRODUCT(($AH$1:$AO$1<AN$1)*$AH25:$AO25))) -> 0 | AX25: =MIN(AO25,MAX(0,$AP25-SUMPRODUCT(($AH$1:$AO$1<AO$1)*$AH25:$AO25))) -> 0 | AY25: =ROUND(AH25-AQ25,2) -> 0 | AZ25: =ROUND(AI25-AR25,2) -> 0 | BA25: =ROUND(AJ25-AS25,2) -> 2533.77 | BB25: =ROUND(AK25-AT25,2) -> 12236.52 | BC25: =ROUND(AL25-AU25,2) -> 0 | BD25: =ROUND(AM25-AV25,2) -> 0 | BE25: =ROUND(AN25-AW25,2) -> 0 | BF25: =ROUND(AO25-AX25,2) -> 0 | BG25: =SUM(AY25:BF25) -> 14770.29
A26: 24 | B26: =AY25 -> 0 | C26: =AZ25 -> 0 | D26: =BA25 -> 2533.77 | E26: =BB25 -> 12236.52 | F26: =BC25 -> 0 | G26: =BD25 -> 0 | H26: =BE25 -> 0 | I26: =BF25 -> 0 | J26: =B26*N('Debt Payoff'!D9)/12 -> 0 | K26: =C26*N('Debt Payoff'!D10)/12 -> 0 | L26: =D26*N('Debt Payoff'!D11)/12 -> 14.569178 | M26: =E26*N('Debt Payoff'!D12)/12 -> 56.08405 | N26: =F26*N('Debt Payoff'!D13)/12 -> 0 | O26: =G26*N('Debt Payoff'!D14)/12 -> 0 | P26: =H26*N('Debt Payoff'!D15)/12 -> 0 | Q26: =I26*N('Debt Payoff'!D16)/12 -> 0 | R26: =B26+J26 -> 0 | S26: =C26+K26 -> 0 | T26: =D26+L26 -> 2548.3392 | U26: =E26+M26 -> 12292.604 | V26: =F26+N26 -> 0 | W26: =G26+O26 -> 0 | X26: =H26+P26 -> 0 | Y26: =I26+Q26 -> 0 | Z26: =MIN(R26,N('Debt Payoff'!E9)) -> 0 | AA26: =MIN(S26,N('Debt Payoff'!E10)) -> 0 | AB26: =MIN(T26,N('Debt Payoff'!E11)) -> 285 | AC26: =MIN(U26,N('Debt Payoff'!E12)) -> 160 | AD26: =MIN(V26,N('Debt Payoff'!E13)) -> 0 | AE26: =MIN(W26,N('Debt Payoff'!E14)) -> 0 | AF26: =MIN(X26,N('Debt Payoff'!E15)) -> 0 | AG26: =MIN(Y26,N('Debt Payoff'!E16)) -> 0 | AH26: =R26-Z26 -> 0 | AI26: =S26-AA26 -> 0 | AJ26: =T26-AB26 -> 2263.3392 | AK26: =U26-AC26 -> 12132.604 | AL26: =V26-AD26 -> 0 | AM26: =W26-AE26 -> 0 | AN26: =X26-AF26 -> 0 | AO26: =Y26-AG26 -> 0 | AP26: =MAX(0,'Debt Payoff'!$D$17-SUM(Z26:AG26)) -> 360 | AQ26: =MIN(AH26,MAX(0,$AP26-SUMPRODUCT(($AH$1:$AO$1<AH$1)*$AH26:$AO26))) -> 0 | AR26: =MIN(AI26,MAX(0,$AP26-SUMPRODUCT(($AH$1:$AO$1<AI$1)*$AH26:$AO26))) -> 0 | AS26: =MIN(AJ26,MAX(0,$AP26-SUMPRODUCT(($AH$1:$AO$1<AJ$1)*$AH26:$AO26))) -> 360 | AT26: =MIN(AK26,MAX(0,$AP26-SUMPRODUCT(($AH$1:$AO$1<AK$1)*$AH26:$AO26))) -> 0 | AU26: =MIN(AL26,MAX(0,$AP26-SUMPRODUCT(($AH$1:$AO$1<AL$1)*$AH26:$AO26))) -> 0 | AV26: =MIN(AM26,MAX(0,$AP26-SUMPRODUCT(($AH$1:$AO$1<AM$1)*$AH26:$AO26))) -> 0 | AW26: =MIN(AN26,MAX(0,$AP26-SUMPRODUCT(($AH$1:$AO$1<AN$1)*$AH26:$AO26))) -> 0 | AX26: =MIN(AO26,MAX(0,$AP26-SUMPRODUCT(($AH$1:$AO$1<AO$1)*$AH26:$AO26))) -> 0 | AY26: =ROUND(AH26-AQ26,2) -> 0 | AZ26: =ROUND(AI26-AR26,2) -> 0 | BA26: =ROUND(AJ26-AS26,2) -> 1903.34 | BB26: =ROUND(AK26-AT26,2) -> 12132.6 | BC26: =ROUND(AL26-AU26,2) -> 0 | BD26: =ROUND(AM26-AV26,2) -> 0 | BE26: =ROUND(AN26-AW26,2) -> 0 | BF26: =ROUND(AO26-AX26,2) -> 0 | BG26: =SUM(AY26:BF26) -> 14035.94
A27: 25 | B27: =AY26 -> 0 | C27: =AZ26 -> 0 | D27: =BA26 -> 1903.34 | E27: =BB26 -> 12132.6 | F27: =BC26 -> 0 | G27: =BD26 -> 0 | H27: =BE26 -> 0 | I27: =BF26 -> 0 | J27: =B27*N('Debt Payoff'!D9)/12 -> 0 | K27: =C27*N('Debt Payoff'!D10)/12 -> 0 | L27: =D27*N('Debt Payoff'!D11)/12 -> 10.944205 | M27: =E27*N('Debt Payoff'!D12)/12 -> 55.60775 | N27: =F27*N('Debt Payoff'!D13)/12 -> 0 | O27: =G27*N('Debt Payoff'!D14)/12 -> 0 | P27: =H27*N('Debt Payoff'!D15)/12 -> 0 | Q27: =I27*N('Debt Payoff'!D16)/12 -> 0 | R27: =B27+J27 -> 0 | S27: =C27+K27 -> 0 | T27: =D27+L27 -> 1914.2842 | U27: =E27+M27 -> 12188.208 | V27: =F27+N27 -> 0 | W27: =G27+O27 -> 0 | X27: =H27+P27 -> 0 | Y27: =I27+Q27 -> 0 | Z27: =MIN(R27,N('Debt Payoff'!E9)) -> 0 | AA27: =MIN(S27,N('Debt Payoff'!E10)) -> 0 | AB27: =MIN(T27,N('Debt Payoff'!E11)) -> 285 | AC27: =MIN(U27,N('Debt Payoff'!E12)) -> 160 | AD27: =MIN(V27,N('Debt Payoff'!E13)) -> 0 | AE27: =MIN(W27,N('Debt Payoff'!E14)) -> 0 | AF27: =MIN(X27,N('Debt Payoff'!E15)) -> 0 | AG27: =MIN(Y27,N('Debt Payoff'!E16)) -> 0 | AH27: =R27-Z27 -> 0 | AI27: =S27-AA27 -> 0 | AJ27: =T27-AB27 -> 1629.2842 | AK27: =U27-AC27 -> 12028.208 | AL27: =V27-AD27 -> 0 | AM27: =W27-AE27 -> 0 | AN27: =X27-AF27 -> 0 | AO27: =Y27-AG27 -> 0 | AP27: =MAX(0,'Debt Payoff'!$D$17-SUM(Z27:AG27)) -> 360 | AQ27: =MIN(AH27,MAX(0,$AP27-SUMPRODUCT(($AH$1:$AO$1<AH$1)*$AH27:$AO27))) -> 0 | AR27: =MIN(AI27,MAX(0,$AP27-SUMPRODUCT(($AH$1:$AO$1<AI$1)*$AH27:$AO27))) -> 0 | AS27: =MIN(AJ27,MAX(0,$AP27-SUMPRODUCT(($AH$1:$AO$1<AJ$1)*$AH27:$AO27))) -> 360 | AT27: =MIN(AK27,MAX(0,$AP27-SUMPRODUCT(($AH$1:$AO$1<AK$1)*$AH27:$AO27))) -> 0 | AU27: =MIN(AL27,MAX(0,$AP27-SUMPRODUCT(($AH$1:$AO$1<AL$1)*$AH27:$AO27))) -> 0 | AV27: =MIN(AM27,MAX(0,$AP27-SUMPRODUCT(($AH$1:$AO$1<AM$1)*$AH27:$AO27))) -> 0 | AW27: =MIN(AN27,MAX(0,$AP27-SUMPRODUCT(($AH$1:$AO$1<AN$1)*$AH27:$AO27))) -> 0 | AX27: =MIN(AO27,MAX(0,$AP27-SUMPRODUCT(($AH$1:$AO$1<AO$1)*$AH27:$AO27))) -> 0 | AY27: =ROUND(AH27-AQ27,2) -> 0 | AZ27: =ROUND(AI27-AR27,2) -> 0 | BA27: =ROUND(AJ27-AS27,2) -> 1269.28 | BB27: =ROUND(AK27-AT27,2) -> 12028.21 | BC27: =ROUND(AL27-AU27,2) -> 0 | BD27: =ROUND(AM27-AV27,2) -> 0 | BE27: =ROUND(AN27-AW27,2) -> 0 | BF27: =ROUND(AO27-AX27,2) -> 0 | BG27: =SUM(AY27:BF27) -> 13297.49
A28: 26 | B28: =AY27 -> 0 | C28: =AZ27 -> 0 | D28: =BA27 -> 1269.28 | E28: =BB27 -> 12028.21 | F28: =BC27 -> 0 | G28: =BD27 -> 0 | H28: =BE27 -> 0 | I28: =BF27 -> 0 | J28: =B28*N('Debt Payoff'!D9)/12 -> 0 | K28: =C28*N('Debt Payoff'!D10)/12 -> 0 | L28: =D28*N('Debt Payoff'!D11)/12 -> 7.29836 | M28: =E28*N('Debt Payoff'!D12)/12 -> 55.129296 | N28: =F28*N('Debt Payoff'!D13)/12 -> 0 | O28: =G28*N('Debt Payoff'!D14)/12 -> 0 | P28: =H28*N('Debt Payoff'!D15)/12 -> 0 | Q28: =I28*N('Debt Payoff'!D16)/12 -> 0 | R28: =B28+J28 -> 0 | S28: =C28+K28 -> 0 | T28: =D28+L28 -> 1276.5784 | U28: =E28+M28 -> 12083.339 | V28: =F28+N28 -> 0 | W28: =G28+O28 -> 0 | X28: =H28+P28 -> 0 | Y28: =I28+Q28 -> 0 | Z28: =MIN(R28,N('Debt Payoff'!E9)) -> 0 | AA28: =MIN(S28,N('Debt Payoff'!E10)) -> 0 | AB28: =MIN(T28,N('Debt Payoff'!E11)) -> 285 | AC28: =MIN(U28,N('Debt Payoff'!E12)) -> 160 | AD28: =MIN(V28,N('Debt Payoff'!E13)) -> 0 | AE28: =MIN(W28,N('Debt Payoff'!E14)) -> 0 | AF28: =MIN(X28,N('Debt Payoff'!E15)) -> 0 | AG28: =MIN(Y28,N('Debt Payoff'!E16)) -> 0 | AH28: =R28-Z28 -> 0 | AI28: =S28-AA28 -> 0 | AJ28: =T28-AB28 -> 991.57836 | AK28: =U28-AC28 -> 11923.339 | AL28: =V28-AD28 -> 0 | AM28: =W28-AE28 -> 0 | AN28: =X28-AF28 -> 0 | AO28: =Y28-AG28 -> 0 | AP28: =MAX(0,'Debt Payoff'!$D$17-SUM(Z28:AG28)) -> 360 | AQ28: =MIN(AH28,MAX(0,$AP28-SUMPRODUCT(($AH$1:$AO$1<AH$1)*$AH28:$AO28))) -> 0 | AR28: =MIN(AI28,MAX(0,$AP28-SUMPRODUCT(($AH$1:$AO$1<AI$1)*$AH28:$AO28))) -> 0 | AS28: =MIN(AJ28,MAX(0,$AP28-SUMPRODUCT(($AH$1:$AO$1<AJ$1)*$AH28:$AO28))) -> 360 | AT28: =MIN(AK28,MAX(0,$AP28-SUMPRODUCT(($AH$1:$AO$1<AK$1)*$AH28:$AO28))) -> 0 | AU28: =MIN(AL28,MAX(0,$AP28-SUMPRODUCT(($AH$1:$AO$1<AL$1)*$AH28:$AO28))) -> 0 | AV28: =MIN(AM28,MAX(0,$AP28-SUMPRODUCT(($AH$1:$AO$1<AM$1)*$AH28:$AO28))) -> 0 | AW28: =MIN(AN28,MAX(0,$AP28-SUMPRODUCT(($AH$1:$AO$1<AN$1)*$AH28:$AO28))) -> 0 | AX28: =MIN(AO28,MAX(0,$AP28-SUMPRODUCT(($AH$1:$AO$1<AO$1)*$AH28:$AO28))) -> 0 | AY28: =ROUND(AH28-AQ28,2) -> 0 | AZ28: =ROUND(AI28-AR28,2) -> 0 | BA28: =ROUND(AJ28-AS28,2) -> 631.58 | BB28: =ROUND(AK28-AT28,2) -> 11923.34 | BC28: =ROUND(AL28-AU28,2) -> 0 | BD28: =ROUND(AM28-AV28,2) -> 0 | BE28: =ROUND(AN28-AW28,2) -> 0 | BF28: =ROUND(AO28-AX28,2) -> 0 | BG28: =SUM(AY28:BF28) -> 12554.92
A29: 27 | B29: =AY28 -> 0 | C29: =AZ28 -> 0 | D29: =BA28 -> 631.58 | E29: =BB28 -> 11923.34 | F29: =BC28 -> 0 | G29: =BD28 -> 0 | H29: =BE28 -> 0 | I29: =BF28 -> 0 | J29: =B29*N('Debt Payoff'!D9)/12 -> 0 | K29: =C29*N('Debt Payoff'!D10)/12 -> 0 | L29: =D29*N('Debt Payoff'!D11)/12 -> 3.631585 | M29: =E29*N('Debt Payoff'!D12)/12 -> 54.648642 | N29: =F29*N('Debt Payoff'!D13)/12 -> 0 | O29: =G29*N('Debt Payoff'!D14)/12 -> 0 | P29: =H29*N('Debt Payoff'!D15)/12 -> 0 | Q29: =I29*N('Debt Payoff'!D16)/12 -> 0 | R29: =B29+J29 -> 0 | S29: =C29+K29 -> 0 | T29: =D29+L29 -> 635.21159 | U29: =E29+M29 -> 11977.989 | V29: =F29+N29 -> 0 | W29: =G29+O29 -> 0 | X29: =H29+P29 -> 0 | Y29: =I29+Q29 -> 0 | Z29: =MIN(R29,N('Debt Payoff'!E9)) -> 0 | AA29: =MIN(S29,N('Debt Payoff'!E10)) -> 0 | AB29: =MIN(T29,N('Debt Payoff'!E11)) -> 285 | AC29: =MIN(U29,N('Debt Payoff'!E12)) -> 160 | AD29: =MIN(V29,N('Debt Payoff'!E13)) -> 0 | AE29: =MIN(W29,N('Debt Payoff'!E14)) -> 0 | AF29: =MIN(X29,N('Debt Payoff'!E15)) -> 0 | AG29: =MIN(Y29,N('Debt Payoff'!E16)) -> 0 | AH29: =R29-Z29 -> 0 | AI29: =S29-AA29 -> 0 | AJ29: =T29-AB29 -> 350.21159 | AK29: =U29-AC29 -> 11817.989 | AL29: =V29-AD29 -> 0 | AM29: =W29-AE29 -> 0 | AN29: =X29-AF29 -> 0 | AO29: =Y29-AG29 -> 0 | AP29: =MAX(0,'Debt Payoff'!$D$17-SUM(Z29:AG29)) -> 360 | AQ29: =MIN(AH29,MAX(0,$AP29-SUMPRODUCT(($AH$1:$AO$1<AH$1)*$AH29:$AO29))) -> 0 | AR29: =MIN(AI29,MAX(0,$AP29-SUMPRODUCT(($AH$1:$AO$1<AI$1)*$AH29:$AO29))) -> 0 | AS29: =MIN(AJ29,MAX(0,$AP29-SUMPRODUCT(($AH$1:$AO$1<AJ$1)*$AH29:$AO29))) -> 350.21159 | AT29: =MIN(AK29,MAX(0,$AP29-SUMPRODUCT(($AH$1:$AO$1<AK$1)*$AH29:$AO29))) -> 9.788415 | AU29: =MIN(AL29,MAX(0,$AP29-SUMPRODUCT(($AH$1:$AO$1<AL$1)*$AH29:$AO29))) -> 0 | AV29: =MIN(AM29,MAX(0,$AP29-SUMPRODUCT(($AH$1:$AO$1<AM$1)*$AH29:$AO29))) -> 0 | AW29: =MIN(AN29,MAX(0,$AP29-SUMPRODUCT(($AH$1:$AO$1<AN$1)*$AH29:$AO29))) -> 0 | AX29: =MIN(AO29,MAX(0,$AP29-SUMPRODUCT(($AH$1:$AO$1<AO$1)*$AH29:$AO29))) -> 0 | AY29: =ROUND(AH29-AQ29,2) -> 0 | AZ29: =ROUND(AI29-AR29,2) -> 0 | BA29: =ROUND(AJ29-AS29,2) -> 0 | BB29: =ROUND(AK29-AT29,2) -> 11808.2 | BC29: =ROUND(AL29-AU29,2) -> 0 | BD29: =ROUND(AM29-AV29,2) -> 0 | BE29: =ROUND(AN29-AW29,2) -> 0 | BF29: =ROUND(AO29-AX29,2) -> 0 | BG29: =SUM(AY29:BF29) -> 11808.2
A30: 28 | B30: =AY29 -> 0 | C30: =AZ29 -> 0 | D30: =BA29 -> 0 | E30: =BB29 -> 11808.2 | F30: =BC29 -> 0 | G30: =BD29 -> 0 | H30: =BE29 -> 0 | I30: =BF29 -> 0 | J30: =B30*N('Debt Payoff'!D9)/12 -> 0 | K30: =C30*N('Debt Payoff'!D10)/12 -> 0 | L30: =D30*N('Debt Payoff'!D11)/12 -> 0 | M30: =E30*N('Debt Payoff'!D12)/12 -> 54.120917 | N30: =F30*N('Debt Payoff'!D13)/12 -> 0 | O30: =G30*N('Debt Payoff'!D14)/12 -> 0 | P30: =H30*N('Debt Payoff'!D15)/12 -> 0 | Q30: =I30*N('Debt Payoff'!D16)/12 -> 0 | R30: =B30+J30 -> 0 | S30: =C30+K30 -> 0 | T30: =D30+L30 -> 0 | U30: =E30+M30 -> 11862.321 | V30: =F30+N30 -> 0 | W30: =G30+O30 -> 0 | X30: =H30+P30 -> 0 | Y30: =I30+Q30 -> 0 | Z30: =MIN(R30,N('Debt Payoff'!E9)) -> 0 | AA30: =MIN(S30,N('Debt Payoff'!E10)) -> 0 | AB30: =MIN(T30,N('Debt Payoff'!E11)) -> 0 | AC30: =MIN(U30,N('Debt Payoff'!E12)) -> 160 | AD30: =MIN(V30,N('Debt Payoff'!E13)) -> 0 | AE30: =MIN(W30,N('Debt Payoff'!E14)) -> 0 | AF30: =MIN(X30,N('Debt Payoff'!E15)) -> 0 | AG30: =MIN(Y30,N('Debt Payoff'!E16)) -> 0 | AH30: =R30-Z30 -> 0 | AI30: =S30-AA30 -> 0 | AJ30: =T30-AB30 -> 0 | AK30: =U30-AC30 -> 11702.321 | AL30: =V30-AD30 -> 0 | AM30: =W30-AE30 -> 0 | AN30: =X30-AF30 -> 0 | AO30: =Y30-AG30 -> 0 | AP30: =MAX(0,'Debt Payoff'!$D$17-SUM(Z30:AG30)) -> 645 | AQ30: =MIN(AH30,MAX(0,$AP30-SUMPRODUCT(($AH$1:$AO$1<AH$1)*$AH30:$AO30))) -> 0 | AR30: =MIN(AI30,MAX(0,$AP30-SUMPRODUCT(($AH$1:$AO$1<AI$1)*$AH30:$AO30))) -> 0 | AS30: =MIN(AJ30,MAX(0,$AP30-SUMPRODUCT(($AH$1:$AO$1<AJ$1)*$AH30:$AO30))) -> 0 | AT30: =MIN(AK30,MAX(0,$AP30-SUMPRODUCT(($AH$1:$AO$1<AK$1)*$AH30:$AO30))) -> 645 | AU30: =MIN(AL30,MAX(0,$AP30-SUMPRODUCT(($AH$1:$AO$1<AL$1)*$AH30:$AO30))) -> 0 | AV30: =MIN(AM30,MAX(0,$AP30-SUMPRODUCT(($AH$1:$AO$1<AM$1)*$AH30:$AO30))) -> 0 | AW30: =MIN(AN30,MAX(0,$AP30-SUMPRODUCT(($AH$1:$AO$1<AN$1)*$AH30:$AO30))) -> 0 | AX30: =MIN(AO30,MAX(0,$AP30-SUMPRODUCT(($AH$1:$AO$1<AO$1)*$AH30:$AO30))) -> 0 | AY30: =ROUND(AH30-AQ30,2) -> 0 | AZ30: =ROUND(AI30-AR30,2) -> 0 | BA30: =ROUND(AJ30-AS30,2) -> 0 | BB30: =ROUND(AK30-AT30,2) -> 11057.32 | BC30: =ROUND(AL30-AU30,2) -> 0 | BD30: =ROUND(AM30-AV30,2) -> 0 | BE30: =ROUND(AN30-AW30,2) -> 0 | BF30: =ROUND(AO30-AX30,2) -> 0 | BG30: =SUM(AY30:BF30) -> 11057.32
A31: 29 | B31: =AY30 -> 0 | C31: =AZ30 -> 0 | D31: =BA30 -> 0 | E31: =BB30 -> 11057.32 | F31: =BC30 -> 0 | G31: =BD30 -> 0 | H31: =BE30 -> 0 | I31: =BF30 -> 0 | J31: =B31*N('Debt Payoff'!D9)/12 -> 0 | K31: =C31*N('Debt Payoff'!D10)/12 -> 0 | L31: =D31*N('Debt Payoff'!D11)/12 -> 0 | M31: =E31*N('Debt Payoff'!D12)/12 -> 50.679383 | N31: =F31*N('Debt Payoff'!D13)/12 -> 0 | O31: =G31*N('Debt Payoff'!D14)/12 -> 0 | P31: =H31*N('Debt Payoff'!D15)/12 -> 0 | Q31: =I31*N('Debt Payoff'!D16)/12 -> 0 | R31: =B31+J31 -> 0 | S31: =C31+K31 -> 0 | T31: =D31+L31 -> 0 | U31: =E31+M31 -> 11107.999 | V31: =F31+N31 -> 0 | W31: =G31+O31 -> 0 | X31: =H31+P31 -> 0 | Y31: =I31+Q31 -> 0 | Z31: =MIN(R31,N('Debt Payoff'!E9)) -> 0 | AA31: =MIN(S31,N('Debt Payoff'!E10)) -> 0 | AB31: =MIN(T31,N('Debt Payoff'!E11)) -> 0 | AC31: =MIN(U31,N('Debt Payoff'!E12)) -> 160 | AD31: =MIN(V31,N('Debt Payoff'!E13)) -> 0 | AE31: =MIN(W31,N('Debt Payoff'!E14)) -> 0 | AF31: =MIN(X31,N('Debt Payoff'!E15)) -> 0 | AG31: =MIN(Y31,N('Debt Payoff'!E16)) -> 0 | AH31: =R31-Z31 -> 0 | AI31: =S31-AA31 -> 0 | AJ31: =T31-AB31 -> 0 | AK31: =U31-AC31 -> 10947.999 | AL31: =V31-AD31 -> 0 | AM31: =W31-AE31 -> 0 | AN31: =X31-AF31 -> 0 | AO31: =Y31-AG31 -> 0 | AP31: =MAX(0,'Debt Payoff'!$D$17-SUM(Z31:AG31)) -> 645 | AQ31: =MIN(AH31,MAX(0,$AP31-SUMPRODUCT(($AH$1:$AO$1<AH$1)*$AH31:$AO31))) -> 0 | AR31: =MIN(AI31,MAX(0,$AP31-SUMPRODUCT(($AH$1:$AO$1<AI$1)*$AH31:$AO31))) -> 0 | AS31: =MIN(AJ31,MAX(0,$AP31-SUMPRODUCT(($AH$1:$AO$1<AJ$1)*$AH31:$AO31))) -> 0 | AT31: =MIN(AK31,MAX(0,$AP31-SUMPRODUCT(($AH$1:$AO$1<AK$1)*$AH31:$AO31))) -> 645 | AU31: =MIN(AL31,MAX(0,$AP31-SUMPRODUCT(($AH$1:$AO$1<AL$1)*$AH31:$AO31))) -> 0 | AV31: =MIN(AM31,MAX(0,$AP31-SUMPRODUCT(($AH$1:$AO$1<AM$1)*$AH31:$AO31))) -> 0 | AW31: =MIN(AN31,MAX(0,$AP31-SUMPRODUCT(($AH$1:$AO$1<AN$1)*$AH31:$AO31))) -> 0 | AX31: =MIN(AO31,MAX(0,$AP31-SUMPRODUCT(($AH$1:$AO$1<AO$1)*$AH31:$AO31))) -> 0 | AY31: =ROUND(AH31-AQ31,2) -> 0 | AZ31: =ROUND(AI31-AR31,2) -> 0 | BA31: =ROUND(AJ31-AS31,2) -> 0 | BB31: =ROUND(AK31-AT31,2) -> 10303 | BC31: =ROUND(AL31-AU31,2) -> 0 | BD31: =ROUND(AM31-AV31,2) -> 0 | BE31: =ROUND(AN31-AW31,2) -> 0 | BF31: =ROUND(AO31-AX31,2) -> 0 | BG31: =SUM(AY31:BF31) -> 10303
A32: 30 | B32: =AY31 -> 0 | C32: =AZ31 -> 0 | D32: =BA31 -> 0 | E32: =BB31 -> 10303 | F32: =BC31 -> 0 | G32: =BD31 -> 0 | H32: =BE31 -> 0 | I32: =BF31 -> 0 | J32: =B32*N('Debt Payoff'!D9)/12 -> 0 | K32: =C32*N('Debt Payoff'!D10)/12 -> 0 | L32: =D32*N('Debt Payoff'!D11)/12 -> 0 | M32: =E32*N('Debt Payoff'!D12)/12 -> 47.222083 | N32: =F32*N('Debt Payoff'!D13)/12 -> 0 | O32: =G32*N('Debt Payoff'!D14)/12 -> 0 | P32: =H32*N('Debt Payoff'!D15)/12 -> 0 | Q32: =I32*N('Debt Payoff'!D16)/12 -> 0 | R32: =B32+J32 -> 0 | S32: =C32+K32 -> 0 | T32: =D32+L32 -> 0 | U32: =E32+M32 -> 10350.222 | V32: =F32+N32 -> 0 | W32: =G32+O32 -> 0 | X32: =H32+P32 -> 0 | Y32: =I32+Q32 -> 0 | Z32: =MIN(R32,N('Debt Payoff'!E9)) -> 0 | AA32: =MIN(S32,N('Debt Payoff'!E10)) -> 0 | AB32: =MIN(T32,N('Debt Payoff'!E11)) -> 0 | AC32: =MIN(U32,N('Debt Payoff'!E12)) -> 160 | AD32: =MIN(V32,N('Debt Payoff'!E13)) -> 0 | AE32: =MIN(W32,N('Debt Payoff'!E14)) -> 0 | AF32: =MIN(X32,N('Debt Payoff'!E15)) -> 0 | AG32: =MIN(Y32,N('Debt Payoff'!E16)) -> 0 | AH32: =R32-Z32 -> 0 | AI32: =S32-AA32 -> 0 | AJ32: =T32-AB32 -> 0 | AK32: =U32-AC32 -> 10190.222 | AL32: =V32-AD32 -> 0 | AM32: =W32-AE32 -> 0 | AN32: =X32-AF32 -> 0 | AO32: =Y32-AG32 -> 0 | AP32: =MAX(0,'Debt Payoff'!$D$17-SUM(Z32:AG32)) -> 645 | AQ32: =MIN(AH32,MAX(0,$AP32-SUMPRODUCT(($AH$1:$AO$1<AH$1)*$AH32:$AO32))) -> 0 | AR32: =MIN(AI32,MAX(0,$AP32-SUMPRODUCT(($AH$1:$AO$1<AI$1)*$AH32:$AO32))) -> 0 | AS32: =MIN(AJ32,MAX(0,$AP32-SUMPRODUCT(($AH$1:$AO$1<AJ$1)*$AH32:$AO32))) -> 0 | AT32: =MIN(AK32,MAX(0,$AP32-SUMPRODUCT(($AH$1:$AO$1<AK$1)*$AH32:$AO32))) -> 645 | AU32: =MIN(AL32,MAX(0,$AP32-SUMPRODUCT(($AH$1:$AO$1<AL$1)*$AH32:$AO32))) -> 0 | AV32: =MIN(AM32,MAX(0,$AP32-SUMPRODUCT(($AH$1:$AO$1<AM$1)*$AH32:$AO32))) -> 0 | AW32: =MIN(AN32,MAX(0,$AP32-SUMPRODUCT(($AH$1:$AO$1<AN$1)*$AH32:$AO32))) -> 0 | AX32: =MIN(AO32,MAX(0,$AP32-SUMPRODUCT(($AH$1:$AO$1<AO$1)*$AH32:$AO32))) -> 0 | AY32: =ROUND(AH32-AQ32,2) -> 0 | AZ32: =ROUND(AI32-AR32,2) -> 0 | BA32: =ROUND(AJ32-AS32,2) -> 0 | BB32: =ROUND(AK32-AT32,2) -> 9545.22 | BC32: =ROUND(AL32-AU32,2) -> 0 | BD32: =ROUND(AM32-AV32,2) -> 0 | BE32: =ROUND(AN32-AW32,2) -> 0 | BF32: =ROUND(AO32-AX32,2) -> 0 | BG32: =SUM(AY32:BF32) -> 9545.22
A33: 31 | B33: =AY32 -> 0 | C33: =AZ32 -> 0 | D33: =BA32 -> 0 | E33: =BB32 -> 9545.22 | F33: =BC32 -> 0 | G33: =BD32 -> 0 | H33: =BE32 -> 0 | I33: =BF32 -> 0 | J33: =B33*N('Debt Payoff'!D9)/12 -> 0 | K33: =C33*N('Debt Payoff'!D10)/12 -> 0 | L33: =D33*N('Debt Payoff'!D11)/12 -> 0 | M33: =E33*N('Debt Payoff'!D12)/12 -> 43.748925 | N33: =F33*N('Debt Payoff'!D13)/12 -> 0 | O33: =G33*N('Debt Payoff'!D14)/12 -> 0 | P33: =H33*N('Debt Payoff'!D15)/12 -> 0 | Q33: =I33*N('Debt Payoff'!D16)/12 -> 0 | R33: =B33+J33 -> 0 | S33: =C33+K33 -> 0 | T33: =D33+L33 -> 0 | U33: =E33+M33 -> 9588.9689 | V33: =F33+N33 -> 0 | W33: =G33+O33 -> 0 | X33: =H33+P33 -> 0 | Y33: =I33+Q33 -> 0 | Z33: =MIN(R33,N('Debt Payoff'!E9)) -> 0 | AA33: =MIN(S33,N('Debt Payoff'!E10)) -> 0 | AB33: =MIN(T33,N('Debt Payoff'!E11)) -> 0 | AC33: =MIN(U33,N('Debt Payoff'!E12)) -> 160 | AD33: =MIN(V33,N('Debt Payoff'!E13)) -> 0 | AE33: =MIN(W33,N('Debt Payoff'!E14)) -> 0 | AF33: =MIN(X33,N('Debt Payoff'!E15)) -> 0 | AG33: =MIN(Y33,N('Debt Payoff'!E16)) -> 0 | AH33: =R33-Z33 -> 0 | AI33: =S33-AA33 -> 0 | AJ33: =T33-AB33 -> 0 | AK33: =U33-AC33 -> 9428.9689 | AL33: =V33-AD33 -> 0 | AM33: =W33-AE33 -> 0 | AN33: =X33-AF33 -> 0 | AO33: =Y33-AG33 -> 0 | AP33: =MAX(0,'Debt Payoff'!$D$17-SUM(Z33:AG33)) -> 645 | AQ33: =MIN(AH33,MAX(0,$AP33-SUMPRODUCT(($AH$1:$AO$1<AH$1)*$AH33:$AO33))) -> 0 | AR33: =MIN(AI33,MAX(0,$AP33-SUMPRODUCT(($AH$1:$AO$1<AI$1)*$AH33:$AO33))) -> 0 | AS33: =MIN(AJ33,MAX(0,$AP33-SUMPRODUCT(($AH$1:$AO$1<AJ$1)*$AH33:$AO33))) -> 0 | AT33: =MIN(AK33,MAX(0,$AP33-SUMPRODUCT(($AH$1:$AO$1<AK$1)*$AH33:$AO33))) -> 645 | AU33: =MIN(AL33,MAX(0,$AP33-SUMPRODUCT(($AH$1:$AO$1<AL$1)*$AH33:$AO33))) -> 0 | AV33: =MIN(AM33,MAX(0,$AP33-SUMPRODUCT(($AH$1:$AO$1<AM$1)*$AH33:$AO33))) -> 0 | AW33: =MIN(AN33,MAX(0,$AP33-SUMPRODUCT(($AH$1:$AO$1<AN$1)*$AH33:$AO33))) -> 0 | AX33: =MIN(AO33,MAX(0,$AP33-SUMPRODUCT(($AH$1:$AO$1<AO$1)*$AH33:$AO33))) -> 0 | AY33: =ROUND(AH33-AQ33,2) -> 0 | AZ33: =ROUND(AI33-AR33,2) -> 0 | BA33: =ROUND(AJ33-AS33,2) -> 0 | BB33: =ROUND(AK33-AT33,2) -> 8783.97 | BC33: =ROUND(AL33-AU33,2) -> 0 | BD33: =ROUND(AM33-AV33,2) -> 0 | BE33: =ROUND(AN33-AW33,2) -> 0 | BF33: =ROUND(AO33-AX33,2) -> 0 | BG33: =SUM(AY33:BF33) -> 8783.97
A34: 32 | B34: =AY33 -> 0 | C34: =AZ33 -> 0 | D34: =BA33 -> 0 | E34: =BB33 -> 8783.97 | F34: =BC33 -> 0 | G34: =BD33 -> 0 | H34: =BE33 -> 0 | I34: =BF33 -> 0 | J34: =B34*N('Debt Payoff'!D9)/12 -> 0 | K34: =C34*N('Debt Payoff'!D10)/12 -> 0 | L34: =D34*N('Debt Payoff'!D11)/12 -> 0 | M34: =E34*N('Debt Payoff'!D12)/12 -> 40.259862 | N34: =F34*N('Debt Payoff'!D13)/12 -> 0 | O34: =G34*N('Debt Payoff'!D14)/12 -> 0 | P34: =H34*N('Debt Payoff'!D15)/12 -> 0 | Q34: =I34*N('Debt Payoff'!D16)/12 -> 0 | R34: =B34+J34 -> 0 | S34: =C34+K34 -> 0 | T34: =D34+L34 -> 0 | U34: =E34+M34 -> 8824.2299 | V34: =F34+N34 -> 0 | W34: =G34+O34 -> 0 | X34: =H34+P34 -> 0 | Y34: =I34+Q34 -> 0 | Z34: =MIN(R34,N('Debt Payoff'!E9)) -> 0 | AA34: =MIN(S34,N('Debt Payoff'!E10)) -> 0 | AB34: =MIN(T34,N('Debt Payoff'!E11)) -> 0 | AC34: =MIN(U34,N('Debt Payoff'!E12)) -> 160 | AD34: =MIN(V34,N('Debt Payoff'!E13)) -> 0 | AE34: =MIN(W34,N('Debt Payoff'!E14)) -> 0 | AF34: =MIN(X34,N('Debt Payoff'!E15)) -> 0 | AG34: =MIN(Y34,N('Debt Payoff'!E16)) -> 0 | AH34: =R34-Z34 -> 0 | AI34: =S34-AA34 -> 0 | AJ34: =T34-AB34 -> 0 | AK34: =U34-AC34 -> 8664.2299 | AL34: =V34-AD34 -> 0 | AM34: =W34-AE34 -> 0 | AN34: =X34-AF34 -> 0 | AO34: =Y34-AG34 -> 0 | AP34: =MAX(0,'Debt Payoff'!$D$17-SUM(Z34:AG34)) -> 645 | AQ34: =MIN(AH34,MAX(0,$AP34-SUMPRODUCT(($AH$1:$AO$1<AH$1)*$AH34:$AO34))) -> 0 | AR34: =MIN(AI34,MAX(0,$AP34-SUMPRODUCT(($AH$1:$AO$1<AI$1)*$AH34:$AO34))) -> 0 | AS34: =MIN(AJ34,MAX(0,$AP34-SUMPRODUCT(($AH$1:$AO$1<AJ$1)*$AH34:$AO34))) -> 0 | AT34: =MIN(AK34,MAX(0,$AP34-SUMPRODUCT(($AH$1:$AO$1<AK$1)*$AH34:$AO34))) -> 645 | AU34: =MIN(AL34,MAX(0,$AP34-SUMPRODUCT(($AH$1:$AO$1<AL$1)*$AH34:$AO34))) -> 0 | AV34: =MIN(AM34,MAX(0,$AP34-SUMPRODUCT(($AH$1:$AO$1<AM$1)*$AH34:$AO34))) -> 0 | AW34: =MIN(AN34,MAX(0,$AP34-SUMPRODUCT(($AH$1:$AO$1<AN$1)*$AH34:$AO34))) -> 0 | AX34: =MIN(AO34,MAX(0,$AP34-SUMPRODUCT(($AH$1:$AO$1<AO$1)*$AH34:$AO34))) -> 0 | AY34: =ROUND(AH34-AQ34,2) -> 0 | AZ34: =ROUND(AI34-AR34,2) -> 0 | BA34: =ROUND(AJ34-AS34,2) -> 0 | BB34: =ROUND(AK34-AT34,2) -> 8019.23 | BC34: =ROUND(AL34-AU34,2) -> 0 | BD34: =ROUND(AM34-AV34,2) -> 0 | BE34: =ROUND(AN34-AW34,2) -> 0 | BF34: =ROUND(AO34-AX34,2) -> 0 | BG34: =SUM(AY34:BF34) -> 8019.23
A35: 33 | B35: =AY34 -> 0 | C35: =AZ34 -> 0 | D35: =BA34 -> 0 | E35: =BB34 -> 8019.23 | F35: =BC34 -> 0 | G35: =BD34 -> 0 | H35: =BE34 -> 0 | I35: =BF34 -> 0 | J35: =B35*N('Debt Payoff'!D9)/12 -> 0 | K35: =C35*N('Debt Payoff'!D10)/12 -> 0 | L35: =D35*N('Debt Payoff'!D11)/12 -> 0 | M35: =E35*N('Debt Payoff'!D12)/12 -> 36.754804 | N35: =F35*N('Debt Payoff'!D13)/12 -> 0 | O35: =G35*N('Debt Payoff'!D14)/12 -> 0 | P35: =H35*N('Debt Payoff'!D15)/12 -> 0 | Q35: =I35*N('Debt Payoff'!D16)/12 -> 0 | R35: =B35+J35 -> 0 | S35: =C35+K35 -> 0 | T35: =D35+L35 -> 0 | U35: =E35+M35 -> 8055.9848 | V35: =F35+N35 -> 0 | W35: =G35+O35 -> 0 | X35: =H35+P35 -> 0 | Y35: =I35+Q35 -> 0 | Z35: =MIN(R35,N('Debt Payoff'!E9)) -> 0 | AA35: =MIN(S35,N('Debt Payoff'!E10)) -> 0 | AB35: =MIN(T35,N('Debt Payoff'!E11)) -> 0 | AC35: =MIN(U35,N('Debt Payoff'!E12)) -> 160 | AD35: =MIN(V35,N('Debt Payoff'!E13)) -> 0 | AE35: =MIN(W35,N('Debt Payoff'!E14)) -> 0 | AF35: =MIN(X35,N('Debt Payoff'!E15)) -> 0 | AG35: =MIN(Y35,N('Debt Payoff'!E16)) -> 0 | AH35: =R35-Z35 -> 0 | AI35: =S35-AA35 -> 0 | AJ35: =T35-AB35 -> 0 | AK35: =U35-AC35 -> 7895.9848 | AL35: =V35-AD35 -> 0 | AM35: =W35-AE35 -> 0 | AN35: =X35-AF35 -> 0 | AO35: =Y35-AG35 -> 0 | AP35: =MAX(0,'Debt Payoff'!$D$17-SUM(Z35:AG35)) -> 645 | AQ35: =MIN(AH35,MAX(0,$AP35-SUMPRODUCT(($AH$1:$AO$1<AH$1)*$AH35:$AO35))) -> 0 | AR35: =MIN(AI35,MAX(0,$AP35-SUMPRODUCT(($AH$1:$AO$1<AI$1)*$AH35:$AO35))) -> 0 | AS35: =MIN(AJ35,MAX(0,$AP35-SUMPRODUCT(($AH$1:$AO$1<AJ$1)*$AH35:$AO35))) -> 0 | AT35: =MIN(AK35,MAX(0,$AP35-SUMPRODUCT(($AH$1:$AO$1<AK$1)*$AH35:$AO35))) -> 645 | AU35: =MIN(AL35,MAX(0,$AP35-SUMPRODUCT(($AH$1:$AO$1<AL$1)*$AH35:$AO35))) -> 0 | AV35: =MIN(AM35,MAX(0,$AP35-SUMPRODUCT(($AH$1:$AO$1<AM$1)*$AH35:$AO35))) -> 0 | AW35: =MIN(AN35,MAX(0,$AP35-SUMPRODUCT(($AH$1:$AO$1<AN$1)*$AH35:$AO35))) -> 0 | AX35: =MIN(AO35,MAX(0,$AP35-SUMPRODUCT(($AH$1:$AO$1<AO$1)*$AH35:$AO35))) -> 0 | AY35: =ROUND(AH35-AQ35,2) -> 0 | AZ35: =ROUND(AI35-AR35,2) -> 0 | BA35: =ROUND(AJ35-AS35,2) -> 0 | BB35: =ROUND(AK35-AT35,2) -> 7250.98 | BC35: =ROUND(AL35-AU35,2) -> 0 | BD35: =ROUND(AM35-AV35,2) -> 0 | BE35: =ROUND(AN35-AW35,2) -> 0 | BF35: =ROUND(AO35-AX35,2) -> 0 | BG35: =SUM(AY35:BF35) -> 7250.98
A36: 34 | B36: =AY35 -> 0 | C36: =AZ35 -> 0 | D36: =BA35 -> 0 | E36: =BB35 -> 7250.98 | F36: =BC35 -> 0 | G36: =BD35 -> 0 | H36: =BE35 -> 0 | I36: =BF35 -> 0 | J36: =B36*N('Debt Payoff'!D9)/12 -> 0 | K36: =C36*N('Debt Payoff'!D10)/12 -> 0 | L36: =D36*N('Debt Payoff'!D11)/12 -> 0 | M36: =E36*N('Debt Payoff'!D12)/12 -> 33.233658 | N36: =F36*N('Debt Payoff'!D13)/12 -> 0 | O36: =G36*N('Debt Payoff'!D14)/12 -> 0 | P36: =H36*N('Debt Payoff'!D15)/12 -> 0 | Q36: =I36*N('Debt Payoff'!D16)/12 -> 0 | R36: =B36+J36 -> 0 | S36: =C36+K36 -> 0 | T36: =D36+L36 -> 0 | U36: =E36+M36 -> 7284.2137 | V36: =F36+N36 -> 0 | W36: =G36+O36 -> 0 | X36: =H36+P36 -> 0 | Y36: =I36+Q36 -> 0 | Z36: =MIN(R36,N('Debt Payoff'!E9)) -> 0 | AA36: =MIN(S36,N('Debt Payoff'!E10)) -> 0 | AB36: =MIN(T36,N('Debt Payoff'!E11)) -> 0 | AC36: =MIN(U36,N('Debt Payoff'!E12)) -> 160 | AD36: =MIN(V36,N('Debt Payoff'!E13)) -> 0 | AE36: =MIN(W36,N('Debt Payoff'!E14)) -> 0 | AF36: =MIN(X36,N('Debt Payoff'!E15)) -> 0 | AG36: =MIN(Y36,N('Debt Payoff'!E16)) -> 0 | AH36: =R36-Z36 -> 0 | AI36: =S36-AA36 -> 0 | AJ36: =T36-AB36 -> 0 | AK36: =U36-AC36 -> 7124.2137 | AL36: =V36-AD36 -> 0 | AM36: =W36-AE36 -> 0 | AN36: =X36-AF36 -> 0 | AO36: =Y36-AG36 -> 0 | AP36: =MAX(0,'Debt Payoff'!$D$17-SUM(Z36:AG36)) -> 645 | AQ36: =MIN(AH36,MAX(0,$AP36-SUMPRODUCT(($AH$1:$AO$1<AH$1)*$AH36:$AO36))) -> 0 | AR36: =MIN(AI36,MAX(0,$AP36-SUMPRODUCT(($AH$1:$AO$1<AI$1)*$AH36:$AO36))) -> 0 | AS36: =MIN(AJ36,MAX(0,$AP36-SUMPRODUCT(($AH$1:$AO$1<AJ$1)*$AH36:$AO36))) -> 0 | AT36: =MIN(AK36,MAX(0,$AP36-SUMPRODUCT(($AH$1:$AO$1<AK$1)*$AH36:$AO36))) -> 645 | AU36: =MIN(AL36,MAX(0,$AP36-SUMPRODUCT(($AH$1:$AO$1<AL$1)*$AH36:$AO36))) -> 0 | AV36: =MIN(AM36,MAX(0,$AP36-SUMPRODUCT(($AH$1:$AO$1<AM$1)*$AH36:$AO36))) -> 0 | AW36: =MIN(AN36,MAX(0,$AP36-SUMPRODUCT(($AH$1:$AO$1<AN$1)*$AH36:$AO36))) -> 0 | AX36: =MIN(AO36,MAX(0,$AP36-SUMPRODUCT(($AH$1:$AO$1<AO$1)*$AH36:$AO36))) -> 0 | AY36: =ROUND(AH36-AQ36,2) -> 0 | AZ36: =ROUND(AI36-AR36,2) -> 0 | BA36: =ROUND(AJ36-AS36,2) -> 0 | BB36: =ROUND(AK36-AT36,2) -> 6479.21 | BC36: =ROUND(AL36-AU36,2) -> 0 | BD36: =ROUND(AM36-AV36,2) -> 0 | BE36: =ROUND(AN36-AW36,2) -> 0 | BF36: =ROUND(AO36-AX36,2) -> 0 | BG36: =SUM(AY36:BF36) -> 6479.21
A37: 35 | B37: =AY36 -> 0 | C37: =AZ36 -> 0 | D37: =BA36 -> 0 | E37: =BB36 -> 6479.21 | F37: =BC36 -> 0 | G37: =BD36 -> 0 | H37: =BE36 -> 0 | I37: =BF36 -> 0 | J37: =B37*N('Debt Payoff'!D9)/12 -> 0 | K37: =C37*N('Debt Payoff'!D10)/12 -> 0 | L37: =D37*N('Debt Payoff'!D11)/12 -> 0 | M37: =E37*N('Debt Payoff'!D12)/12 -> 29.696379 | N37: =F37*N('Debt Payoff'!D13)/12 -> 0 | O37: =G37*N('Debt Payoff'!D14)/12 -> 0 | P37: =H37*N('Debt Payoff'!D15)/12 -> 0 | Q37: =I37*N('Debt Payoff'!D16)/12 -> 0 | R37: =B37+J37 -> 0 | S37: =C37+K37 -> 0 | T37: =D37+L37 -> 0 | U37: =E37+M37 -> 6508.9064 | V37: =F37+N37 -> 0 | W37: =G37+O37 -> 0 | X37: =H37+P37 -> 0 | Y37: =I37+Q37 -> 0 | Z37: =MIN(R37,N('Debt Payoff'!E9)) -> 0 | AA37: =MIN(S37,N('Debt Payoff'!E10)) -> 0 | AB37: =MIN(T37,N('Debt Payoff'!E11)) -> 0 | AC37: =MIN(U37,N('Debt Payoff'!E12)) -> 160 | AD37: =MIN(V37,N('Debt Payoff'!E13)) -> 0 | AE37: =MIN(W37,N('Debt Payoff'!E14)) -> 0 | AF37: =MIN(X37,N('Debt Payoff'!E15)) -> 0 | AG37: =MIN(Y37,N('Debt Payoff'!E16)) -> 0 | AH37: =R37-Z37 -> 0 | AI37: =S37-AA37 -> 0 | AJ37: =T37-AB37 -> 0 | AK37: =U37-AC37 -> 6348.9064 | AL37: =V37-AD37 -> 0 | AM37: =W37-AE37 -> 0 | AN37: =X37-AF37 -> 0 | AO37: =Y37-AG37 -> 0 | AP37: =MAX(0,'Debt Payoff'!$D$17-SUM(Z37:AG37)) -> 645 | AQ37: =MIN(AH37,MAX(0,$AP37-SUMPRODUCT(($AH$1:$AO$1<AH$1)*$AH37:$AO37))) -> 0 | AR37: =MIN(AI37,MAX(0,$AP37-SUMPRODUCT(($AH$1:$AO$1<AI$1)*$AH37:$AO37))) -> 0 | AS37: =MIN(AJ37,MAX(0,$AP37-SUMPRODUCT(($AH$1:$AO$1<AJ$1)*$AH37:$AO37))) -> 0 | AT37: =MIN(AK37,MAX(0,$AP37-SUMPRODUCT(($AH$1:$AO$1<AK$1)*$AH37:$AO37))) -> 645 | AU37: =MIN(AL37,MAX(0,$AP37-SUMPRODUCT(($AH$1:$AO$1<AL$1)*$AH37:$AO37))) -> 0 | AV37: =MIN(AM37,MAX(0,$AP37-SUMPRODUCT(($AH$1:$AO$1<AM$1)*$AH37:$AO37))) -> 0 | AW37: =MIN(AN37,MAX(0,$AP37-SUMPRODUCT(($AH$1:$AO$1<AN$1)*$AH37:$AO37))) -> 0 | AX37: =MIN(AO37,MAX(0,$AP37-SUMPRODUCT(($AH$1:$AO$1<AO$1)*$AH37:$AO37))) -> 0 | AY37: =ROUND(AH37-AQ37,2) -> 0 | AZ37: =ROUND(AI37-AR37,2) -> 0 | BA37: =ROUND(AJ37-AS37,2) -> 0 | BB37: =ROUND(AK37-AT37,2) -> 5703.91 | BC37: =ROUND(AL37-AU37,2) -> 0 | BD37: =ROUND(AM37-AV37,2) -> 0 | BE37: =ROUND(AN37-AW37,2) -> 0 | BF37: =ROUND(AO37-AX37,2) -> 0 | BG37: =SUM(AY37:BF37) -> 5703.91
A38: 36 | B38: =AY37 -> 0 | C38: =AZ37 -> 0 | D38: =BA37 -> 0 | E38: =BB37 -> 5703.91 | F38: =BC37 -> 0 | G38: =BD37 -> 0 | H38: =BE37 -> 0 | I38: =BF37 -> 0 | J38: =B38*N('Debt Payoff'!D9)/12 -> 0 | K38: =C38*N('Debt Payoff'!D10)/12 -> 0 | L38: =D38*N('Debt Payoff'!D11)/12 -> 0 | M38: =E38*N('Debt Payoff'!D12)/12 -> 26.142921 | N38: =F38*N('Debt Payoff'!D13)/12 -> 0 | O38: =G38*N('Debt Payoff'!D14)/12 -> 0 | P38: =H38*N('Debt Payoff'!D15)/12 -> 0 | Q38: =I38*N('Debt Payoff'!D16)/12 -> 0 | R38: =B38+J38 -> 0 | S38: =C38+K38 -> 0 | T38: =D38+L38 -> 0 | U38: =E38+M38 -> 5730.0529 | V38: =F38+N38 -> 0 | W38: =G38+O38 -> 0 | X38: =H38+P38 -> 0 | Y38: =I38+Q38 -> 0 | Z38: =MIN(R38,N('Debt Payoff'!E9)) -> 0 | AA38: =MIN(S38,N('Debt Payoff'!E10)) -> 0 | AB38: =MIN(T38,N('Debt Payoff'!E11)) -> 0 | AC38: =MIN(U38,N('Debt Payoff'!E12)) -> 160 | AD38: =MIN(V38,N('Debt Payoff'!E13)) -> 0 | AE38: =MIN(W38,N('Debt Payoff'!E14)) -> 0 | AF38: =MIN(X38,N('Debt Payoff'!E15)) -> 0 | AG38: =MIN(Y38,N('Debt Payoff'!E16)) -> 0 | AH38: =R38-Z38 -> 0 | AI38: =S38-AA38 -> 0 | AJ38: =T38-AB38 -> 0 | AK38: =U38-AC38 -> 5570.0529 | AL38: =V38-AD38 -> 0 | AM38: =W38-AE38 -> 0 | AN38: =X38-AF38 -> 0 | AO38: =Y38-AG38 -> 0 | AP38: =MAX(0,'Debt Payoff'!$D$17-SUM(Z38:AG38)) -> 645 | AQ38: =MIN(AH38,MAX(0,$AP38-SUMPRODUCT(($AH$1:$AO$1<AH$1)*$AH38:$AO38))) -> 0 | AR38: =MIN(AI38,MAX(0,$AP38-SUMPRODUCT(($AH$1:$AO$1<AI$1)*$AH38:$AO38))) -> 0 | AS38: =MIN(AJ38,MAX(0,$AP38-SUMPRODUCT(($AH$1:$AO$1<AJ$1)*$AH38:$AO38))) -> 0 | AT38: =MIN(AK38,MAX(0,$AP38-SUMPRODUCT(($AH$1:$AO$1<AK$1)*$AH38:$AO38))) -> 645 | AU38: =MIN(AL38,MAX(0,$AP38-SUMPRODUCT(($AH$1:$AO$1<AL$1)*$AH38:$AO38))) -> 0 | AV38: =MIN(AM38,MAX(0,$AP38-SUMPRODUCT(($AH$1:$AO$1<AM$1)*$AH38:$AO38))) -> 0 | AW38: =MIN(AN38,MAX(0,$AP38-SUMPRODUCT(($AH$1:$AO$1<AN$1)*$AH38:$AO38))) -> 0 | AX38: =MIN(AO38,MAX(0,$AP38-SUMPRODUCT(($AH$1:$AO$1<AO$1)*$AH38:$AO38))) -> 0 | AY38: =ROUND(AH38-AQ38,2) -> 0 | AZ38: =ROUND(AI38-AR38,2) -> 0 | BA38: =ROUND(AJ38-AS38,2) -> 0 | BB38: =ROUND(AK38-AT38,2) -> 4925.05 | BC38: =ROUND(AL38-AU38,2) -> 0 | BD38: =ROUND(AM38-AV38,2) -> 0 | BE38: =ROUND(AN38-AW38,2) -> 0 | BF38: =ROUND(AO38-AX38,2) -> 0 | BG38: =SUM(AY38:BF38) -> 4925.05
A39: 37 | B39: =AY38 -> 0 | C39: =AZ38 -> 0 | D39: =BA38 -> 0 | E39: =BB38 -> 4925.05 | F39: =BC38 -> 0 | G39: =BD38 -> 0 | H39: =BE38 -> 0 | I39: =BF38 -> 0 | J39: =B39*N('Debt Payoff'!D9)/12 -> 0 | K39: =C39*N('Debt Payoff'!D10)/12 -> 0 | L39: =D39*N('Debt Payoff'!D11)/12 -> 0 | M39: =E39*N('Debt Payoff'!D12)/12 -> 22.573146 | N39: =F39*N('Debt Payoff'!D13)/12 -> 0 | O39: =G39*N('Debt Payoff'!D14)/12 -> 0 | P39: =H39*N('Debt Payoff'!D15)/12 -> 0 | Q39: =I39*N('Debt Payoff'!D16)/12 -> 0 | R39: =B39+J39 -> 0 | S39: =C39+K39 -> 0 | T39: =D39+L39 -> 0 | U39: =E39+M39 -> 4947.6231 | V39: =F39+N39 -> 0 | W39: =G39+O39 -> 0 | X39: =H39+P39 -> 0 | Y39: =I39+Q39 -> 0 | Z39: =MIN(R39,N('Debt Payoff'!E9)) -> 0 | AA39: =MIN(S39,N('Debt Payoff'!E10)) -> 0 | AB39: =MIN(T39,N('Debt Payoff'!E11)) -> 0 | AC39: =MIN(U39,N('Debt Payoff'!E12)) -> 160 | AD39: =MIN(V39,N('Debt Payoff'!E13)) -> 0 | AE39: =MIN(W39,N('Debt Payoff'!E14)) -> 0 | AF39: =MIN(X39,N('Debt Payoff'!E15)) -> 0 | AG39: =MIN(Y39,N('Debt Payoff'!E16)) -> 0 | AH39: =R39-Z39 -> 0 | AI39: =S39-AA39 -> 0 | AJ39: =T39-AB39 -> 0 | AK39: =U39-AC39 -> 4787.6231 | AL39: =V39-AD39 -> 0 | AM39: =W39-AE39 -> 0 | AN39: =X39-AF39 -> 0 | AO39: =Y39-AG39 -> 0 | AP39: =MAX(0,'Debt Payoff'!$D$17-SUM(Z39:AG39)) -> 645 | AQ39: =MIN(AH39,MAX(0,$AP39-SUMPRODUCT(($AH$1:$AO$1<AH$1)*$AH39:$AO39))) -> 0 | AR39: =MIN(AI39,MAX(0,$AP39-SUMPRODUCT(($AH$1:$AO$1<AI$1)*$AH39:$AO39))) -> 0 | AS39: =MIN(AJ39,MAX(0,$AP39-SUMPRODUCT(($AH$1:$AO$1<AJ$1)*$AH39:$AO39))) -> 0 | AT39: =MIN(AK39,MAX(0,$AP39-SUMPRODUCT(($AH$1:$AO$1<AK$1)*$AH39:$AO39))) -> 645 | AU39: =MIN(AL39,MAX(0,$AP39-SUMPRODUCT(($AH$1:$AO$1<AL$1)*$AH39:$AO39))) -> 0 | AV39: =MIN(AM39,MAX(0,$AP39-SUMPRODUCT(($AH$1:$AO$1<AM$1)*$AH39:$AO39))) -> 0 | AW39: =MIN(AN39,MAX(0,$AP39-SUMPRODUCT(($AH$1:$AO$1<AN$1)*$AH39:$AO39))) -> 0 | AX39: =MIN(AO39,MAX(0,$AP39-SUMPRODUCT(($AH$1:$AO$1<AO$1)*$AH39:$AO39))) -> 0 | AY39: =ROUND(AH39-AQ39,2) -> 0 | AZ39: =ROUND(AI39-AR39,2) -> 0 | BA39: =ROUND(AJ39-AS39,2) -> 0 | BB39: =ROUND(AK39-AT39,2) -> 4142.62 | BC39: =ROUND(AL39-AU39,2) -> 0 | BD39: =ROUND(AM39-AV39,2) -> 0 | BE39: =ROUND(AN39-AW39,2) -> 0 | BF39: =ROUND(AO39-AX39,2) -> 0 | BG39: =SUM(AY39:BF39) -> 4142.62
A40: 38 | B40: =AY39 -> 0 | C40: =AZ39 -> 0 | D40: =BA39 -> 0 | E40: =BB39 -> 4142.62 | F40: =BC39 -> 0 | G40: =BD39 -> 0 | H40: =BE39 -> 0 | I40: =BF39 -> 0 | J40: =B40*N('Debt Payoff'!D9)/12 -> 0 | K40: =C40*N('Debt Payoff'!D10)/12 -> 0 | L40: =D40*N('Debt Payoff'!D11)/12 -> 0 | M40: =E40*N('Debt Payoff'!D12)/12 -> 18.987008 | N40: =F40*N('Debt Payoff'!D13)/12 -> 0 | O40: =G40*N('Debt Payoff'!D14)/12 -> 0 | P40: =H40*N('Debt Payoff'!D15)/12 -> 0 | Q40: =I40*N('Debt Payoff'!D16)/12 -> 0 | R40: =B40+J40 -> 0 | S40: =C40+K40 -> 0 | T40: =D40+L40 -> 0 | U40: =E40+M40 -> 4161.607 | V40: =F40+N40 -> 0 | W40: =G40+O40 -> 0 | X40: =H40+P40 -> 0 | Y40: =I40+Q40 -> 0 | Z40: =MIN(R40,N('Debt Payoff'!E9)) -> 0 | AA40: =MIN(S40,N('Debt Payoff'!E10)) -> 0 | AB40: =MIN(T40,N('Debt Payoff'!E11)) -> 0 | AC40: =MIN(U40,N('Debt Payoff'!E12)) -> 160 | AD40: =MIN(V40,N('Debt Payoff'!E13)) -> 0 | AE40: =MIN(W40,N('Debt Payoff'!E14)) -> 0 | AF40: =MIN(X40,N('Debt Payoff'!E15)) -> 0 | AG40: =MIN(Y40,N('Debt Payoff'!E16)) -> 0 | AH40: =R40-Z40 -> 0 | AI40: =S40-AA40 -> 0 | AJ40: =T40-AB40 -> 0 | AK40: =U40-AC40 -> 4001.607 | AL40: =V40-AD40 -> 0 | AM40: =W40-AE40 -> 0 | AN40: =X40-AF40 -> 0 | AO40: =Y40-AG40 -> 0 | AP40: =MAX(0,'Debt Payoff'!$D$17-SUM(Z40:AG40)) -> 645 | AQ40: =MIN(AH40,MAX(0,$AP40-SUMPRODUCT(($AH$1:$AO$1<AH$1)*$AH40:$AO40))) -> 0 | AR40: =MIN(AI40,MAX(0,$AP40-SUMPRODUCT(($AH$1:$AO$1<AI$1)*$AH40:$AO40))) -> 0 | AS40: =MIN(AJ40,MAX(0,$AP40-SUMPRODUCT(($AH$1:$AO$1<AJ$1)*$AH40:$AO40))) -> 0 | AT40: =MIN(AK40,MAX(0,$AP40-SUMPRODUCT(($AH$1:$AO$1<AK$1)*$AH40:$AO40))) -> 645 | AU40: =MIN(AL40,MAX(0,$AP40-SUMPRODUCT(($AH$1:$AO$1<AL$1)*$AH40:$AO40))) -> 0 | AV40: =MIN(AM40,MAX(0,$AP40-SUMPRODUCT(($AH$1:$AO$1<AM$1)*$AH40:$AO40))) -> 0 | AW40: =MIN(AN40,MAX(0,$AP40-SUMPRODUCT(($AH$1:$AO$1<AN$1)*$AH40:$AO40))) -> 0 | AX40: =MIN(AO40,MAX(0,$AP40-SUMPRODUCT(($AH$1:$AO$1<AO$1)*$AH40:$AO40))) -> 0 | AY40: =ROUND(AH40-AQ40,2) -> 0 | AZ40: =ROUND(AI40-AR40,2) -> 0 | BA40: =ROUND(AJ40-AS40,2) -> 0 | BB40: =ROUND(AK40-AT40,2) -> 3356.61 | BC40: =ROUND(AL40-AU40,2) -> 0 | BD40: =ROUND(AM40-AV40,2) -> 0 | BE40: =ROUND(AN40-AW40,2) -> 0 | BF40: =ROUND(AO40-AX40,2) -> 0 | BG40: =SUM(AY40:BF40) -> 3356.61
A41: 39 | B41: =AY40 -> 0 | C41: =AZ40 -> 0 | D41: =BA40 -> 0 | E41: =BB40 -> 3356.61 | F41: =BC40 -> 0 | G41: =BD40 -> 0 | H41: =BE40 -> 0 | I41: =BF40 -> 0 | J41: =B41*N('Debt Payoff'!D9)/12 -> 0 | K41: =C41*N('Debt Payoff'!D10)/12 -> 0 | L41: =D41*N('Debt Payoff'!D11)/12 -> 0 | M41: =E41*N('Debt Payoff'!D12)/12 -> 15.384462 | N41: =F41*N('Debt Payoff'!D13)/12 -> 0 | O41: =G41*N('Debt Payoff'!D14)/12 -> 0 | P41: =H41*N('Debt Payoff'!D15)/12 -> 0 | Q41: =I41*N('Debt Payoff'!D16)/12 -> 0 | R41: =B41+J41 -> 0 | S41: =C41+K41 -> 0 | T41: =D41+L41 -> 0 | U41: =E41+M41 -> 3371.9945 | V41: =F41+N41 -> 0 | W41: =G41+O41 -> 0 | X41: =H41+P41 -> 0 | Y41: =I41+Q41 -> 0 | Z41: =MIN(R41,N('Debt Payoff'!E9)) -> 0 | AA41: =MIN(S41,N('Debt Payoff'!E10)) -> 0 | AB41: =MIN(T41,N('Debt Payoff'!E11)) -> 0 | AC41: =MIN(U41,N('Debt Payoff'!E12)) -> 160 | AD41: =MIN(V41,N('Debt Payoff'!E13)) -> 0 | AE41: =MIN(W41,N('Debt Payoff'!E14)) -> 0 | AF41: =MIN(X41,N('Debt Payoff'!E15)) -> 0 | AG41: =MIN(Y41,N('Debt Payoff'!E16)) -> 0 | AH41: =R41-Z41 -> 0 | AI41: =S41-AA41 -> 0 | AJ41: =T41-AB41 -> 0 | AK41: =U41-AC41 -> 3211.9945 | AL41: =V41-AD41 -> 0 | AM41: =W41-AE41 -> 0 | AN41: =X41-AF41 -> 0 | AO41: =Y41-AG41 -> 0 | AP41: =MAX(0,'Debt Payoff'!$D$17-SUM(Z41:AG41)) -> 645 | AQ41: =MIN(AH41,MAX(0,$AP41-SUMPRODUCT(($AH$1:$AO$1<AH$1)*$AH41:$AO41))) -> 0 | AR41: =MIN(AI41,MAX(0,$AP41-SUMPRODUCT(($AH$1:$AO$1<AI$1)*$AH41:$AO41))) -> 0 | AS41: =MIN(AJ41,MAX(0,$AP41-SUMPRODUCT(($AH$1:$AO$1<AJ$1)*$AH41:$AO41))) -> 0 | AT41: =MIN(AK41,MAX(0,$AP41-SUMPRODUCT(($AH$1:$AO$1<AK$1)*$AH41:$AO41))) -> 645 | AU41: =MIN(AL41,MAX(0,$AP41-SUMPRODUCT(($AH$1:$AO$1<AL$1)*$AH41:$AO41))) -> 0 | AV41: =MIN(AM41,MAX(0,$AP41-SUMPRODUCT(($AH$1:$AO$1<AM$1)*$AH41:$AO41))) -> 0 | AW41: =MIN(AN41,MAX(0,$AP41-SUMPRODUCT(($AH$1:$AO$1<AN$1)*$AH41:$AO41))) -> 0 | AX41: =MIN(AO41,MAX(0,$AP41-SUMPRODUCT(($AH$1:$AO$1<AO$1)*$AH41:$AO41))) -> 0 | AY41: =ROUND(AH41-AQ41,2) -> 0 | AZ41: =ROUND(AI41-AR41,2) -> 0 | BA41: =ROUND(AJ41-AS41,2) -> 0 | BB41: =ROUND(AK41-AT41,2) -> 2566.99 | BC41: =ROUND(AL41-AU41,2) -> 0 | BD41: =ROUND(AM41-AV41,2) -> 0 | BE41: =ROUND(AN41-AW41,2) -> 0 | BF41: =ROUND(AO41-AX41,2) -> 0 | BG41: =SUM(AY41:BF41) -> 2566.99
A42: 40 | B42: =AY41 -> 0 | C42: =AZ41 -> 0 | D42: =BA41 -> 0 | E42: =BB41 -> 2566.99 | F42: =BC41 -> 0 | G42: =BD41 -> 0 | H42: =BE41 -> 0 | I42: =BF41 -> 0 | J42: =B42*N('Debt Payoff'!D9)/12 -> 0 | K42: =C42*N('Debt Payoff'!D10)/12 -> 0 | L42: =D42*N('Debt Payoff'!D11)/12 -> 0 | M42: =E42*N('Debt Payoff'!D12)/12 -> 11.765371 | N42: =F42*N('Debt Payoff'!D13)/12 -> 0 | O42: =G42*N('Debt Payoff'!D14)/12 -> 0 | P42: =H42*N('Debt Payoff'!D15)/12 -> 0 | Q42: =I42*N('Debt Payoff'!D16)/12 -> 0 | R42: =B42+J42 -> 0 | S42: =C42+K42 -> 0 | T42: =D42+L42 -> 0 | U42: =E42+M42 -> 2578.7554 | V42: =F42+N42 -> 0 | W42: =G42+O42 -> 0 | X42: =H42+P42 -> 0 | Y42: =I42+Q42 -> 0 | Z42: =MIN(R42,N('Debt Payoff'!E9)) -> 0 | AA42: =MIN(S42,N('Debt Payoff'!E10)) -> 0 | AB42: =MIN(T42,N('Debt Payoff'!E11)) -> 0 | AC42: =MIN(U42,N('Debt Payoff'!E12)) -> 160 | AD42: =MIN(V42,N('Debt Payoff'!E13)) -> 0 | AE42: =MIN(W42,N('Debt Payoff'!E14)) -> 0 | AF42: =MIN(X42,N('Debt Payoff'!E15)) -> 0 | AG42: =MIN(Y42,N('Debt Payoff'!E16)) -> 0 | AH42: =R42-Z42 -> 0 | AI42: =S42-AA42 -> 0 | AJ42: =T42-AB42 -> 0 | AK42: =U42-AC42 -> 2418.7554 | AL42: =V42-AD42 -> 0 | AM42: =W42-AE42 -> 0 | AN42: =X42-AF42 -> 0 | AO42: =Y42-AG42 -> 0 | AP42: =MAX(0,'Debt Payoff'!$D$17-SUM(Z42:AG42)) -> 645 | AQ42: =MIN(AH42,MAX(0,$AP42-SUMPRODUCT(($AH$1:$AO$1<AH$1)*$AH42:$AO42))) -> 0 | AR42: =MIN(AI42,MAX(0,$AP42-SUMPRODUCT(($AH$1:$AO$1<AI$1)*$AH42:$AO42))) -> 0 | AS42: =MIN(AJ42,MAX(0,$AP42-SUMPRODUCT(($AH$1:$AO$1<AJ$1)*$AH42:$AO42))) -> 0 | AT42: =MIN(AK42,MAX(0,$AP42-SUMPRODUCT(($AH$1:$AO$1<AK$1)*$AH42:$AO42))) -> 645 | AU42: =MIN(AL42,MAX(0,$AP42-SUMPRODUCT(($AH$1:$AO$1<AL$1)*$AH42:$AO42))) -> 0 | AV42: =MIN(AM42,MAX(0,$AP42-SUMPRODUCT(($AH$1:$AO$1<AM$1)*$AH42:$AO42))) -> 0 | AW42: =MIN(AN42,MAX(0,$AP42-SUMPRODUCT(($AH$1:$AO$1<AN$1)*$AH42:$AO42))) -> 0 | AX42: =MIN(AO42,MAX(0,$AP42-SUMPRODUCT(($AH$1:$AO$1<AO$1)*$AH42:$AO42))) -> 0 | AY42: =ROUND(AH42-AQ42,2) -> 0 | AZ42: =ROUND(AI42-AR42,2) -> 0 | BA42: =ROUND(AJ42-AS42,2) -> 0 | BB42: =ROUND(AK42-AT42,2) -> 1773.76 | BC42: =ROUND(AL42-AU42,2) -> 0 | BD42: =ROUND(AM42-AV42,2) -> 0 | BE42: =ROUND(AN42-AW42,2) -> 0 | BF42: =ROUND(AO42-AX42,2) -> 0 | BG42: =SUM(AY42:BF42) -> 1773.76
A43: 41 | B43: =AY42 -> 0 | C43: =AZ42 -> 0 | D43: =BA42 -> 0 | E43: =BB42 -> 1773.76 | F43: =BC42 -> 0 | G43: =BD42 -> 0 | H43: =BE42 -> 0 | I43: =BF42 -> 0 | J43: =B43*N('Debt Payoff'!D9)/12 -> 0 | K43: =C43*N('Debt Payoff'!D10)/12 -> 0 | L43: =D43*N('Debt Payoff'!D11)/12 -> 0 | M43: =E43*N('Debt Payoff'!D12)/12 -> 8.1297333 | N43: =F43*N('Debt Payoff'!D13)/12 -> 0 | O43: =G43*N('Debt Payoff'!D14)/12 -> 0 | P43: =H43*N('Debt Payoff'!D15)/12 -> 0 | Q43: =I43*N('Debt Payoff'!D16)/12 -> 0 | R43: =B43+J43 -> 0 | S43: =C43+K43 -> 0 | T43: =D43+L43 -> 0 | U43: =E43+M43 -> 1781.8897 | V43: =F43+N43 -> 0 | W43: =G43+O43 -> 0 | X43: =H43+P43 -> 0 | Y43: =I43+Q43 -> 0 | Z43: =MIN(R43,N('Debt Payoff'!E9)) -> 0 | AA43: =MIN(S43,N('Debt Payoff'!E10)) -> 0 | AB43: =MIN(T43,N('Debt Payoff'!E11)) -> 0 | AC43: =MIN(U43,N('Debt Payoff'!E12)) -> 160 | AD43: =MIN(V43,N('Debt Payoff'!E13)) -> 0 | AE43: =MIN(W43,N('Debt Payoff'!E14)) -> 0 | AF43: =MIN(X43,N('Debt Payoff'!E15)) -> 0 | AG43: =MIN(Y43,N('Debt Payoff'!E16)) -> 0 | AH43: =R43-Z43 -> 0 | AI43: =S43-AA43 -> 0 | AJ43: =T43-AB43 -> 0 | AK43: =U43-AC43 -> 1621.8897 | AL43: =V43-AD43 -> 0 | AM43: =W43-AE43 -> 0 | AN43: =X43-AF43 -> 0 | AO43: =Y43-AG43 -> 0 | AP43: =MAX(0,'Debt Payoff'!$D$17-SUM(Z43:AG43)) -> 645 | AQ43: =MIN(AH43,MAX(0,$AP43-SUMPRODUCT(($AH$1:$AO$1<AH$1)*$AH43:$AO43))) -> 0 | AR43: =MIN(AI43,MAX(0,$AP43-SUMPRODUCT(($AH$1:$AO$1<AI$1)*$AH43:$AO43))) -> 0 | AS43: =MIN(AJ43,MAX(0,$AP43-SUMPRODUCT(($AH$1:$AO$1<AJ$1)*$AH43:$AO43))) -> 0 | AT43: =MIN(AK43,MAX(0,$AP43-SUMPRODUCT(($AH$1:$AO$1<AK$1)*$AH43:$AO43))) -> 645 | AU43: =MIN(AL43,MAX(0,$AP43-SUMPRODUCT(($AH$1:$AO$1<AL$1)*$AH43:$AO43))) -> 0 | AV43: =MIN(AM43,MAX(0,$AP43-SUMPRODUCT(($AH$1:$AO$1<AM$1)*$AH43:$AO43))) -> 0 | AW43: =MIN(AN43,MAX(0,$AP43-SUMPRODUCT(($AH$1:$AO$1<AN$1)*$AH43:$AO43))) -> 0 | AX43: =MIN(AO43,MAX(0,$AP43-SUMPRODUCT(($AH$1:$AO$1<AO$1)*$AH43:$AO43))) -> 0 | AY43: =ROUND(AH43-AQ43,2) -> 0 | AZ43: =ROUND(AI43-AR43,2) -> 0 | BA43: =ROUND(AJ43-AS43,2) -> 0 | BB43: =ROUND(AK43-AT43,2) -> 976.89 | BC43: =ROUND(AL43-AU43,2) -> 0 | BD43: =ROUND(AM43-AV43,2) -> 0 | BE43: =ROUND(AN43-AW43,2) -> 0 | BF43: =ROUND(AO43-AX43,2) -> 0 | BG43: =SUM(AY43:BF43) -> 976.89
A44: 42 | B44: =AY43 -> 0 | C44: =AZ43 -> 0 | D44: =BA43 -> 0 | E44: =BB43 -> 976.89 | F44: =BC43 -> 0 | G44: =BD43 -> 0 | H44: =BE43 -> 0 | I44: =BF43 -> 0 | J44: =B44*N('Debt Payoff'!D9)/12 -> 0 | K44: =C44*N('Debt Payoff'!D10)/12 -> 0 | L44: =D44*N('Debt Payoff'!D11)/12 -> 0 | M44: =E44*N('Debt Payoff'!D12)/12 -> 4.4774125 | N44: =F44*N('Debt Payoff'!D13)/12 -> 0 | O44: =G44*N('Debt Payoff'!D14)/12 -> 0 | P44: =H44*N('Debt Payoff'!D15)/12 -> 0 | Q44: =I44*N('Debt Payoff'!D16)/12 -> 0 | R44: =B44+J44 -> 0 | S44: =C44+K44 -> 0 | T44: =D44+L44 -> 0 | U44: =E44+M44 -> 981.36741 | V44: =F44+N44 -> 0 | W44: =G44+O44 -> 0 | X44: =H44+P44 -> 0 | Y44: =I44+Q44 -> 0 | Z44: =MIN(R44,N('Debt Payoff'!E9)) -> 0 | AA44: =MIN(S44,N('Debt Payoff'!E10)) -> 0 | AB44: =MIN(T44,N('Debt Payoff'!E11)) -> 0 | AC44: =MIN(U44,N('Debt Payoff'!E12)) -> 160 | AD44: =MIN(V44,N('Debt Payoff'!E13)) -> 0 | AE44: =MIN(W44,N('Debt Payoff'!E14)) -> 0 | AF44: =MIN(X44,N('Debt Payoff'!E15)) -> 0 | AG44: =MIN(Y44,N('Debt Payoff'!E16)) -> 0 | AH44: =R44-Z44 -> 0 | AI44: =S44-AA44 -> 0 | AJ44: =T44-AB44 -> 0 | AK44: =U44-AC44 -> 821.36741 | AL44: =V44-AD44 -> 0 | AM44: =W44-AE44 -> 0 | AN44: =X44-AF44 -> 0 | AO44: =Y44-AG44 -> 0 | AP44: =MAX(0,'Debt Payoff'!$D$17-SUM(Z44:AG44)) -> 645 | AQ44: =MIN(AH44,MAX(0,$AP44-SUMPRODUCT(($AH$1:$AO$1<AH$1)*$AH44:$AO44))) -> 0 | AR44: =MIN(AI44,MAX(0,$AP44-SUMPRODUCT(($AH$1:$AO$1<AI$1)*$AH44:$AO44))) -> 0 | AS44: =MIN(AJ44,MAX(0,$AP44-SUMPRODUCT(($AH$1:$AO$1<AJ$1)*$AH44:$AO44))) -> 0 | AT44: =MIN(AK44,MAX(0,$AP44-SUMPRODUCT(($AH$1:$AO$1<AK$1)*$AH44:$AO44))) -> 645 | AU44: =MIN(AL44,MAX(0,$AP44-SUMPRODUCT(($AH$1:$AO$1<AL$1)*$AH44:$AO44))) -> 0 | AV44: =MIN(AM44,MAX(0,$AP44-SUMPRODUCT(($AH$1:$AO$1<AM$1)*$AH44:$AO44))) -> 0 | AW44: =MIN(AN44,MAX(0,$AP44-SUMPRODUCT(($AH$1:$AO$1<AN$1)*$AH44:$AO44))) -> 0 | AX44: =MIN(AO44,MAX(0,$AP44-SUMPRODUCT(($AH$1:$AO$1<AO$1)*$AH44:$AO44))) -> 0 | AY44: =ROUND(AH44-AQ44,2) -> 0 | AZ44: =ROUND(AI44-AR44,2) -> 0 | BA44: =ROUND(AJ44-AS44,2) -> 0 | BB44: =ROUND(AK44-AT44,2) -> 176.37 | BC44: =ROUND(AL44-AU44,2) -> 0 | BD44: =ROUND(AM44-AV44,2) -> 0 | BE44: =ROUND(AN44-AW44,2) -> 0 | BF44: =ROUND(AO44-AX44,2) -> 0 | BG44: =SUM(AY44:BF44) -> 176.37
A45: 43 | B45: =AY44 -> 0 | C45: =AZ44 -> 0 | D45: =BA44 -> 0 | E45: =BB44 -> 176.37 | F45: =BC44 -> 0 | G45: =BD44 -> 0 | H45: =BE44 -> 0 | I45: =BF44 -> 0 | J45: =B45*N('Debt Payoff'!D9)/12 -> 0 | K45: =C45*N('Debt Payoff'!D10)/12 -> 0 | L45: =D45*N('Debt Payoff'!D11)/12 -> 0 | M45: =E45*N('Debt Payoff'!D12)/12 -> 0.8083625 | N45: =F45*N('Debt Payoff'!D13)/12 -> 0 | O45: =G45*N('Debt Payoff'!D14)/12 -> 0 | P45: =H45*N('Debt Payoff'!D15)/12 -> 0 | Q45: =I45*N('Debt Payoff'!D16)/12 -> 0 | R45: =B45+J45 -> 0 | S45: =C45+K45 -> 0 | T45: =D45+L45 -> 0 | U45: =E45+M45 -> 177.17836 | V45: =F45+N45 -> 0 | W45: =G45+O45 -> 0 | X45: =H45+P45 -> 0 | Y45: =I45+Q45 -> 0 | Z45: =MIN(R45,N('Debt Payoff'!E9)) -> 0 | AA45: =MIN(S45,N('Debt Payoff'!E10)) -> 0 | AB45: =MIN(T45,N('Debt Payoff'!E11)) -> 0 | AC45: =MIN(U45,N('Debt Payoff'!E12)) -> 160 | AD45: =MIN(V45,N('Debt Payoff'!E13)) -> 0 | AE45: =MIN(W45,N('Debt Payoff'!E14)) -> 0 | AF45: =MIN(X45,N('Debt Payoff'!E15)) -> 0 | AG45: =MIN(Y45,N('Debt Payoff'!E16)) -> 0 | AH45: =R45-Z45 -> 0 | AI45: =S45-AA45 -> 0 | AJ45: =T45-AB45 -> 0 | AK45: =U45-AC45 -> 17.178362 | AL45: =V45-AD45 -> 0 | AM45: =W45-AE45 -> 0 | AN45: =X45-AF45 -> 0 | AO45: =Y45-AG45 -> 0 | AP45: =MAX(0,'Debt Payoff'!$D$17-SUM(Z45:AG45)) -> 645 | AQ45: =MIN(AH45,MAX(0,$AP45-SUMPRODUCT(($AH$1:$AO$1<AH$1)*$AH45:$AO45))) -> 0 | AR45: =MIN(AI45,MAX(0,$AP45-SUMPRODUCT(($AH$1:$AO$1<AI$1)*$AH45:$AO45))) -> 0 | AS45: =MIN(AJ45,MAX(0,$AP45-SUMPRODUCT(($AH$1:$AO$1<AJ$1)*$AH45:$AO45))) -> 0 | AT45: =MIN(AK45,MAX(0,$AP45-SUMPRODUCT(($AH$1:$AO$1<AK$1)*$AH45:$AO45))) -> 17.178362 | AU45: =MIN(AL45,MAX(0,$AP45-SUMPRODUCT(($AH$1:$AO$1<AL$1)*$AH45:$AO45))) -> 0 | AV45: =MIN(AM45,MAX(0,$AP45-SUMPRODUCT(($AH$1:$AO$1<AM$1)*$AH45:$AO45))) -> 0 | AW45: =MIN(AN45,MAX(0,$AP45-SUMPRODUCT(($AH$1:$AO$1<AN$1)*$AH45:$AO45))) -> 0 | AX45: =MIN(AO45,MAX(0,$AP45-SUMPRODUCT(($AH$1:$AO$1<AO$1)*$AH45:$AO45))) -> 0 | AY45: =ROUND(AH45-AQ45,2) -> 0 | AZ45: =ROUND(AI45-AR45,2) -> 0 | BA45: =ROUND(AJ45-AS45,2) -> 0 | BB45: =ROUND(AK45-AT45,2) -> 0 | BC45: =ROUND(AL45-AU45,2) -> 0 | BD45: =ROUND(AM45-AV45,2) -> 0 | BE45: =ROUND(AN45-AW45,2) -> 0 | BF45: =ROUND(AO45-AX45,2) -> 0 | BG45: =SUM(AY45:BF45) -> 0
A46: 44 | B46: =AY45 -> 0 | C46: =AZ45 -> 0 | D46: =BA45 -> 0 | E46: =BB45 -> 0 | F46: =BC45 -> 0 | G46: =BD45 -> 0 | H46: =BE45 -> 0 | I46: =BF45 -> 0 | J46: =B46*N('Debt Payoff'!D9)/12 -> 0 | K46: =C46*N('Debt Payoff'!D10)/12 -> 0 | L46: =D46*N('Debt Payoff'!D11)/12 -> 0 | M46: =E46*N('Debt Payoff'!D12)/12 -> 0 | N46: =F46*N('Debt Payoff'!D13)/12 -> 0 | O46: =G46*N('Debt Payoff'!D14)/12 -> 0 | P46: =H46*N('Debt Payoff'!D15)/12 -> 0 | Q46: =I46*N('Debt Payoff'!D16)/12 -> 0 | R46: =B46+J46 -> 0 | S46: =C46+K46 -> 0 | T46: =D46+L46 -> 0 | U46: =E46+M46 -> 0 | V46: =F46+N46 -> 0 | W46: =G46+O46 -> 0 | X46: =H46+P46 -> 0 | Y46: =I46+Q46 -> 0 | Z46: =MIN(R46,N('Debt Payoff'!E9)) -> 0 | AA46: =MIN(S46,N('Debt Payoff'!E10)) -> 0 | AB46: =MIN(T46,N('Debt Payoff'!E11)) -> 0 | AC46: =MIN(U46,N('Debt Payoff'!E12)) -> 0 | AD46: =MIN(V46,N('Debt Payoff'!E13)) -> 0 | AE46: =MIN(W46,N('Debt Payoff'!E14)) -> 0 | AF46: =MIN(X46,N('Debt Payoff'!E15)) -> 0 | AG46: =MIN(Y46,N('Debt Payoff'!E16)) -> 0 | AH46: =R46-Z46 -> 0 | AI46: =S46-AA46 -> 0 | AJ46: =T46-AB46 -> 0 | AK46: =U46-AC46 -> 0 | AL46: =V46-AD46 -> 0 | AM46: =W46-AE46 -> 0 | AN46: =X46-AF46 -> 0 | AO46: =Y46-AG46 -> 0 | AP46: =MAX(0,'Debt Payoff'!$D$17-SUM(Z46:AG46)) -> 805 | AQ46: =MIN(AH46,MAX(0,$AP46-SUMPRODUCT(($AH$1:$AO$1<AH$1)*$AH46:$AO46))) -> 0 | AR46: =MIN(AI46,MAX(0,$AP46-SUMPRODUCT(($AH$1:$AO$1<AI$1)*$AH46:$AO46))) -> 0 | AS46: =MIN(AJ46,MAX(0,$AP46-SUMPRODUCT(($AH$1:$AO$1<AJ$1)*$AH46:$AO46))) -> 0 | AT46: =MIN(AK46,MAX(0,$AP46-SUMPRODUCT(($AH$1:$AO$1<AK$1)*$AH46:$AO46))) -> 0 | AU46: =MIN(AL46,MAX(0,$AP46-SUMPRODUCT(($AH$1:$AO$1<AL$1)*$AH46:$AO46))) -> 0 | AV46: =MIN(AM46,MAX(0,$AP46-SUMPRODUCT(($AH$1:$AO$1<AM$1)*$AH46:$AO46))) -> 0 | AW46: =MIN(AN46,MAX(0,$AP46-SUMPRODUCT(($AH$1:$AO$1<AN$1)*$AH46:$AO46))) -> 0 | AX46: =MIN(AO46,MAX(0,$AP46-SUMPRODUCT(($AH$1:$AO$1<AO$1)*$AH46:$AO46))) -> 0 | AY46: =ROUND(AH46-AQ46,2) -> 0 | AZ46: =ROUND(AI46-AR46,2) -> 0 | BA46: =ROUND(AJ46-AS46,2) -> 0 | BB46: =ROUND(AK46-AT46,2) -> 0 | BC46: =ROUND(AL46-AU46,2) -> 0 | BD46: =ROUND(AM46-AV46,2) -> 0 | BE46: =ROUND(AN46-AW46,2) -> 0 | BF46: =ROUND(AO46-AX46,2) -> 0 | BG46: =SUM(AY46:BF46) -> 0
A47: 45 | B47: =AY46 -> 0 | C47: =AZ46 -> 0 | D47: =BA46 -> 0 | E47: =BB46 -> 0 | F47: =BC46 -> 0 | G47: =BD46 -> 0 | H47: =BE46 -> 0 | I47: =BF46 -> 0 | J47: =B47*N('Debt Payoff'!D9)/12 -> 0 | K47: =C47*N('Debt Payoff'!D10)/12 -> 0 | L47: =D47*N('Debt Payoff'!D11)/12 -> 0 | M47: =E47*N('Debt Payoff'!D12)/12 -> 0 | N47: =F47*N('Debt Payoff'!D13)/12 -> 0 | O47: =G47*N('Debt Payoff'!D14)/12 -> 0 | P47: =H47*N('Debt Payoff'!D15)/12 -> 0 | Q47: =I47*N('Debt Payoff'!D16)/12 -> 0 | R47: =B47+J47 -> 0 | S47: =C47+K47 -> 0 | T47: =D47+L47 -> 0 | U47: =E47+M47 -> 0 | V47: =F47+N47 -> 0 | W47: =G47+O47 -> 0 | X47: =H47+P47 -> 0 | Y47: =I47+Q47 -> 0 | Z47: =MIN(R47,N('Debt Payoff'!E9)) -> 0 | AA47: =MIN(S47,N('Debt Payoff'!E10)) -> 0 | AB47: =MIN(T47,N('Debt Payoff'!E11)) -> 0 | AC47: =MIN(U47,N('Debt Payoff'!E12)) -> 0 | AD47: =MIN(V47,N('Debt Payoff'!E13)) -> 0 | AE47: =MIN(W47,N('Debt Payoff'!E14)) -> 0 | AF47: =MIN(X47,N('Debt Payoff'!E15)) -> 0 | AG47: =MIN(Y47,N('Debt Payoff'!E16)) -> 0 | AH47: =R47-Z47 -> 0 | AI47: =S47-AA47 -> 0 | AJ47: =T47-AB47 -> 0 | AK47: =U47-AC47 -> 0 | AL47: =V47-AD47 -> 0 | AM47: =W47-AE47 -> 0 | AN47: =X47-AF47 -> 0 | AO47: =Y47-AG47 -> 0 | AP47: =MAX(0,'Debt Payoff'!$D$17-SUM(Z47:AG47)) -> 805 | AQ47: =MIN(AH47,MAX(0,$AP47-SUMPRODUCT(($AH$1:$AO$1<AH$1)*$AH47:$AO47))) -> 0 | AR47: =MIN(AI47,MAX(0,$AP47-SUMPRODUCT(($AH$1:$AO$1<AI$1)*$AH47:$AO47))) -> 0 | AS47: =MIN(AJ47,MAX(0,$AP47-SUMPRODUCT(($AH$1:$AO$1<AJ$1)*$AH47:$AO47))) -> 0 | AT47: =MIN(AK47,MAX(0,$AP47-SUMPRODUCT(($AH$1:$AO$1<AK$1)*$AH47:$AO47))) -> 0 | AU47: =MIN(AL47,MAX(0,$AP47-SUMPRODUCT(($AH$1:$AO$1<AL$1)*$AH47:$AO47))) -> 0 | AV47: =MIN(AM47,MAX(0,$AP47-SUMPRODUCT(($AH$1:$AO$1<AM$1)*$AH47:$AO47))) -> 0 | AW47: =MIN(AN47,MAX(0,$AP47-SUMPRODUCT(($AH$1:$AO$1<AN$1)*$AH47:$AO47))) -> 0 | AX47: =MIN(AO47,MAX(0,$AP47-SUMPRODUCT(($AH$1:$AO$1<AO$1)*$AH47:$AO47))) -> 0 | AY47: =ROUND(AH47-AQ47,2) -> 0 | AZ47: =ROUND(AI47-AR47,2) -> 0 | BA47: =ROUND(AJ47-AS47,2) -> 0 | BB47: =ROUND(AK47-AT47,2) -> 0 | BC47: =ROUND(AL47-AU47,2) -> 0 | BD47: =ROUND(AM47-AV47,2) -> 0 | BE47: =ROUND(AN47-AW47,2) -> 0 | BF47: =ROUND(AO47-AX47,2) -> 0 | BG47: =SUM(AY47:BF47) -> 0
A48: 46 | B48: =AY47 -> 0 | C48: =AZ47 -> 0 | D48: =BA47 -> 0 | E48: =BB47 -> 0 | F48: =BC47 -> 0 | G48: =BD47 -> 0 | H48: =BE47 -> 0 | I48: =BF47 -> 0 | J48: =B48*N('Debt Payoff'!D9)/12 -> 0 | K48: =C48*N('Debt Payoff'!D10)/12 -> 0 | L48: =D48*N('Debt Payoff'!D11)/12 -> 0 | M48: =E48*N('Debt Payoff'!D12)/12 -> 0 | N48: =F48*N('Debt Payoff'!D13)/12 -> 0 | O48: =G48*N('Debt Payoff'!D14)/12 -> 0 | P48: =H48*N('Debt Payoff'!D15)/12 -> 0 | Q48: =I48*N('Debt Payoff'!D16)/12 -> 0 | R48: =B48+J48 -> 0 | S48: =C48+K48 -> 0 | T48: =D48+L48 -> 0 | U48: =E48+M48 -> 0 | V48: =F48+N48 -> 0 | W48: =G48+O48 -> 0 | X48: =H48+P48 -> 0 | Y48: =I48+Q48 -> 0 | Z48: =MIN(R48,N('Debt Payoff'!E9)) -> 0 | AA48: =MIN(S48,N('Debt Payoff'!E10)) -> 0 | AB48: =MIN(T48,N('Debt Payoff'!E11)) -> 0 | AC48: =MIN(U48,N('Debt Payoff'!E12)) -> 0 | AD48: =MIN(V48,N('Debt Payoff'!E13)) -> 0 | AE48: =MIN(W48,N('Debt Payoff'!E14)) -> 0 | AF48: =MIN(X48,N('Debt Payoff'!E15)) -> 0 | AG48: =MIN(Y48,N('Debt Payoff'!E16)) -> 0 | AH48: =R48-Z48 -> 0 | AI48: =S48-AA48 -> 0 | AJ48: =T48-AB48 -> 0 | AK48: =U48-AC48 -> 0 | AL48: =V48-AD48 -> 0 | AM48: =W48-AE48 -> 0 | AN48: =X48-AF48 -> 0 | AO48: =Y48-AG48 -> 0 | AP48: =MAX(0,'Debt Payoff'!$D$17-SUM(Z48:AG48)) -> 805 | AQ48: =MIN(AH48,MAX(0,$AP48-SUMPRODUCT(($AH$1:$AO$1<AH$1)*$AH48:$AO48))) -> 0 | AR48: =MIN(AI48,MAX(0,$AP48-SUMPRODUCT(($AH$1:$AO$1<AI$1)*$AH48:$AO48))) -> 0 | AS48: =MIN(AJ48,MAX(0,$AP48-SUMPRODUCT(($AH$1:$AO$1<AJ$1)*$AH48:$AO48))) -> 0 | AT48: =MIN(AK48,MAX(0,$AP48-SUMPRODUCT(($AH$1:$AO$1<AK$1)*$AH48:$AO48))) -> 0 | AU48: =MIN(AL48,MAX(0,$AP48-SUMPRODUCT(($AH$1:$AO$1<AL$1)*$AH48:$AO48))) -> 0 | AV48: =MIN(AM48,MAX(0,$AP48-SUMPRODUCT(($AH$1:$AO$1<AM$1)*$AH48:$AO48))) -> 0 | AW48: =MIN(AN48,MAX(0,$AP48-SUMPRODUCT(($AH$1:$AO$1<AN$1)*$AH48:$AO48))) -> 0 | AX48: =MIN(AO48,MAX(0,$AP48-SUMPRODUCT(($AH$1:$AO$1<AO$1)*$AH48:$AO48))) -> 0 | AY48: =ROUND(AH48-AQ48,2) -> 0 | AZ48: =ROUND(AI48-AR48,2) -> 0 | BA48: =ROUND(AJ48-AS48,2) -> 0 | BB48: =ROUND(AK48-AT48,2) -> 0 | BC48: =ROUND(AL48-AU48,2) -> 0 | BD48: =ROUND(AM48-AV48,2) -> 0 | BE48: =ROUND(AN48-AW48,2) -> 0 | BF48: =ROUND(AO48-AX48,2) -> 0 | BG48: =SUM(AY48:BF48) -> 0
A49: 47 | B49: =AY48 -> 0 | C49: =AZ48 -> 0 | D49: =BA48 -> 0 | E49: =BB48 -> 0 | F49: =BC48 -> 0 | G49: =BD48 -> 0 | H49: =BE48 -> 0 | I49: =BF48 -> 0 | J49: =B49*N('Debt Payoff'!D9)/12 -> 0 | K49: =C49*N('Debt Payoff'!D10)/12 -> 0 | L49: =D49*N('Debt Payoff'!D11)/12 -> 0 | M49: =E49*N('Debt Payoff'!D12)/12 -> 0 | N49: =F49*N('Debt Payoff'!D13)/12 -> 0 | O49: =G49*N('Debt Payoff'!D14)/12 -> 0 | P49: =H49*N('Debt Payoff'!D15)/12 -> 0 | Q49: =I49*N('Debt Payoff'!D16)/12 -> 0 | R49: =B49+J49 -> 0 | S49: =C49+K49 -> 0 | T49: =D49+L49 -> 0 | U49: =E49+M49 -> 0 | V49: =F49+N49 -> 0 | W49: =G49+O49 -> 0 | X49: =H49+P49 -> 0 | Y49: =I49+Q49 -> 0 | Z49: =MIN(R49,N('Debt Payoff'!E9)) -> 0 | AA49: =MIN(S49,N('Debt Payoff'!E10)) -> 0 | AB49: =MIN(T49,N('Debt Payoff'!E11)) -> 0 | AC49: =MIN(U49,N('Debt Payoff'!E12)) -> 0 | AD49: =MIN(V49,N('Debt Payoff'!E13)) -> 0 | AE49: =MIN(W49,N('Debt Payoff'!E14)) -> 0 | AF49: =MIN(X49,N('Debt Payoff'!E15)) -> 0 | AG49: =MIN(Y49,N('Debt Payoff'!E16)) -> 0 | AH49: =R49-Z49 -> 0 | AI49: =S49-AA49 -> 0 | AJ49: =T49-AB49 -> 0 | AK49: =U49-AC49 -> 0 | AL49: =V49-AD49 -> 0 | AM49: =W49-AE49 -> 0 | AN49: =X49-AF49 -> 0 | AO49: =Y49-AG49 -> 0 | AP49: =MAX(0,'Debt Payoff'!$D$17-SUM(Z49:AG49)) -> 805 | AQ49: =MIN(AH49,MAX(0,$AP49-SUMPRODUCT(($AH$1:$AO$1<AH$1)*$AH49:$AO49))) -> 0 | AR49: =MIN(AI49,MAX(0,$AP49-SUMPRODUCT(($AH$1:$AO$1<AI$1)*$AH49:$AO49))) -> 0 | AS49: =MIN(AJ49,MAX(0,$AP49-SUMPRODUCT(($AH$1:$AO$1<AJ$1)*$AH49:$AO49))) -> 0 | AT49: =MIN(AK49,MAX(0,$AP49-SUMPRODUCT(($AH$1:$AO$1<AK$1)*$AH49:$AO49))) -> 0 | AU49: =MIN(AL49,MAX(0,$AP49-SUMPRODUCT(($AH$1:$AO$1<AL$1)*$AH49:$AO49))) -> 0 | AV49: =MIN(AM49,MAX(0,$AP49-SUMPRODUCT(($AH$1:$AO$1<AM$1)*$AH49:$AO49))) -> 0 | AW49: =MIN(AN49,MAX(0,$AP49-SUMPRODUCT(($AH$1:$AO$1<AN$1)*$AH49:$AO49))) -> 0 | AX49: =MIN(AO49,MAX(0,$AP49-SUMPRODUCT(($AH$1:$AO$1<AO$1)*$AH49:$AO49))) -> 0 | AY49: =ROUND(AH49-AQ49,2) -> 0 | AZ49: =ROUND(AI49-AR49,2) -> 0 | BA49: =ROUND(AJ49-AS49,2) -> 0 | BB49: =ROUND(AK49-AT49,2) -> 0 | BC49: =ROUND(AL49-AU49,2) -> 0 | BD49: =ROUND(AM49-AV49,2) -> 0 | BE49: =ROUND(AN49-AW49,2) -> 0 | BF49: =ROUND(AO49-AX49,2) -> 0 | BG49: =SUM(AY49:BF49) -> 0
A50: 48 | B50: =AY49 -> 0 | C50: =AZ49 -> 0 | D50: =BA49 -> 0 | E50: =BB49 -> 0 | F50: =BC49 -> 0 | G50: =BD49 -> 0 | H50: =BE49 -> 0 | I50: =BF49 -> 0 | J50: =B50*N('Debt Payoff'!D9)/12 -> 0 | K50: =C50*N('Debt Payoff'!D10)/12 -> 0 | L50: =D50*N('Debt Payoff'!D11)/12 -> 0 | M50: =E50*N('Debt Payoff'!D12)/12 -> 0 | N50: =F50*N('Debt Payoff'!D13)/12 -> 0 | O50: =G50*N('Debt Payoff'!D14)/12 -> 0 | P50: =H50*N('Debt Payoff'!D15)/12 -> 0 | Q50: =I50*N('Debt Payoff'!D16)/12 -> 0 | R50: =B50+J50 -> 0 | S50: =C50+K50 -> 0 | T50: =D50+L50 -> 0 | U50: =E50+M50 -> 0 | V50: =F50+N50 -> 0 | W50: =G50+O50 -> 0 | X50: =H50+P50 -> 0 | Y50: =I50+Q50 -> 0 | Z50: =MIN(R50,N('Debt Payoff'!E9)) -> 0 | AA50: =MIN(S50,N('Debt Payoff'!E10)) -> 0 | AB50: =MIN(T50,N('Debt Payoff'!E11)) -> 0 | AC50: =MIN(U50,N('Debt Payoff'!E12)) -> 0 | AD50: =MIN(V50,N('Debt Payoff'!E13)) -> 0 | AE50: =MIN(W50,N('Debt Payoff'!E14)) -> 0 | AF50: =MIN(X50,N('Debt Payoff'!E15)) -> 0 | AG50: =MIN(Y50,N('Debt Payoff'!E16)) -> 0 | AH50: =R50-Z50 -> 0 | AI50: =S50-AA50 -> 0 | AJ50: =T50-AB50 -> 0 | AK50: =U50-AC50 -> 0 | AL50: =V50-AD50 -> 0 | AM50: =W50-AE50 -> 0 | AN50: =X50-AF50 -> 0 | AO50: =Y50-AG50 -> 0 | AP50: =MAX(0,'Debt Payoff'!$D$17-SUM(Z50:AG50)) -> 805 | AQ50: =MIN(AH50,MAX(0,$AP50-SUMPRODUCT(($AH$1:$AO$1<AH$1)*$AH50:$AO50))) -> 0 | AR50: =MIN(AI50,MAX(0,$AP50-SUMPRODUCT(($AH$1:$AO$1<AI$1)*$AH50:$AO50))) -> 0 | AS50: =MIN(AJ50,MAX(0,$AP50-SUMPRODUCT(($AH$1:$AO$1<AJ$1)*$AH50:$AO50))) -> 0 | AT50: =MIN(AK50,MAX(0,$AP50-SUMPRODUCT(($AH$1:$AO$1<AK$1)*$AH50:$AO50))) -> 0 | AU50: =MIN(AL50,MAX(0,$AP50-SUMPRODUCT(($AH$1:$AO$1<AL$1)*$AH50:$AO50))) -> 0 | AV50: =MIN(AM50,MAX(0,$AP50-SUMPRODUCT(($AH$1:$AO$1<AM$1)*$AH50:$AO50))) -> 0 | AW50: =MIN(AN50,MAX(0,$AP50-SUMPRODUCT(($AH$1:$AO$1<AN$1)*$AH50:$AO50))) -> 0 | AX50: =MIN(AO50,MAX(0,$AP50-SUMPRODUCT(($AH$1:$AO$1<AO$1)*$AH50:$AO50))) -> 0 | AY50: =ROUND(AH50-AQ50,2) -> 0 | AZ50: =ROUND(AI50-AR50,2) -> 0 | BA50: =ROUND(AJ50-AS50,2) -> 0 | BB50: =ROUND(AK50-AT50,2) -> 0 | BC50: =ROUND(AL50-AU50,2) -> 0 | BD50: =ROUND(AM50-AV50,2) -> 0 | BE50: =ROUND(AN50-AW50,2) -> 0 | BF50: =ROUND(AO50-AX50,2) -> 0 | BG50: =SUM(AY50:BF50) -> 0
A51: 49 | B51: =AY50 -> 0 | C51: =AZ50 -> 0 | D51: =BA50 -> 0 | E51: =BB50 -> 0 | F51: =BC50 -> 0 | G51: =BD50 -> 0 | H51: =BE50 -> 0 | I51: =BF50 -> 0 | J51: =B51*N('Debt Payoff'!D9)/12 -> 0 | K51: =C51*N('Debt Payoff'!D10)/12 -> 0 | L51: =D51*N('Debt Payoff'!D11)/12 -> 0 | M51: =E51*N('Debt Payoff'!D12)/12 -> 0 | N51: =F51*N('Debt Payoff'!D13)/12 -> 0 | O51: =G51*N('Debt Payoff'!D14)/12 -> 0 | P51: =H51*N('Debt Payoff'!D15)/12 -> 0 | Q51: =I51*N('Debt Payoff'!D16)/12 -> 0 | R51: =B51+J51 -> 0 | S51: =C51+K51 -> 0 | T51: =D51+L51 -> 0 | U51: =E51+M51 -> 0 | V51: =F51+N51 -> 0 | W51: =G51+O51 -> 0 | X51: =H51+P51 -> 0 | Y51: =I51+Q51 -> 0 | Z51: =MIN(R51,N('Debt Payoff'!E9)) -> 0 | AA51: =MIN(S51,N('Debt Payoff'!E10)) -> 0 | AB51: =MIN(T51,N('Debt Payoff'!E11)) -> 0 | AC51: =MIN(U51,N('Debt Payoff'!E12)) -> 0 | AD51: =MIN(V51,N('Debt Payoff'!E13)) -> 0 | AE51: =MIN(W51,N('Debt Payoff'!E14)) -> 0 | AF51: =MIN(X51,N('Debt Payoff'!E15)) -> 0 | AG51: =MIN(Y51,N('Debt Payoff'!E16)) -> 0 | AH51: =R51-Z51 -> 0 | AI51: =S51-AA51 -> 0 | AJ51: =T51-AB51 -> 0 | AK51: =U51-AC51 -> 0 | AL51: =V51-AD51 -> 0 | AM51: =W51-AE51 -> 0 | AN51: =X51-AF51 -> 0 | AO51: =Y51-AG51 -> 0 | AP51: =MAX(0,'Debt Payoff'!$D$17-SUM(Z51:AG51)) -> 805 | AQ51: =MIN(AH51,MAX(0,$AP51-SUMPRODUCT(($AH$1:$AO$1<AH$1)*$AH51:$AO51))) -> 0 | AR51: =MIN(AI51,MAX(0,$AP51-SUMPRODUCT(($AH$1:$AO$1<AI$1)*$AH51:$AO51))) -> 0 | AS51: =MIN(AJ51,MAX(0,$AP51-SUMPRODUCT(($AH$1:$AO$1<AJ$1)*$AH51:$AO51))) -> 0 | AT51: =MIN(AK51,MAX(0,$AP51-SUMPRODUCT(($AH$1:$AO$1<AK$1)*$AH51:$AO51))) -> 0 | AU51: =MIN(AL51,MAX(0,$AP51-SUMPRODUCT(($AH$1:$AO$1<AL$1)*$AH51:$AO51))) -> 0 | AV51: =MIN(AM51,MAX(0,$AP51-SUMPRODUCT(($AH$1:$AO$1<AM$1)*$AH51:$AO51))) -> 0 | AW51: =MIN(AN51,MAX(0,$AP51-SUMPRODUCT(($AH$1:$AO$1<AN$1)*$AH51:$AO51))) -> 0 | AX51: =MIN(AO51,MAX(0,$AP51-SUMPRODUCT(($AH$1:$AO$1<AO$1)*$AH51:$AO51))) -> 0 | AY51: =ROUND(AH51-AQ51,2) -> 0 | AZ51: =ROUND(AI51-AR51,2) -> 0 | BA51: =ROUND(AJ51-AS51,2) -> 0 | BB51: =ROUND(AK51-AT51,2) -> 0 | BC51: =ROUND(AL51-AU51,2) -> 0 | BD51: =ROUND(AM51-AV51,2) -> 0 | BE51: =ROUND(AN51-AW51,2) -> 0 | BF51: =ROUND(AO51-AX51,2) -> 0 | BG51: =SUM(AY51:BF51) -> 0
A52: 50 | B52: =AY51 -> 0 | C52: =AZ51 -> 0 | D52: =BA51 -> 0 | E52: =BB51 -> 0 | F52: =BC51 -> 0 | G52: =BD51 -> 0 | H52: =BE51 -> 0 | I52: =BF51 -> 0 | J52: =B52*N('Debt Payoff'!D9)/12 -> 0 | K52: =C52*N('Debt Payoff'!D10)/12 -> 0 | L52: =D52*N('Debt Payoff'!D11)/12 -> 0 | M52: =E52*N('Debt Payoff'!D12)/12 -> 0 | N52: =F52*N('Debt Payoff'!D13)/12 -> 0 | O52: =G52*N('Debt Payoff'!D14)/12 -> 0 | P52: =H52*N('Debt Payoff'!D15)/12 -> 0 | Q52: =I52*N('Debt Payoff'!D16)/12 -> 0 | R52: =B52+J52 -> 0 | S52: =C52+K52 -> 0 | T52: =D52+L52 -> 0 | U52: =E52+M52 -> 0 | V52: =F52+N52 -> 0 | W52: =G52+O52 -> 0 | X52: =H52+P52 -> 0 | Y52: =I52+Q52 -> 0 | Z52: =MIN(R52,N('Debt Payoff'!E9)) -> 0 | AA52: =MIN(S52,N('Debt Payoff'!E10)) -> 0 | AB52: =MIN(T52,N('Debt Payoff'!E11)) -> 0 | AC52: =MIN(U52,N('Debt Payoff'!E12)) -> 0 | AD52: =MIN(V52,N('Debt Payoff'!E13)) -> 0 | AE52: =MIN(W52,N('Debt Payoff'!E14)) -> 0 | AF52: =MIN(X52,N('Debt Payoff'!E15)) -> 0 | AG52: =MIN(Y52,N('Debt Payoff'!E16)) -> 0 | AH52: =R52-Z52 -> 0 | AI52: =S52-AA52 -> 0 | AJ52: =T52-AB52 -> 0 | AK52: =U52-AC52 -> 0 | AL52: =V52-AD52 -> 0 | AM52: =W52-AE52 -> 0 | AN52: =X52-AF52 -> 0 | AO52: =Y52-AG52 -> 0 | AP52: =MAX(0,'Debt Payoff'!$D$17-SUM(Z52:AG52)) -> 805 | AQ52: =MIN(AH52,MAX(0,$AP52-SUMPRODUCT(($AH$1:$AO$1<AH$1)*$AH52:$AO52))) -> 0 | AR52: =MIN(AI52,MAX(0,$AP52-SUMPRODUCT(($AH$1:$AO$1<AI$1)*$AH52:$AO52))) -> 0 | AS52: =MIN(AJ52,MAX(0,$AP52-SUMPRODUCT(($AH$1:$AO$1<AJ$1)*$AH52:$AO52))) -> 0 | AT52: =MIN(AK52,MAX(0,$AP52-SUMPRODUCT(($AH$1:$AO$1<AK$1)*$AH52:$AO52))) -> 0 | AU52: =MIN(AL52,MAX(0,$AP52-SUMPRODUCT(($AH$1:$AO$1<AL$1)*$AH52:$AO52))) -> 0 | AV52: =MIN(AM52,MAX(0,$AP52-SUMPRODUCT(($AH$1:$AO$1<AM$1)*$AH52:$AO52))) -> 0 | AW52: =MIN(AN52,MAX(0,$AP52-SUMPRODUCT(($AH$1:$AO$1<AN$1)*$AH52:$AO52))) -> 0 | AX52: =MIN(AO52,MAX(0,$AP52-SUMPRODUCT(($AH$1:$AO$1<AO$1)*$AH52:$AO52))) -> 0 | AY52: =ROUND(AH52-AQ52,2) -> 0 | AZ52: =ROUND(AI52-AR52,2) -> 0 | BA52: =ROUND(AJ52-AS52,2) -> 0 | BB52: =ROUND(AK52-AT52,2) -> 0 | BC52: =ROUND(AL52-AU52,2) -> 0 | BD52: =ROUND(AM52-AV52,2) -> 0 | BE52: =ROUND(AN52-AW52,2) -> 0 | BF52: =ROUND(AO52-AX52,2) -> 0 | BG52: =SUM(AY52:BF52) -> 0
A53: 51 | B53: =AY52 -> 0 | C53: =AZ52 -> 0 | D53: =BA52 -> 0 | E53: =BB52 -> 0 | F53: =BC52 -> 0 | G53: =BD52 -> 0 | H53: =BE52 -> 0 | I53: =BF52 -> 0 | J53: =B53*N('Debt Payoff'!D9)/12 -> 0 | K53: =C53*N('Debt Payoff'!D10)/12 -> 0 | L53: =D53*N('Debt Payoff'!D11)/12 -> 0 | M53: =E53*N('Debt Payoff'!D12)/12 -> 0 | N53: =F53*N('Debt Payoff'!D13)/12 -> 0 | O53: =G53*N('Debt Payoff'!D14)/12 -> 0 | P53: =H53*N('Debt Payoff'!D15)/12 -> 0 | Q53: =I53*N('Debt Payoff'!D16)/12 -> 0 | R53: =B53+J53 -> 0 | S53: =C53+K53 -> 0 | T53: =D53+L53 -> 0 | U53: =E53+M53 -> 0 | V53: =F53+N53 -> 0 | W53: =G53+O53 -> 0 | X53: =H53+P53 -> 0 | Y53: =I53+Q53 -> 0 | Z53: =MIN(R53,N('Debt Payoff'!E9)) -> 0 | AA53: =MIN(S53,N('Debt Payoff'!E10)) -> 0 | AB53: =MIN(T53,N('Debt Payoff'!E11)) -> 0 | AC53: =MIN(U53,N('Debt Payoff'!E12)) -> 0 | AD53: =MIN(V53,N('Debt Payoff'!E13)) -> 0 | AE53: =MIN(W53,N('Debt Payoff'!E14)) -> 0 | AF53: =MIN(X53,N('Debt Payoff'!E15)) -> 0 | AG53: =MIN(Y53,N('Debt Payoff'!E16)) -> 0 | AH53: =R53-Z53 -> 0 | AI53: =S53-AA53 -> 0 | AJ53: =T53-AB53 -> 0 | AK53: =U53-AC53 -> 0 | AL53: =V53-AD53 -> 0 | AM53: =W53-AE53 -> 0 | AN53: =X53-AF53 -> 0 | AO53: =Y53-AG53 -> 0 | AP53: =MAX(0,'Debt Payoff'!$D$17-SUM(Z53:AG53)) -> 805 | AQ53: =MIN(AH53,MAX(0,$AP53-SUMPRODUCT(($AH$1:$AO$1<AH$1)*$AH53:$AO53))) -> 0 | AR53: =MIN(AI53,MAX(0,$AP53-SUMPRODUCT(($AH$1:$AO$1<AI$1)*$AH53:$AO53))) -> 0 | AS53: =MIN(AJ53,MAX(0,$AP53-SUMPRODUCT(($AH$1:$AO$1<AJ$1)*$AH53:$AO53))) -> 0 | AT53: =MIN(AK53,MAX(0,$AP53-SUMPRODUCT(($AH$1:$AO$1<AK$1)*$AH53:$AO53))) -> 0 | AU53: =MIN(AL53,MAX(0,$AP53-SUMPRODUCT(($AH$1:$AO$1<AL$1)*$AH53:$AO53))) -> 0 | AV53: =MIN(AM53,MAX(0,$AP53-SUMPRODUCT(($AH$1:$AO$1<AM$1)*$AH53:$AO53))) -> 0 | AW53: =MIN(AN53,MAX(0,$AP53-SUMPRODUCT(($AH$1:$AO$1<AN$1)*$AH53:$AO53))) -> 0 | AX53: =MIN(AO53,MAX(0,$AP53-SUMPRODUCT(($AH$1:$AO$1<AO$1)*$AH53:$AO53))) -> 0 | AY53: =ROUND(AH53-AQ53,2) -> 0 | AZ53: =ROUND(AI53-AR53,2) -> 0 | BA53: =ROUND(AJ53-AS53,2) -> 0 | BB53: =ROUND(AK53-AT53,2) -> 0 | BC53: =ROUND(AL53-AU53,2) -> 0 | BD53: =ROUND(AM53-AV53,2) -> 0 | BE53: =ROUND(AN53-AW53,2) -> 0 | BF53: =ROUND(AO53-AX53,2) -> 0 | BG53: =SUM(AY53:BF53) -> 0
A54: 52 | B54: =AY53 -> 0 | C54: =AZ53 -> 0 | D54: =BA53 -> 0 | E54: =BB53 -> 0 | F54: =BC53 -> 0 | G54: =BD53 -> 0 | H54: =BE53 -> 0 | I54: =BF53 -> 0 | J54: =B54*N('Debt Payoff'!D9)/12 -> 0 | K54: =C54*N('Debt Payoff'!D10)/12 -> 0 | L54: =D54*N('Debt Payoff'!D11)/12 -> 0 | M54: =E54*N('Debt Payoff'!D12)/12 -> 0 | N54: =F54*N('Debt Payoff'!D13)/12 -> 0 | O54: =G54*N('Debt Payoff'!D14)/12 -> 0 | P54: =H54*N('Debt Payoff'!D15)/12 -> 0 | Q54: =I54*N('Debt Payoff'!D16)/12 -> 0 | R54: =B54+J54 -> 0 | S54: =C54+K54 -> 0 | T54: =D54+L54 -> 0 | U54: =E54+M54 -> 0 | V54: =F54+N54 -> 0 | W54: =G54+O54 -> 0 | X54: =H54+P54 -> 0 | Y54: =I54+Q54 -> 0 | Z54: =MIN(R54,N('Debt Payoff'!E9)) -> 0 | AA54: =MIN(S54,N('Debt Payoff'!E10)) -> 0 | AB54: =MIN(T54,N('Debt Payoff'!E11)) -> 0 | AC54: =MIN(U54,N('Debt Payoff'!E12)) -> 0 | AD54: =MIN(V54,N('Debt Payoff'!E13)) -> 0 | AE54: =MIN(W54,N('Debt Payoff'!E14)) -> 0 | AF54: =MIN(X54,N('Debt Payoff'!E15)) -> 0 | AG54: =MIN(Y54,N('Debt Payoff'!E16)) -> 0 | AH54: =R54-Z54 -> 0 | AI54: =S54-AA54 -> 0 | AJ54: =T54-AB54 -> 0 | AK54: =U54-AC54 -> 0 | AL54: =V54-AD54 -> 0 | AM54: =W54-AE54 -> 0 | AN54: =X54-AF54 -> 0 | AO54: =Y54-AG54 -> 0 | AP54: =MAX(0,'Debt Payoff'!$D$17-SUM(Z54:AG54)) -> 805 | AQ54: =MIN(AH54,MAX(0,$AP54-SUMPRODUCT(($AH$1:$AO$1<AH$1)*$AH54:$AO54))) -> 0 | AR54: =MIN(AI54,MAX(0,$AP54-SUMPRODUCT(($AH$1:$AO$1<AI$1)*$AH54:$AO54))) -> 0 | AS54: =MIN(AJ54,MAX(0,$AP54-SUMPRODUCT(($AH$1:$AO$1<AJ$1)*$AH54:$AO54))) -> 0 | AT54: =MIN(AK54,MAX(0,$AP54-SUMPRODUCT(($AH$1:$AO$1<AK$1)*$AH54:$AO54))) -> 0 | AU54: =MIN(AL54,MAX(0,$AP54-SUMPRODUCT(($AH$1:$AO$1<AL$1)*$AH54:$AO54))) -> 0 | AV54: =MIN(AM54,MAX(0,$AP54-SUMPRODUCT(($AH$1:$AO$1<AM$1)*$AH54:$AO54))) -> 0 | AW54: =MIN(AN54,MAX(0,$AP54-SUMPRODUCT(($AH$1:$AO$1<AN$1)*$AH54:$AO54))) -> 0 | AX54: =MIN(AO54,MAX(0,$AP54-SUMPRODUCT(($AH$1:$AO$1<AO$1)*$AH54:$AO54))) -> 0 | AY54: =ROUND(AH54-AQ54,2) -> 0 | AZ54: =ROUND(AI54-AR54,2) -> 0 | BA54: =ROUND(AJ54-AS54,2) -> 0 | BB54: =ROUND(AK54-AT54,2) -> 0 | BC54: =ROUND(AL54-AU54,2) -> 0 | BD54: =ROUND(AM54-AV54,2) -> 0 | BE54: =ROUND(AN54-AW54,2) -> 0 | BF54: =ROUND(AO54-AX54,2) -> 0 | BG54: =SUM(AY54:BF54) -> 0
A55: 53 | B55: =AY54 -> 0 | C55: =AZ54 -> 0 | D55: =BA54 -> 0 | E55: =BB54 -> 0 | F55: =BC54 -> 0 | G55: =BD54 -> 0 | H55: =BE54 -> 0 | I55: =BF54 -> 0 | J55: =B55*N('Debt Payoff'!D9)/12 -> 0 | K55: =C55*N('Debt Payoff'!D10)/12 -> 0 | L55: =D55*N('Debt Payoff'!D11)/12 -> 0 | M55: =E55*N('Debt Payoff'!D12)/12 -> 0 | N55: =F55*N('Debt Payoff'!D13)/12 -> 0 | O55: =G55*N('Debt Payoff'!D14)/12 -> 0 | P55: =H55*N('Debt Payoff'!D15)/12 -> 0 | Q55: =I55*N('Debt Payoff'!D16)/12 -> 0 | R55: =B55+J55 -> 0 | S55: =C55+K55 -> 0 | T55: =D55+L55 -> 0 | U55: =E55+M55 -> 0 | V55: =F55+N55 -> 0 | W55: =G55+O55 -> 0 | X55: =H55+P55 -> 0 | Y55: =I55+Q55 -> 0 | Z55: =MIN(R55,N('Debt Payoff'!E9)) -> 0 | AA55: =MIN(S55,N('Debt Payoff'!E10)) -> 0 | AB55: =MIN(T55,N('Debt Payoff'!E11)) -> 0 | AC55: =MIN(U55,N('Debt Payoff'!E12)) -> 0 | AD55: =MIN(V55,N('Debt Payoff'!E13)) -> 0 | AE55: =MIN(W55,N('Debt Payoff'!E14)) -> 0 | AF55: =MIN(X55,N('Debt Payoff'!E15)) -> 0 | AG55: =MIN(Y55,N('Debt Payoff'!E16)) -> 0 | AH55: =R55-Z55 -> 0 | AI55: =S55-AA55 -> 0 | AJ55: =T55-AB55 -> 0 | AK55: =U55-AC55 -> 0 | AL55: =V55-AD55 -> 0 | AM55: =W55-AE55 -> 0 | AN55: =X55-AF55 -> 0 | AO55: =Y55-AG55 -> 0 | AP55: =MAX(0,'Debt Payoff'!$D$17-SUM(Z55:AG55)) -> 805 | AQ55: =MIN(AH55,MAX(0,$AP55-SUMPRODUCT(($AH$1:$AO$1<AH$1)*$AH55:$AO55))) -> 0 | AR55: =MIN(AI55,MAX(0,$AP55-SUMPRODUCT(($AH$1:$AO$1<AI$1)*$AH55:$AO55))) -> 0 | AS55: =MIN(AJ55,MAX(0,$AP55-SUMPRODUCT(($AH$1:$AO$1<AJ$1)*$AH55:$AO55))) -> 0 | AT55: =MIN(AK55,MAX(0,$AP55-SUMPRODUCT(($AH$1:$AO$1<AK$1)*$AH55:$AO55))) -> 0 | AU55: =MIN(AL55,MAX(0,$AP55-SUMPRODUCT(($AH$1:$AO$1<AL$1)*$AH55:$AO55))) -> 0 | AV55: =MIN(AM55,MAX(0,$AP55-SUMPRODUCT(($AH$1:$AO$1<AM$1)*$AH55:$AO55))) -> 0 | AW55: =MIN(AN55,MAX(0,$AP55-SUMPRODUCT(($AH$1:$AO$1<AN$1)*$AH55:$AO55))) -> 0 | AX55: =MIN(AO55,MAX(0,$AP55-SUMPRODUCT(($AH$1:$AO$1<AO$1)*$AH55:$AO55))) -> 0 | AY55: =ROUND(AH55-AQ55,2) -> 0 | AZ55: =ROUND(AI55-AR55,2) -> 0 | BA55: =ROUND(AJ55-AS55,2) -> 0 | BB55: =ROUND(AK55-AT55,2) -> 0 | BC55: =ROUND(AL55-AU55,2) -> 0 | BD55: =ROUND(AM55-AV55,2) -> 0 | BE55: =ROUND(AN55-AW55,2) -> 0 | BF55: =ROUND(AO55-AX55,2) -> 0 | BG55: =SUM(AY55:BF55) -> 0
A56: 54 | B56: =AY55 -> 0 | C56: =AZ55 -> 0 | D56: =BA55 -> 0 | E56: =BB55 -> 0 | F56: =BC55 -> 0 | G56: =BD55 -> 0 | H56: =BE55 -> 0 | I56: =BF55 -> 0 | J56: =B56*N('Debt Payoff'!D9)/12 -> 0 | K56: =C56*N('Debt Payoff'!D10)/12 -> 0 | L56: =D56*N('Debt Payoff'!D11)/12 -> 0 | M56: =E56*N('Debt Payoff'!D12)/12 -> 0 | N56: =F56*N('Debt Payoff'!D13)/12 -> 0 | O56: =G56*N('Debt Payoff'!D14)/12 -> 0 | P56: =H56*N('Debt Payoff'!D15)/12 -> 0 | Q56: =I56*N('Debt Payoff'!D16)/12 -> 0 | R56: =B56+J56 -> 0 | S56: =C56+K56 -> 0 | T56: =D56+L56 -> 0 | U56: =E56+M56 -> 0 | V56: =F56+N56 -> 0 | W56: =G56+O56 -> 0 | X56: =H56+P56 -> 0 | Y56: =I56+Q56 -> 0 | Z56: =MIN(R56,N('Debt Payoff'!E9)) -> 0 | AA56: =MIN(S56,N('Debt Payoff'!E10)) -> 0 | AB56: =MIN(T56,N('Debt Payoff'!E11)) -> 0 | AC56: =MIN(U56,N('Debt Payoff'!E12)) -> 0 | AD56: =MIN(V56,N('Debt Payoff'!E13)) -> 0 | AE56: =MIN(W56,N('Debt Payoff'!E14)) -> 0 | AF56: =MIN(X56,N('Debt Payoff'!E15)) -> 0 | AG56: =MIN(Y56,N('Debt Payoff'!E16)) -> 0 | AH56: =R56-Z56 -> 0 | AI56: =S56-AA56 -> 0 | AJ56: =T56-AB56 -> 0 | AK56: =U56-AC56 -> 0 | AL56: =V56-AD56 -> 0 | AM56: =W56-AE56 -> 0 | AN56: =X56-AF56 -> 0 | AO56: =Y56-AG56 -> 0 | AP56: =MAX(0,'Debt Payoff'!$D$17-SUM(Z56:AG56)) -> 805 | AQ56: =MIN(AH56,MAX(0,$AP56-SUMPRODUCT(($AH$1:$AO$1<AH$1)*$AH56:$AO56))) -> 0 | AR56: =MIN(AI56,MAX(0,$AP56-SUMPRODUCT(($AH$1:$AO$1<AI$1)*$AH56:$AO56))) -> 0 | AS56: =MIN(AJ56,MAX(0,$AP56-SUMPRODUCT(($AH$1:$AO$1<AJ$1)*$AH56:$AO56))) -> 0 | AT56: =MIN(AK56,MAX(0,$AP56-SUMPRODUCT(($AH$1:$AO$1<AK$1)*$AH56:$AO56))) -> 0 | AU56: =MIN(AL56,MAX(0,$AP56-SUMPRODUCT(($AH$1:$AO$1<AL$1)*$AH56:$AO56))) -> 0 | AV56: =MIN(AM56,MAX(0,$AP56-SUMPRODUCT(($AH$1:$AO$1<AM$1)*$AH56:$AO56))) -> 0 | AW56: =MIN(AN56,MAX(0,$AP56-SUMPRODUCT(($AH$1:$AO$1<AN$1)*$AH56:$AO56))) -> 0 | AX56: =MIN(AO56,MAX(0,$AP56-SUMPRODUCT(($AH$1:$AO$1<AO$1)*$AH56:$AO56))) -> 0 | AY56: =ROUND(AH56-AQ56,2) -> 0 | AZ56: =ROUND(AI56-AR56,2) -> 0 | BA56: =ROUND(AJ56-AS56,2) -> 0 | BB56: =ROUND(AK56-AT56,2) -> 0 | BC56: =ROUND(AL56-AU56,2) -> 0 | BD56: =ROUND(AM56-AV56,2) -> 0 | BE56: =ROUND(AN56-AW56,2) -> 0 | BF56: =ROUND(AO56-AX56,2) -> 0 | BG56: =SUM(AY56:BF56) -> 0
A57: 55 | B57: =AY56 -> 0 | C57: =AZ56 -> 0 | D57: =BA56 -> 0 | E57: =BB56 -> 0 | F57: =BC56 -> 0 | G57: =BD56 -> 0 | H57: =BE56 -> 0 | I57: =BF56 -> 0 | J57: =B57*N('Debt Payoff'!D9)/12 -> 0 | K57: =C57*N('Debt Payoff'!D10)/12 -> 0 | L57: =D57*N('Debt Payoff'!D11)/12 -> 0 | M57: =E57*N('Debt Payoff'!D12)/12 -> 0 | N57: =F57*N('Debt Payoff'!D13)/12 -> 0 | O57: =G57*N('Debt Payoff'!D14)/12 -> 0 | P57: =H57*N('Debt Payoff'!D15)/12 -> 0 | Q57: =I57*N('Debt Payoff'!D16)/12 -> 0 | R57: =B57+J57 -> 0 | S57: =C57+K57 -> 0 | T57: =D57+L57 -> 0 | U57: =E57+M57 -> 0 | V57: =F57+N57 -> 0 | W57: =G57+O57 -> 0 | X57: =H57+P57 -> 0 | Y57: =I57+Q57 -> 0 | Z57: =MIN(R57,N('Debt Payoff'!E9)) -> 0 | AA57: =MIN(S57,N('Debt Payoff'!E10)) -> 0 | AB57: =MIN(T57,N('Debt Payoff'!E11)) -> 0 | AC57: =MIN(U57,N('Debt Payoff'!E12)) -> 0 | AD57: =MIN(V57,N('Debt Payoff'!E13)) -> 0 | AE57: =MIN(W57,N('Debt Payoff'!E14)) -> 0 | AF57: =MIN(X57,N('Debt Payoff'!E15)) -> 0 | AG57: =MIN(Y57,N('Debt Payoff'!E16)) -> 0 | AH57: =R57-Z57 -> 0 | AI57: =S57-AA57 -> 0 | AJ57: =T57-AB57 -> 0 | AK57: =U57-AC57 -> 0 | AL57: =V57-AD57 -> 0 | AM57: =W57-AE57 -> 0 | AN57: =X57-AF57 -> 0 | AO57: =Y57-AG57 -> 0 | AP57: =MAX(0,'Debt Payoff'!$D$17-SUM(Z57:AG57)) -> 805 | AQ57: =MIN(AH57,MAX(0,$AP57-SUMPRODUCT(($AH$1:$AO$1<AH$1)*$AH57:$AO57))) -> 0 | AR57: =MIN(AI57,MAX(0,$AP57-SUMPRODUCT(($AH$1:$AO$1<AI$1)*$AH57:$AO57))) -> 0 | AS57: =MIN(AJ57,MAX(0,$AP57-SUMPRODUCT(($AH$1:$AO$1<AJ$1)*$AH57:$AO57))) -> 0 | AT57: =MIN(AK57,MAX(0,$AP57-SUMPRODUCT(($AH$1:$AO$1<AK$1)*$AH57:$AO57))) -> 0 | AU57: =MIN(AL57,MAX(0,$AP57-SUMPRODUCT(($AH$1:$AO$1<AL$1)*$AH57:$AO57))) -> 0 | AV57: =MIN(AM57,MAX(0,$AP57-SUMPRODUCT(($AH$1:$AO$1<AM$1)*$AH57:$AO57))) -> 0 | AW57: =MIN(AN57,MAX(0,$AP57-SUMPRODUCT(($AH$1:$AO$1<AN$1)*$AH57:$AO57))) -> 0 | AX57: =MIN(AO57,MAX(0,$AP57-SUMPRODUCT(($AH$1:$AO$1<AO$1)*$AH57:$AO57))) -> 0 | AY57: =ROUND(AH57-AQ57,2) -> 0 | AZ57: =ROUND(AI57-AR57,2) -> 0 | BA57: =ROUND(AJ57-AS57,2) -> 0 | BB57: =ROUND(AK57-AT57,2) -> 0 | BC57: =ROUND(AL57-AU57,2) -> 0 | BD57: =ROUND(AM57-AV57,2) -> 0 | BE57: =ROUND(AN57-AW57,2) -> 0 | BF57: =ROUND(AO57-AX57,2) -> 0 | BG57: =SUM(AY57:BF57) -> 0
A58: 56 | B58: =AY57 -> 0 | C58: =AZ57 -> 0 | D58: =BA57 -> 0 | E58: =BB57 -> 0 | F58: =BC57 -> 0 | G58: =BD57 -> 0 | H58: =BE57 -> 0 | I58: =BF57 -> 0 | J58: =B58*N('Debt Payoff'!D9)/12 -> 0 | K58: =C58*N('Debt Payoff'!D10)/12 -> 0 | L58: =D58*N('Debt Payoff'!D11)/12 -> 0 | M58: =E58*N('Debt Payoff'!D12)/12 -> 0 | N58: =F58*N('Debt Payoff'!D13)/12 -> 0 | O58: =G58*N('Debt Payoff'!D14)/12 -> 0 | P58: =H58*N('Debt Payoff'!D15)/12 -> 0 | Q58: =I58*N('Debt Payoff'!D16)/12 -> 0 | R58: =B58+J58 -> 0 | S58: =C58+K58 -> 0 | T58: =D58+L58 -> 0 | U58: =E58+M58 -> 0 | V58: =F58+N58 -> 0 | W58: =G58+O58 -> 0 | X58: =H58+P58 -> 0 | Y58: =I58+Q58 -> 0 | Z58: =MIN(R58,N('Debt Payoff'!E9)) -> 0 | AA58: =MIN(S58,N('Debt Payoff'!E10)) -> 0 | AB58: =MIN(T58,N('Debt Payoff'!E11)) -> 0 | AC58: =MIN(U58,N('Debt Payoff'!E12)) -> 0 | AD58: =MIN(V58,N('Debt Payoff'!E13)) -> 0 | AE58: =MIN(W58,N('Debt Payoff'!E14)) -> 0 | AF58: =MIN(X58,N('Debt Payoff'!E15)) -> 0 | AG58: =MIN(Y58,N('Debt Payoff'!E16)) -> 0 | AH58: =R58-Z58 -> 0 | AI58: =S58-AA58 -> 0 | AJ58: =T58-AB58 -> 0 | AK58: =U58-AC58 -> 0 | AL58: =V58-AD58 -> 0 | AM58: =W58-AE58 -> 0 | AN58: =X58-AF58 -> 0 | AO58: =Y58-AG58 -> 0 | AP58: =MAX(0,'Debt Payoff'!$D$17-SUM(Z58:AG58)) -> 805 | AQ58: =MIN(AH58,MAX(0,$AP58-SUMPRODUCT(($AH$1:$AO$1<AH$1)*$AH58:$AO58))) -> 0 | AR58: =MIN(AI58,MAX(0,$AP58-SUMPRODUCT(($AH$1:$AO$1<AI$1)*$AH58:$AO58))) -> 0 | AS58: =MIN(AJ58,MAX(0,$AP58-SUMPRODUCT(($AH$1:$AO$1<AJ$1)*$AH58:$AO58))) -> 0 | AT58: =MIN(AK58,MAX(0,$AP58-SUMPRODUCT(($AH$1:$AO$1<AK$1)*$AH58:$AO58))) -> 0 | AU58: =MIN(AL58,MAX(0,$AP58-SUMPRODUCT(($AH$1:$AO$1<AL$1)*$AH58:$AO58))) -> 0 | AV58: =MIN(AM58,MAX(0,$AP58-SUMPRODUCT(($AH$1:$AO$1<AM$1)*$AH58:$AO58))) -> 0 | AW58: =MIN(AN58,MAX(0,$AP58-SUMPRODUCT(($AH$1:$AO$1<AN$1)*$AH58:$AO58))) -> 0 | AX58: =MIN(AO58,MAX(0,$AP58-SUMPRODUCT(($AH$1:$AO$1<AO$1)*$AH58:$AO58))) -> 0 | AY58: =ROUND(AH58-AQ58,2) -> 0 | AZ58: =ROUND(AI58-AR58,2) -> 0 | BA58: =ROUND(AJ58-AS58,2) -> 0 | BB58: =ROUND(AK58-AT58,2) -> 0 | BC58: =ROUND(AL58-AU58,2) -> 0 | BD58: =ROUND(AM58-AV58,2) -> 0 | BE58: =ROUND(AN58-AW58,2) -> 0 | BF58: =ROUND(AO58-AX58,2) -> 0 | BG58: =SUM(AY58:BF58) -> 0
A59: 57 | B59: =AY58 -> 0 | C59: =AZ58 -> 0 | D59: =BA58 -> 0 | E59: =BB58 -> 0 | F59: =BC58 -> 0 | G59: =BD58 -> 0 | H59: =BE58 -> 0 | I59: =BF58 -> 0 | J59: =B59*N('Debt Payoff'!D9)/12 -> 0 | K59: =C59*N('Debt Payoff'!D10)/12 -> 0 | L59: =D59*N('Debt Payoff'!D11)/12 -> 0 | M59: =E59*N('Debt Payoff'!D12)/12 -> 0 | N59: =F59*N('Debt Payoff'!D13)/12 -> 0 | O59: =G59*N('Debt Payoff'!D14)/12 -> 0 | P59: =H59*N('Debt Payoff'!D15)/12 -> 0 | Q59: =I59*N('Debt Payoff'!D16)/12 -> 0 | R59: =B59+J59 -> 0 | S59: =C59+K59 -> 0 | T59: =D59+L59 -> 0 | U59: =E59+M59 -> 0 | V59: =F59+N59 -> 0 | W59: =G59+O59 -> 0 | X59: =H59+P59 -> 0 | Y59: =I59+Q59 -> 0 | Z59: =MIN(R59,N('Debt Payoff'!E9)) -> 0 | AA59: =MIN(S59,N('Debt Payoff'!E10)) -> 0 | AB59: =MIN(T59,N('Debt Payoff'!E11)) -> 0 | AC59: =MIN(U59,N('Debt Payoff'!E12)) -> 0 | AD59: =MIN(V59,N('Debt Payoff'!E13)) -> 0 | AE59: =MIN(W59,N('Debt Payoff'!E14)) -> 0 | AF59: =MIN(X59,N('Debt Payoff'!E15)) -> 0 | AG59: =MIN(Y59,N('Debt Payoff'!E16)) -> 0 | AH59: =R59-Z59 -> 0 | AI59: =S59-AA59 -> 0 | AJ59: =T59-AB59 -> 0 | AK59: =U59-AC59 -> 0 | AL59: =V59-AD59 -> 0 | AM59: =W59-AE59 -> 0 | AN59: =X59-AF59 -> 0 | AO59: =Y59-AG59 -> 0 | AP59: =MAX(0,'Debt Payoff'!$D$17-SUM(Z59:AG59)) -> 805 | AQ59: =MIN(AH59,MAX(0,$AP59-SUMPRODUCT(($AH$1:$AO$1<AH$1)*$AH59:$AO59))) -> 0 | AR59: =MIN(AI59,MAX(0,$AP59-SUMPRODUCT(($AH$1:$AO$1<AI$1)*$AH59:$AO59))) -> 0 | AS59: =MIN(AJ59,MAX(0,$AP59-SUMPRODUCT(($AH$1:$AO$1<AJ$1)*$AH59:$AO59))) -> 0 | AT59: =MIN(AK59,MAX(0,$AP59-SUMPRODUCT(($AH$1:$AO$1<AK$1)*$AH59:$AO59))) -> 0 | AU59: =MIN(AL59,MAX(0,$AP59-SUMPRODUCT(($AH$1:$AO$1<AL$1)*$AH59:$AO59))) -> 0 | AV59: =MIN(AM59,MAX(0,$AP59-SUMPRODUCT(($AH$1:$AO$1<AM$1)*$AH59:$AO59))) -> 0 | AW59: =MIN(AN59,MAX(0,$AP59-SUMPRODUCT(($AH$1:$AO$1<AN$1)*$AH59:$AO59))) -> 0 | AX59: =MIN(AO59,MAX(0,$AP59-SUMPRODUCT(($AH$1:$AO$1<AO$1)*$AH59:$AO59))) -> 0 | AY59: =ROUND(AH59-AQ59,2) -> 0 | AZ59: =ROUND(AI59-AR59,2) -> 0 | BA59: =ROUND(AJ59-AS59,2) -> 0 | BB59: =ROUND(AK59-AT59,2) -> 0 | BC59: =ROUND(AL59-AU59,2) -> 0 | BD59: =ROUND(AM59-AV59,2) -> 0 | BE59: =ROUND(AN59-AW59,2) -> 0 | BF59: =ROUND(AO59-AX59,2) -> 0 | BG59: =SUM(AY59:BF59) -> 0
A60: 58 | B60: =AY59 -> 0 | C60: =AZ59 -> 0 | D60: =BA59 -> 0 | E60: =BB59 -> 0 | F60: =BC59 -> 0 | G60: =BD59 -> 0 | H60: =BE59 -> 0 | I60: =BF59 -> 0 | J60: =B60*N('Debt Payoff'!D9)/12 -> 0 | K60: =C60*N('Debt Payoff'!D10)/12 -> 0 | L60: =D60*N('Debt Payoff'!D11)/12 -> 0 | M60: =E60*N('Debt Payoff'!D12)/12 -> 0 | N60: =F60*N('Debt Payoff'!D13)/12 -> 0 | O60: =G60*N('Debt Payoff'!D14)/12 -> 0 | P60: =H60*N('Debt Payoff'!D15)/12 -> 0 | Q60: =I60*N('Debt Payoff'!D16)/12 -> 0 | R60: =B60+J60 -> 0 | S60: =C60+K60 -> 0 | T60: =D60+L60 -> 0 | U60: =E60+M60 -> 0 | V60: =F60+N60 -> 0 | W60: =G60+O60 -> 0 | X60: =H60+P60 -> 0 | Y60: =I60+Q60 -> 0 | Z60: =MIN(R60,N('Debt Payoff'!E9)) -> 0 | AA60: =MIN(S60,N('Debt Payoff'!E10)) -> 0 | AB60: =MIN(T60,N('Debt Payoff'!E11)) -> 0 | AC60: =MIN(U60,N('Debt Payoff'!E12)) -> 0 | AD60: =MIN(V60,N('Debt Payoff'!E13)) -> 0 | AE60: =MIN(W60,N('Debt Payoff'!E14)) -> 0 | AF60: =MIN(X60,N('Debt Payoff'!E15)) -> 0 | AG60: =MIN(Y60,N('Debt Payoff'!E16)) -> 0 | AH60: =R60-Z60 -> 0 | AI60: =S60-AA60 -> 0 | AJ60: =T60-AB60 -> 0 | AK60: =U60-AC60 -> 0 | AL60: =V60-AD60 -> 0 | AM60: =W60-AE60 -> 0 | AN60: =X60-AF60 -> 0 | AO60: =Y60-AG60 -> 0 | AP60: =MAX(0,'Debt Payoff'!$D$17-SUM(Z60:AG60)) -> 805 | AQ60: =MIN(AH60,MAX(0,$AP60-SUMPRODUCT(($AH$1:$AO$1<AH$1)*$AH60:$AO60))) -> 0 | AR60: =MIN(AI60,MAX(0,$AP60-SUMPRODUCT(($AH$1:$AO$1<AI$1)*$AH60:$AO60))) -> 0 | AS60: =MIN(AJ60,MAX(0,$AP60-SUMPRODUCT(($AH$1:$AO$1<AJ$1)*$AH60:$AO60))) -> 0 | AT60: =MIN(AK60,MAX(0,$AP60-SUMPRODUCT(($AH$1:$AO$1<AK$1)*$AH60:$AO60))) -> 0 | AU60: =MIN(AL60,MAX(0,$AP60-SUMPRODUCT(($AH$1:$AO$1<AL$1)*$AH60:$AO60))) -> 0 | AV60: =MIN(AM60,MAX(0,$AP60-SUMPRODUCT(($AH$1:$AO$1<AM$1)*$AH60:$AO60))) -> 0 | AW60: =MIN(AN60,MAX(0,$AP60-SUMPRODUCT(($AH$1:$AO$1<AN$1)*$AH60:$AO60))) -> 0 | AX60: =MIN(AO60,MAX(0,$AP60-SUMPRODUCT(($AH$1:$AO$1<AO$1)*$AH60:$AO60))) -> 0 | AY60: =ROUND(AH60-AQ60,2) -> 0 | AZ60: =ROUND(AI60-AR60,2) -> 0 | BA60: =ROUND(AJ60-AS60,2) -> 0 | BB60: =ROUND(AK60-AT60,2) -> 0 | BC60: =ROUND(AL60-AU60,2) -> 0 | BD60: =ROUND(AM60-AV60,2) -> 0 | BE60: =ROUND(AN60-AW60,2) -> 0 | BF60: =ROUND(AO60-AX60,2) -> 0 | BG60: =SUM(AY60:BF60) -> 0
A61: 59 | B61: =AY60 -> 0 | C61: =AZ60 -> 0 | D61: =BA60 -> 0 | E61: =BB60 -> 0 | F61: =BC60 -> 0 | G61: =BD60 -> 0 | H61: =BE60 -> 0 | I61: =BF60 -> 0 | J61: =B61*N('Debt Payoff'!D9)/12 -> 0 | K61: =C61*N('Debt Payoff'!D10)/12 -> 0 | L61: =D61*N('Debt Payoff'!D11)/12 -> 0 | M61: =E61*N('Debt Payoff'!D12)/12 -> 0 | N61: =F61*N('Debt Payoff'!D13)/12 -> 0 | O61: =G61*N('Debt Payoff'!D14)/12 -> 0 | P61: =H61*N('Debt Payoff'!D15)/12 -> 0 | Q61: =I61*N('Debt Payoff'!D16)/12 -> 0 | R61: =B61+J61 -> 0 | S61: =C61+K61 -> 0 | T61: =D61+L61 -> 0 | U61: =E61+M61 -> 0 | V61: =F61+N61 -> 0 | W61: =G61+O61 -> 0 | X61: =H61+P61 -> 0 | Y61: =I61+Q61 -> 0 | Z61: =MIN(R61,N('Debt Payoff'!E9)) -> 0 | AA61: =MIN(S61,N('Debt Payoff'!E10)) -> 0 | AB61: =MIN(T61,N('Debt Payoff'!E11)) -> 0 | AC61: =MIN(U61,N('Debt Payoff'!E12)) -> 0 | AD61: =MIN(V61,N('Debt Payoff'!E13)) -> 0 | AE61: =MIN(W61,N('Debt Payoff'!E14)) -> 0 | AF61: =MIN(X61,N('Debt Payoff'!E15)) -> 0 | AG61: =MIN(Y61,N('Debt Payoff'!E16)) -> 0 | AH61: =R61-Z61 -> 0 | AI61: =S61-AA61 -> 0 | AJ61: =T61-AB61 -> 0 | AK61: =U61-AC61 -> 0 | AL61: =V61-AD61 -> 0 | AM61: =W61-AE61 -> 0 | AN61: =X61-AF61 -> 0 | AO61: =Y61-AG61 -> 0 | AP61: =MAX(0,'Debt Payoff'!$D$17-SUM(Z61:AG61)) -> 805 | AQ61: =MIN(AH61,MAX(0,$AP61-SUMPRODUCT(($AH$1:$AO$1<AH$1)*$AH61:$AO61))) -> 0 | AR61: =MIN(AI61,MAX(0,$AP61-SUMPRODUCT(($AH$1:$AO$1<AI$1)*$AH61:$AO61))) -> 0 | AS61: =MIN(AJ61,MAX(0,$AP61-SUMPRODUCT(($AH$1:$AO$1<AJ$1)*$AH61:$AO61))) -> 0 | AT61: =MIN(AK61,MAX(0,$AP61-SUMPRODUCT(($AH$1:$AO$1<AK$1)*$AH61:$AO61))) -> 0 | AU61: =MIN(AL61,MAX(0,$AP61-SUMPRODUCT(($AH$1:$AO$1<AL$1)*$AH61:$AO61))) -> 0 | AV61: =MIN(AM61,MAX(0,$AP61-SUMPRODUCT(($AH$1:$AO$1<AM$1)*$AH61:$AO61))) -> 0 | AW61: =MIN(AN61,MAX(0,$AP61-SUMPRODUCT(($AH$1:$AO$1<AN$1)*$AH61:$AO61))) -> 0 | AX61: =MIN(AO61,MAX(0,$AP61-SUMPRODUCT(($AH$1:$AO$1<AO$1)*$AH61:$AO61))) -> 0 | AY61: =ROUND(AH61-AQ61,2) -> 0 | AZ61: =ROUND(AI61-AR61,2) -> 0 | BA61: =ROUND(AJ61-AS61,2) -> 0 | BB61: =ROUND(AK61-AT61,2) -> 0 | BC61: =ROUND(AL61-AU61,2) -> 0 | BD61: =ROUND(AM61-AV61,2) -> 0 | BE61: =ROUND(AN61-AW61,2) -> 0 | BF61: =ROUND(AO61-AX61,2) -> 0 | BG61: =SUM(AY61:BF61) -> 0
A62: 60 | B62: =AY61 -> 0 | C62: =AZ61 -> 0 | D62: =BA61 -> 0 | E62: =BB61 -> 0 | F62: =BC61 -> 0 | G62: =BD61 -> 0 | H62: =BE61 -> 0 | I62: =BF61 -> 0 | J62: =B62*N('Debt Payoff'!D9)/12 -> 0 | K62: =C62*N('Debt Payoff'!D10)/12 -> 0 | L62: =D62*N('Debt Payoff'!D11)/12 -> 0 | M62: =E62*N('Debt Payoff'!D12)/12 -> 0 | N62: =F62*N('Debt Payoff'!D13)/12 -> 0 | O62: =G62*N('Debt Payoff'!D14)/12 -> 0 | P62: =H62*N('Debt Payoff'!D15)/12 -> 0 | Q62: =I62*N('Debt Payoff'!D16)/12 -> 0 | R62: =B62+J62 -> 0 | S62: =C62+K62 -> 0 | T62: =D62+L62 -> 0 | U62: =E62+M62 -> 0 | V62: =F62+N62 -> 0 | W62: =G62+O62 -> 0 | X62: =H62+P62 -> 0 | Y62: =I62+Q62 -> 0 | Z62: =MIN(R62,N('Debt Payoff'!E9)) -> 0 | AA62: =MIN(S62,N('Debt Payoff'!E10)) -> 0 | AB62: =MIN(T62,N('Debt Payoff'!E11)) -> 0 | AC62: =MIN(U62,N('Debt Payoff'!E12)) -> 0 | AD62: =MIN(V62,N('Debt Payoff'!E13)) -> 0 | AE62: =MIN(W62,N('Debt Payoff'!E14)) -> 0 | AF62: =MIN(X62,N('Debt Payoff'!E15)) -> 0 | AG62: =MIN(Y62,N('Debt Payoff'!E16)) -> 0 | AH62: =R62-Z62 -> 0 | AI62: =S62-AA62 -> 0 | AJ62: =T62-AB62 -> 0 | AK62: =U62-AC62 -> 0 | AL62: =V62-AD62 -> 0 | AM62: =W62-AE62 -> 0 | AN62: =X62-AF62 -> 0 | AO62: =Y62-AG62 -> 0 | AP62: =MAX(0,'Debt Payoff'!$D$17-SUM(Z62:AG62)) -> 805 | AQ62: =MIN(AH62,MAX(0,$AP62-SUMPRODUCT(($AH$1:$AO$1<AH$1)*$AH62:$AO62))) -> 0 | AR62: =MIN(AI62,MAX(0,$AP62-SUMPRODUCT(($AH$1:$AO$1<AI$1)*$AH62:$AO62))) -> 0 | AS62: =MIN(AJ62,MAX(0,$AP62-SUMPRODUCT(($AH$1:$AO$1<AJ$1)*$AH62:$AO62))) -> 0 | AT62: =MIN(AK62,MAX(0,$AP62-SUMPRODUCT(($AH$1:$AO$1<AK$1)*$AH62:$AO62))) -> 0 | AU62: =MIN(AL62,MAX(0,$AP62-SUMPRODUCT(($AH$1:$AO$1<AL$1)*$AH62:$AO62))) -> 0 | AV62: =MIN(AM62,MAX(0,$AP62-SUMPRODUCT(($AH$1:$AO$1<AM$1)*$AH62:$AO62))) -> 0 | AW62: =MIN(AN62,MAX(0,$AP62-SUMPRODUCT(($AH$1:$AO$1<AN$1)*$AH62:$AO62))) -> 0 | AX62: =MIN(AO62,MAX(0,$AP62-SUMPRODUCT(($AH$1:$AO$1<AO$1)*$AH62:$AO62))) -> 0 | AY62: =ROUND(AH62-AQ62,2) -> 0 | AZ62: =ROUND(AI62-AR62,2) -> 0 | BA62: =ROUND(AJ62-AS62,2) -> 0 | BB62: =ROUND(AK62-AT62,2) -> 0 | BC62: =ROUND(AL62-AU62,2) -> 0 | BD62: =ROUND(AM62-AV62,2) -> 0 | BE62: =ROUND(AN62-AW62,2) -> 0 | BF62: =ROUND(AO62-AX62,2) -> 0 | BG62: =SUM(AY62:BF62) -> 0
A63: 61 | B63: =AY62 -> 0 | C63: =AZ62 -> 0 | D63: =BA62 -> 0 | E63: =BB62 -> 0 | F63: =BC62 -> 0 | G63: =BD62 -> 0 | H63: =BE62 -> 0 | I63: =BF62 -> 0 | J63: =B63*N('Debt Payoff'!D9)/12 -> 0 | K63: =C63*N('Debt Payoff'!D10)/12 -> 0 | L63: =D63*N('Debt Payoff'!D11)/12 -> 0 | M63: =E63*N('Debt Payoff'!D12)/12 -> 0 | N63: =F63*N('Debt Payoff'!D13)/12 -> 0 | O63: =G63*N('Debt Payoff'!D14)/12 -> 0 | P63: =H63*N('Debt Payoff'!D15)/12 -> 0 | Q63: =I63*N('Debt Payoff'!D16)/12 -> 0 | R63: =B63+J63 -> 0 | S63: =C63+K63 -> 0 | T63: =D63+L63 -> 0 | U63: =E63+M63 -> 0 | V63: =F63+N63 -> 0 | W63: =G63+O63 -> 0 | X63: =H63+P63 -> 0 | Y63: =I63+Q63 -> 0 | Z63: =MIN(R63,N('Debt Payoff'!E9)) -> 0 | AA63: =MIN(S63,N('Debt Payoff'!E10)) -> 0 | AB63: =MIN(T63,N('Debt Payoff'!E11)) -> 0 | AC63: =MIN(U63,N('Debt Payoff'!E12)) -> 0 | AD63: =MIN(V63,N('Debt Payoff'!E13)) -> 0 | AE63: =MIN(W63,N('Debt Payoff'!E14)) -> 0 | AF63: =MIN(X63,N('Debt Payoff'!E15)) -> 0 | AG63: =MIN(Y63,N('Debt Payoff'!E16)) -> 0 | AH63: =R63-Z63 -> 0 | AI63: =S63-AA63 -> 0 | AJ63: =T63-AB63 -> 0 | AK63: =U63-AC63 -> 0 | AL63: =V63-AD63 -> 0 | AM63: =W63-AE63 -> 0 | AN63: =X63-AF63 -> 0 | AO63: =Y63-AG63 -> 0 | AP63: =MAX(0,'Debt Payoff'!$D$17-SUM(Z63:AG63)) -> 805 | AQ63: =MIN(AH63,MAX(0,$AP63-SUMPRODUCT(($AH$1:$AO$1<AH$1)*$AH63:$AO63))) -> 0 | AR63: =MIN(AI63,MAX(0,$AP63-SUMPRODUCT(($AH$1:$AO$1<AI$1)*$AH63:$AO63))) -> 0 | AS63: =MIN(AJ63,MAX(0,$AP63-SUMPRODUCT(($AH$1:$AO$1<AJ$1)*$AH63:$AO63))) -> 0 | AT63: =MIN(AK63,MAX(0,$AP63-SUMPRODUCT(($AH$1:$AO$1<AK$1)*$AH63:$AO63))) -> 0 | AU63: =MIN(AL63,MAX(0,$AP63-SUMPRODUCT(($AH$1:$AO$1<AL$1)*$AH63:$AO63))) -> 0 | AV63: =MIN(AM63,MAX(0,$AP63-SUMPRODUCT(($AH$1:$AO$1<AM$1)*$AH63:$AO63))) -> 0 | AW63: =MIN(AN63,MAX(0,$AP63-SUMPRODUCT(($AH$1:$AO$1<AN$1)*$AH63:$AO63))) -> 0 | AX63: =MIN(AO63,MAX(0,$AP63-SUMPRODUCT(($AH$1:$AO$1<AO$1)*$AH63:$AO63))) -> 0 | AY63: =ROUND(AH63-AQ63,2) -> 0 | AZ63: =ROUND(AI63-AR63,2) -> 0 | BA63: =ROUND(AJ63-AS63,2) -> 0 | BB63: =ROUND(AK63-AT63,2) -> 0 | BC63: =ROUND(AL63-AU63,2) -> 0 | BD63: =ROUND(AM63-AV63,2) -> 0 | BE63: =ROUND(AN63-AW63,2) -> 0 | BF63: =ROUND(AO63-AX63,2) -> 0 | BG63: =SUM(AY63:BF63) -> 0
A64: 62 | B64: =AY63 -> 0 | C64: =AZ63 -> 0 | D64: =BA63 -> 0 | E64: =BB63 -> 0 | F64: =BC63 -> 0 | G64: =BD63 -> 0 | H64: =BE63 -> 0 | I64: =BF63 -> 0 | J64: =B64*N('Debt Payoff'!D9)/12 -> 0 | K64: =C64*N('Debt Payoff'!D10)/12 -> 0 | L64: =D64*N('Debt Payoff'!D11)/12 -> 0 | M64: =E64*N('Debt Payoff'!D12)/12 -> 0 | N64: =F64*N('Debt Payoff'!D13)/12 -> 0 | O64: =G64*N('Debt Payoff'!D14)/12 -> 0 | P64: =H64*N('Debt Payoff'!D15)/12 -> 0 | Q64: =I64*N('Debt Payoff'!D16)/12 -> 0 | R64: =B64+J64 -> 0 | S64: =C64+K64 -> 0 | T64: =D64+L64 -> 0 | U64: =E64+M64 -> 0 | V64: =F64+N64 -> 0 | W64: =G64+O64 -> 0 | X64: =H64+P64 -> 0 | Y64: =I64+Q64 -> 0 | Z64: =MIN(R64,N('Debt Payoff'!E9)) -> 0 | AA64: =MIN(S64,N('Debt Payoff'!E10)) -> 0 | AB64: =MIN(T64,N('Debt Payoff'!E11)) -> 0 | AC64: =MIN(U64,N('Debt Payoff'!E12)) -> 0 | AD64: =MIN(V64,N('Debt Payoff'!E13)) -> 0 | AE64: =MIN(W64,N('Debt Payoff'!E14)) -> 0 | AF64: =MIN(X64,N('Debt Payoff'!E15)) -> 0 | AG64: =MIN(Y64,N('Debt Payoff'!E16)) -> 0 | AH64: =R64-Z64 -> 0 | AI64: =S64-AA64 -> 0 | AJ64: =T64-AB64 -> 0 | AK64: =U64-AC64 -> 0 | AL64: =V64-AD64 -> 0 | AM64: =W64-AE64 -> 0 | AN64: =X64-AF64 -> 0 | AO64: =Y64-AG64 -> 0 | AP64: =MAX(0,'Debt Payoff'!$D$17-SUM(Z64:AG64)) -> 805 | AQ64: =MIN(AH64,MAX(0,$AP64-SUMPRODUCT(($AH$1:$AO$1<AH$1)*$AH64:$AO64))) -> 0 | AR64: =MIN(AI64,MAX(0,$AP64-SUMPRODUCT(($AH$1:$AO$1<AI$1)*$AH64:$AO64))) -> 0 | AS64: =MIN(AJ64,MAX(0,$AP64-SUMPRODUCT(($AH$1:$AO$1<AJ$1)*$AH64:$AO64))) -> 0 | AT64: =MIN(AK64,MAX(0,$AP64-SUMPRODUCT(($AH$1:$AO$1<AK$1)*$AH64:$AO64))) -> 0 | AU64: =MIN(AL64,MAX(0,$AP64-SUMPRODUCT(($AH$1:$AO$1<AL$1)*$AH64:$AO64))) -> 0 | AV64: =MIN(AM64,MAX(0,$AP64-SUMPRODUCT(($AH$1:$AO$1<AM$1)*$AH64:$AO64))) -> 0 | AW64: =MIN(AN64,MAX(0,$AP64-SUMPRODUCT(($AH$1:$AO$1<AN$1)*$AH64:$AO64))) -> 0 | AX64: =MIN(AO64,MAX(0,$AP64-SUMPRODUCT(($AH$1:$AO$1<AO$1)*$AH64:$AO64))) -> 0 | AY64: =ROUND(AH64-AQ64,2) -> 0 | AZ64: =ROUND(AI64-AR64,2) -> 0 | BA64: =ROUND(AJ64-AS64,2) -> 0 | BB64: =ROUND(AK64-AT64,2) -> 0 | BC64: =ROUND(AL64-AU64,2) -> 0 | BD64: =ROUND(AM64-AV64,2) -> 0 | BE64: =ROUND(AN64-AW64,2) -> 0 | BF64: =ROUND(AO64-AX64,2) -> 0 | BG64: =SUM(AY64:BF64) -> 0
A65: 63 | B65: =AY64 -> 0 | C65: =AZ64 -> 0 | D65: =BA64 -> 0 | E65: =BB64 -> 0 | F65: =BC64 -> 0 | G65: =BD64 -> 0 | H65: =BE64 -> 0 | I65: =BF64 -> 0 | J65: =B65*N('Debt Payoff'!D9)/12 -> 0 | K65: =C65*N('Debt Payoff'!D10)/12 -> 0 | L65: =D65*N('Debt Payoff'!D11)/12 -> 0 | M65: =E65*N('Debt Payoff'!D12)/12 -> 0 | N65: =F65*N('Debt Payoff'!D13)/12 -> 0 | O65: =G65*N('Debt Payoff'!D14)/12 -> 0 | P65: =H65*N('Debt Payoff'!D15)/12 -> 0 | Q65: =I65*N('Debt Payoff'!D16)/12 -> 0 | R65: =B65+J65 -> 0 | S65: =C65+K65 -> 0 | T65: =D65+L65 -> 0 | U65: =E65+M65 -> 0 | V65: =F65+N65 -> 0 | W65: =G65+O65 -> 0 | X65: =H65+P65 -> 0 | Y65: =I65+Q65 -> 0 | Z65: =MIN(R65,N('Debt Payoff'!E9)) -> 0 | AA65: =MIN(S65,N('Debt Payoff'!E10)) -> 0 | AB65: =MIN(T65,N('Debt Payoff'!E11)) -> 0 | AC65: =MIN(U65,N('Debt Payoff'!E12)) -> 0 | AD65: =MIN(V65,N('Debt Payoff'!E13)) -> 0 | AE65: =MIN(W65,N('Debt Payoff'!E14)) -> 0 | AF65: =MIN(X65,N('Debt Payoff'!E15)) -> 0 | AG65: =MIN(Y65,N('Debt Payoff'!E16)) -> 0 | AH65: =R65-Z65 -> 0 | AI65: =S65-AA65 -> 0 | AJ65: =T65-AB65 -> 0 | AK65: =U65-AC65 -> 0 | AL65: =V65-AD65 -> 0 | AM65: =W65-AE65 -> 0 | AN65: =X65-AF65 -> 0 | AO65: =Y65-AG65 -> 0 | AP65: =MAX(0,'Debt Payoff'!$D$17-SUM(Z65:AG65)) -> 805 | AQ65: =MIN(AH65,MAX(0,$AP65-SUMPRODUCT(($AH$1:$AO$1<AH$1)*$AH65:$AO65))) -> 0 | AR65: =MIN(AI65,MAX(0,$AP65-SUMPRODUCT(($AH$1:$AO$1<AI$1)*$AH65:$AO65))) -> 0 | AS65: =MIN(AJ65,MAX(0,$AP65-SUMPRODUCT(($AH$1:$AO$1<AJ$1)*$AH65:$AO65))) -> 0 | AT65: =MIN(AK65,MAX(0,$AP65-SUMPRODUCT(($AH$1:$AO$1<AK$1)*$AH65:$AO65))) -> 0 | AU65: =MIN(AL65,MAX(0,$AP65-SUMPRODUCT(($AH$1:$AO$1<AL$1)*$AH65:$AO65))) -> 0 | AV65: =MIN(AM65,MAX(0,$AP65-SUMPRODUCT(($AH$1:$AO$1<AM$1)*$AH65:$AO65))) -> 0 | AW65: =MIN(AN65,MAX(0,$AP65-SUMPRODUCT(($AH$1:$AO$1<AN$1)*$AH65:$AO65))) -> 0 | AX65: =MIN(AO65,MAX(0,$AP65-SUMPRODUCT(($AH$1:$AO$1<AO$1)*$AH65:$AO65))) -> 0 | AY65: =ROUND(AH65-AQ65,2) -> 0 | AZ65: =ROUND(AI65-AR65,2) -> 0 | BA65: =ROUND(AJ65-AS65,2) -> 0 | BB65: =ROUND(AK65-AT65,2) -> 0 | BC65: =ROUND(AL65-AU65,2) -> 0 | BD65: =ROUND(AM65-AV65,2) -> 0 | BE65: =ROUND(AN65-AW65,2) -> 0 | BF65: =ROUND(AO65-AX65,2) -> 0 | BG65: =SUM(AY65:BF65) -> 0
A66: 64 | B66: =AY65 -> 0 | C66: =AZ65 -> 0 | D66: =BA65 -> 0 | E66: =BB65 -> 0 | F66: =BC65 -> 0 | G66: =BD65 -> 0 | H66: =BE65 -> 0 | I66: =BF65 -> 0 | J66: =B66*N('Debt Payoff'!D9)/12 -> 0 | K66: =C66*N('Debt Payoff'!D10)/12 -> 0 | L66: =D66*N('Debt Payoff'!D11)/12 -> 0 | M66: =E66*N('Debt Payoff'!D12)/12 -> 0 | N66: =F66*N('Debt Payoff'!D13)/12 -> 0 | O66: =G66*N('Debt Payoff'!D14)/12 -> 0 | P66: =H66*N('Debt Payoff'!D15)/12 -> 0 | Q66: =I66*N('Debt Payoff'!D16)/12 -> 0 | R66: =B66+J66 -> 0 | S66: =C66+K66 -> 0 | T66: =D66+L66 -> 0 | U66: =E66+M66 -> 0 | V66: =F66+N66 -> 0 | W66: =G66+O66 -> 0 | X66: =H66+P66 -> 0 | Y66: =I66+Q66 -> 0 | Z66: =MIN(R66,N('Debt Payoff'!E9)) -> 0 | AA66: =MIN(S66,N('Debt Payoff'!E10)) -> 0 | AB66: =MIN(T66,N('Debt Payoff'!E11)) -> 0 | AC66: =MIN(U66,N('Debt Payoff'!E12)) -> 0 | AD66: =MIN(V66,N('Debt Payoff'!E13)) -> 0 | AE66: =MIN(W66,N('Debt Payoff'!E14)) -> 0 | AF66: =MIN(X66,N('Debt Payoff'!E15)) -> 0 | AG66: =MIN(Y66,N('Debt Payoff'!E16)) -> 0 | AH66: =R66-Z66 -> 0 | AI66: =S66-AA66 -> 0 | AJ66: =T66-AB66 -> 0 | AK66: =U66-AC66 -> 0 | AL66: =V66-AD66 -> 0 | AM66: =W66-AE66 -> 0 | AN66: =X66-AF66 -> 0 | AO66: =Y66-AG66 -> 0 | AP66: =MAX(0,'Debt Payoff'!$D$17-SUM(Z66:AG66)) -> 805 | AQ66: =MIN(AH66,MAX(0,$AP66-SUMPRODUCT(($AH$1:$AO$1<AH$1)*$AH66:$AO66))) -> 0 | AR66: =MIN(AI66,MAX(0,$AP66-SUMPRODUCT(($AH$1:$AO$1<AI$1)*$AH66:$AO66))) -> 0 | AS66: =MIN(AJ66,MAX(0,$AP66-SUMPRODUCT(($AH$1:$AO$1<AJ$1)*$AH66:$AO66))) -> 0 | AT66: =MIN(AK66,MAX(0,$AP66-SUMPRODUCT(($AH$1:$AO$1<AK$1)*$AH66:$AO66))) -> 0 | AU66: =MIN(AL66,MAX(0,$AP66-SUMPRODUCT(($AH$1:$AO$1<AL$1)*$AH66:$AO66))) -> 0 | AV66: =MIN(AM66,MAX(0,$AP66-SUMPRODUCT(($AH$1:$AO$1<AM$1)*$AH66:$AO66))) -> 0 | AW66: =MIN(AN66,MAX(0,$AP66-SUMPRODUCT(($AH$1:$AO$1<AN$1)*$AH66:$AO66))) -> 0 | AX66: =MIN(AO66,MAX(0,$AP66-SUMPRODUCT(($AH$1:$AO$1<AO$1)*$AH66:$AO66))) -> 0 | AY66: =ROUND(AH66-AQ66,2) -> 0 | AZ66: =ROUND(AI66-AR66,2) -> 0 | BA66: =ROUND(AJ66-AS66,2) -> 0 | BB66: =ROUND(AK66-AT66,2) -> 0 | BC66: =ROUND(AL66-AU66,2) -> 0 | BD66: =ROUND(AM66-AV66,2) -> 0 | BE66: =ROUND(AN66-AW66,2) -> 0 | BF66: =ROUND(AO66-AX66,2) -> 0 | BG66: =SUM(AY66:BF66) -> 0
A67: 65 | B67: =AY66 -> 0 | C67: =AZ66 -> 0 | D67: =BA66 -> 0 | E67: =BB66 -> 0 | F67: =BC66 -> 0 | G67: =BD66 -> 0 | H67: =BE66 -> 0 | I67: =BF66 -> 0 | J67: =B67*N('Debt Payoff'!D9)/12 -> 0 | K67: =C67*N('Debt Payoff'!D10)/12 -> 0 | L67: =D67*N('Debt Payoff'!D11)/12 -> 0 | M67: =E67*N('Debt Payoff'!D12)/12 -> 0 | N67: =F67*N('Debt Payoff'!D13)/12 -> 0 | O67: =G67*N('Debt Payoff'!D14)/12 -> 0 | P67: =H67*N('Debt Payoff'!D15)/12 -> 0 | Q67: =I67*N('Debt Payoff'!D16)/12 -> 0 | R67: =B67+J67 -> 0 | S67: =C67+K67 -> 0 | T67: =D67+L67 -> 0 | U67: =E67+M67 -> 0 | V67: =F67+N67 -> 0 | W67: =G67+O67 -> 0 | X67: =H67+P67 -> 0 | Y67: =I67+Q67 -> 0 | Z67: =MIN(R67,N('Debt Payoff'!E9)) -> 0 | AA67: =MIN(S67,N('Debt Payoff'!E10)) -> 0 | AB67: =MIN(T67,N('Debt Payoff'!E11)) -> 0 | AC67: =MIN(U67,N('Debt Payoff'!E12)) -> 0 | AD67: =MIN(V67,N('Debt Payoff'!E13)) -> 0 | AE67: =MIN(W67,N('Debt Payoff'!E14)) -> 0 | AF67: =MIN(X67,N('Debt Payoff'!E15)) -> 0 | AG67: =MIN(Y67,N('Debt Payoff'!E16)) -> 0 | AH67: =R67-Z67 -> 0 | AI67: =S67-AA67 -> 0 | AJ67: =T67-AB67 -> 0 | AK67: =U67-AC67 -> 0 | AL67: =V67-AD67 -> 0 | AM67: =W67-AE67 -> 0 | AN67: =X67-AF67 -> 0 | AO67: =Y67-AG67 -> 0 | AP67: =MAX(0,'Debt Payoff'!$D$17-SUM(Z67:AG67)) -> 805 | AQ67: =MIN(AH67,MAX(0,$AP67-SUMPRODUCT(($AH$1:$AO$1<AH$1)*$AH67:$AO67))) -> 0 | AR67: =MIN(AI67,MAX(0,$AP67-SUMPRODUCT(($AH$1:$AO$1<AI$1)*$AH67:$AO67))) -> 0 | AS67: =MIN(AJ67,MAX(0,$AP67-SUMPRODUCT(($AH$1:$AO$1<AJ$1)*$AH67:$AO67))) -> 0 | AT67: =MIN(AK67,MAX(0,$AP67-SUMPRODUCT(($AH$1:$AO$1<AK$1)*$AH67:$AO67))) -> 0 | AU67: =MIN(AL67,MAX(0,$AP67-SUMPRODUCT(($AH$1:$AO$1<AL$1)*$AH67:$AO67))) -> 0 | AV67: =MIN(AM67,MAX(0,$AP67-SUMPRODUCT(($AH$1:$AO$1<AM$1)*$AH67:$AO67))) -> 0 | AW67: =MIN(AN67,MAX(0,$AP67-SUMPRODUCT(($AH$1:$AO$1<AN$1)*$AH67:$AO67))) -> 0 | AX67: =MIN(AO67,MAX(0,$AP67-SUMPRODUCT(($AH$1:$AO$1<AO$1)*$AH67:$AO67))) -> 0 | AY67: =ROUND(AH67-AQ67,2) -> 0 | AZ67: =ROUND(AI67-AR67,2) -> 0 | BA67: =ROUND(AJ67-AS67,2) -> 0 | BB67: =ROUND(AK67-AT67,2) -> 0 | BC67: =ROUND(AL67-AU67,2) -> 0 | BD67: =ROUND(AM67-AV67,2) -> 0 | BE67: =ROUND(AN67-AW67,2) -> 0 | BF67: =ROUND(AO67-AX67,2) -> 0 | BG67: =SUM(AY67:BF67) -> 0
A68: 66 | B68: =AY67 -> 0 | C68: =AZ67 -> 0 | D68: =BA67 -> 0 | E68: =BB67 -> 0 | F68: =BC67 -> 0 | G68: =BD67 -> 0 | H68: =BE67 -> 0 | I68: =BF67 -> 0 | J68: =B68*N('Debt Payoff'!D9)/12 -> 0 | K68: =C68*N('Debt Payoff'!D10)/12 -> 0 | L68: =D68*N('Debt Payoff'!D11)/12 -> 0 | M68: =E68*N('Debt Payoff'!D12)/12 -> 0 | N68: =F68*N('Debt Payoff'!D13)/12 -> 0 | O68: =G68*N('Debt Payoff'!D14)/12 -> 0 | P68: =H68*N('Debt Payoff'!D15)/12 -> 0 | Q68: =I68*N('Debt Payoff'!D16)/12 -> 0 | R68: =B68+J68 -> 0 | S68: =C68+K68 -> 0 | T68: =D68+L68 -> 0 | U68: =E68+M68 -> 0 | V68: =F68+N68 -> 0 | W68: =G68+O68 -> 0 | X68: =H68+P68 -> 0 | Y68: =I68+Q68 -> 0 | Z68: =MIN(R68,N('Debt Payoff'!E9)) -> 0 | AA68: =MIN(S68,N('Debt Payoff'!E10)) -> 0 | AB68: =MIN(T68,N('Debt Payoff'!E11)) -> 0 | AC68: =MIN(U68,N('Debt Payoff'!E12)) -> 0 | AD68: =MIN(V68,N('Debt Payoff'!E13)) -> 0 | AE68: =MIN(W68,N('Debt Payoff'!E14)) -> 0 | AF68: =MIN(X68,N('Debt Payoff'!E15)) -> 0 | AG68: =MIN(Y68,N('Debt Payoff'!E16)) -> 0 | AH68: =R68-Z68 -> 0 | AI68: =S68-AA68 -> 0 | AJ68: =T68-AB68 -> 0 | AK68: =U68-AC68 -> 0 | AL68: =V68-AD68 -> 0 | AM68: =W68-AE68 -> 0 | AN68: =X68-AF68 -> 0 | AO68: =Y68-AG68 -> 0 | AP68: =MAX(0,'Debt Payoff'!$D$17-SUM(Z68:AG68)) -> 805 | AQ68: =MIN(AH68,MAX(0,$AP68-SUMPRODUCT(($AH$1:$AO$1<AH$1)*$AH68:$AO68))) -> 0 | AR68: =MIN(AI68,MAX(0,$AP68-SUMPRODUCT(($AH$1:$AO$1<AI$1)*$AH68:$AO68))) -> 0 | AS68: =MIN(AJ68,MAX(0,$AP68-SUMPRODUCT(($AH$1:$AO$1<AJ$1)*$AH68:$AO68))) -> 0 | AT68: =MIN(AK68,MAX(0,$AP68-SUMPRODUCT(($AH$1:$AO$1<AK$1)*$AH68:$AO68))) -> 0 | AU68: =MIN(AL68,MAX(0,$AP68-SUMPRODUCT(($AH$1:$AO$1<AL$1)*$AH68:$AO68))) -> 0 | AV68: =MIN(AM68,MAX(0,$AP68-SUMPRODUCT(($AH$1:$AO$1<AM$1)*$AH68:$AO68))) -> 0 | AW68: =MIN(AN68,MAX(0,$AP68-SUMPRODUCT(($AH$1:$AO$1<AN$1)*$AH68:$AO68))) -> 0 | AX68: =MIN(AO68,MAX(0,$AP68-SUMPRODUCT(($AH$1:$AO$1<AO$1)*$AH68:$AO68))) -> 0 | AY68: =ROUND(AH68-AQ68,2) -> 0 | AZ68: =ROUND(AI68-AR68,2) -> 0 | BA68: =ROUND(AJ68-AS68,2) -> 0 | BB68: =ROUND(AK68-AT68,2) -> 0 | BC68: =ROUND(AL68-AU68,2) -> 0 | BD68: =ROUND(AM68-AV68,2) -> 0 | BE68: =ROUND(AN68-AW68,2) -> 0 | BF68: =ROUND(AO68-AX68,2) -> 0 | BG68: =SUM(AY68:BF68) -> 0
A69: 67 | B69: =AY68 -> 0 | C69: =AZ68 -> 0 | D69: =BA68 -> 0 | E69: =BB68 -> 0 | F69: =BC68 -> 0 | G69: =BD68 -> 0 | H69: =BE68 -> 0 | I69: =BF68 -> 0 | J69: =B69*N('Debt Payoff'!D9)/12 -> 0 | K69: =C69*N('Debt Payoff'!D10)/12 -> 0 | L69: =D69*N('Debt Payoff'!D11)/12 -> 0 | M69: =E69*N('Debt Payoff'!D12)/12 -> 0 | N69: =F69*N('Debt Payoff'!D13)/12 -> 0 | O69: =G69*N('Debt Payoff'!D14)/12 -> 0 | P69: =H69*N('Debt Payoff'!D15)/12 -> 0 | Q69: =I69*N('Debt Payoff'!D16)/12 -> 0 | R69: =B69+J69 -> 0 | S69: =C69+K69 -> 0 | T69: =D69+L69 -> 0 | U69: =E69+M69 -> 0 | V69: =F69+N69 -> 0 | W69: =G69+O69 -> 0 | X69: =H69+P69 -> 0 | Y69: =I69+Q69 -> 0 | Z69: =MIN(R69,N('Debt Payoff'!E9)) -> 0 | AA69: =MIN(S69,N('Debt Payoff'!E10)) -> 0 | AB69: =MIN(T69,N('Debt Payoff'!E11)) -> 0 | AC69: =MIN(U69,N('Debt Payoff'!E12)) -> 0 | AD69: =MIN(V69,N('Debt Payoff'!E13)) -> 0 | AE69: =MIN(W69,N('Debt Payoff'!E14)) -> 0 | AF69: =MIN(X69,N('Debt Payoff'!E15)) -> 0 | AG69: =MIN(Y69,N('Debt Payoff'!E16)) -> 0 | AH69: =R69-Z69 -> 0 | AI69: =S69-AA69 -> 0 | AJ69: =T69-AB69 -> 0 | AK69: =U69-AC69 -> 0 | AL69: =V69-AD69 -> 0 | AM69: =W69-AE69 -> 0 | AN69: =X69-AF69 -> 0 | AO69: =Y69-AG69 -> 0 | AP69: =MAX(0,'Debt Payoff'!$D$17-SUM(Z69:AG69)) -> 805 | AQ69: =MIN(AH69,MAX(0,$AP69-SUMPRODUCT(($AH$1:$AO$1<AH$1)*$AH69:$AO69))) -> 0 | AR69: =MIN(AI69,MAX(0,$AP69-SUMPRODUCT(($AH$1:$AO$1<AI$1)*$AH69:$AO69))) -> 0 | AS69: =MIN(AJ69,MAX(0,$AP69-SUMPRODUCT(($AH$1:$AO$1<AJ$1)*$AH69:$AO69))) -> 0 | AT69: =MIN(AK69,MAX(0,$AP69-SUMPRODUCT(($AH$1:$AO$1<AK$1)*$AH69:$AO69))) -> 0 | AU69: =MIN(AL69,MAX(0,$AP69-SUMPRODUCT(($AH$1:$AO$1<AL$1)*$AH69:$AO69))) -> 0 | AV69: =MIN(AM69,MAX(0,$AP69-SUMPRODUCT(($AH$1:$AO$1<AM$1)*$AH69:$AO69))) -> 0 | AW69: =MIN(AN69,MAX(0,$AP69-SUMPRODUCT(($AH$1:$AO$1<AN$1)*$AH69:$AO69))) -> 0 | AX69: =MIN(AO69,MAX(0,$AP69-SUMPRODUCT(($AH$1:$AO$1<AO$1)*$AH69:$AO69))) -> 0 | AY69: =ROUND(AH69-AQ69,2) -> 0 | AZ69: =ROUND(AI69-AR69,2) -> 0 | BA69: =ROUND(AJ69-AS69,2) -> 0 | BB69: =ROUND(AK69-AT69,2) -> 0 | BC69: =ROUND(AL69-AU69,2) -> 0 | BD69: =ROUND(AM69-AV69,2) -> 0 | BE69: =ROUND(AN69-AW69,2) -> 0 | BF69: =ROUND(AO69-AX69,2) -> 0 | BG69: =SUM(AY69:BF69) -> 0
A70: 68 | B70: =AY69 -> 0 | C70: =AZ69 -> 0 | D70: =BA69 -> 0 | E70: =BB69 -> 0 | F70: =BC69 -> 0 | G70: =BD69 -> 0 | H70: =BE69 -> 0 | I70: =BF69 -> 0 | J70: =B70*N('Debt Payoff'!D9)/12 -> 0 | K70: =C70*N('Debt Payoff'!D10)/12 -> 0 | L70: =D70*N('Debt Payoff'!D11)/12 -> 0 | M70: =E70*N('Debt Payoff'!D12)/12 -> 0 | N70: =F70*N('Debt Payoff'!D13)/12 -> 0 | O70: =G70*N('Debt Payoff'!D14)/12 -> 0 | P70: =H70*N('Debt Payoff'!D15)/12 -> 0 | Q70: =I70*N('Debt Payoff'!D16)/12 -> 0 | R70: =B70+J70 -> 0 | S70: =C70+K70 -> 0 | T70: =D70+L70 -> 0 | U70: =E70+M70 -> 0 | V70: =F70+N70 -> 0 | W70: =G70+O70 -> 0 | X70: =H70+P70 -> 0 | Y70: =I70+Q70 -> 0 | Z70: =MIN(R70,N('Debt Payoff'!E9)) -> 0 | AA70: =MIN(S70,N('Debt Payoff'!E10)) -> 0 | AB70: =MIN(T70,N('Debt Payoff'!E11)) -> 0 | AC70: =MIN(U70,N('Debt Payoff'!E12)) -> 0 | AD70: =MIN(V70,N('Debt Payoff'!E13)) -> 0 | AE70: =MIN(W70,N('Debt Payoff'!E14)) -> 0 | AF70: =MIN(X70,N('Debt Payoff'!E15)) -> 0 | AG70: =MIN(Y70,N('Debt Payoff'!E16)) -> 0 | AH70: =R70-Z70 -> 0 | AI70: =S70-AA70 -> 0 | AJ70: =T70-AB70 -> 0 | AK70: =U70-AC70 -> 0 | AL70: =V70-AD70 -> 0 | AM70: =W70-AE70 -> 0 | AN70: =X70-AF70 -> 0 | AO70: =Y70-AG70 -> 0 | AP70: =MAX(0,'Debt Payoff'!$D$17-SUM(Z70:AG70)) -> 805 | AQ70: =MIN(AH70,MAX(0,$AP70-SUMPRODUCT(($AH$1:$AO$1<AH$1)*$AH70:$AO70))) -> 0 | AR70: =MIN(AI70,MAX(0,$AP70-SUMPRODUCT(($AH$1:$AO$1<AI$1)*$AH70:$AO70))) -> 0 | AS70: =MIN(AJ70,MAX(0,$AP70-SUMPRODUCT(($AH$1:$AO$1<AJ$1)*$AH70:$AO70))) -> 0 | AT70: =MIN(AK70,MAX(0,$AP70-SUMPRODUCT(($AH$1:$AO$1<AK$1)*$AH70:$AO70))) -> 0 | AU70: =MIN(AL70,MAX(0,$AP70-SUMPRODUCT(($AH$1:$AO$1<AL$1)*$AH70:$AO70))) -> 0 | AV70: =MIN(AM70,MAX(0,$AP70-SUMPRODUCT(($AH$1:$AO$1<AM$1)*$AH70:$AO70))) -> 0 | AW70: =MIN(AN70,MAX(0,$AP70-SUMPRODUCT(($AH$1:$AO$1<AN$1)*$AH70:$AO70))) -> 0 | AX70: =MIN(AO70,MAX(0,$AP70-SUMPRODUCT(($AH$1:$AO$1<AO$1)*$AH70:$AO70))) -> 0 | AY70: =ROUND(AH70-AQ70,2) -> 0 | AZ70: =ROUND(AI70-AR70,2) -> 0 | BA70: =ROUND(AJ70-AS70,2) -> 0 | BB70: =ROUND(AK70-AT70,2) -> 0 | BC70: =ROUND(AL70-AU70,2) -> 0 | BD70: =ROUND(AM70-AV70,2) -> 0 | BE70: =ROUND(AN70-AW70,2) -> 0 | BF70: =ROUND(AO70-AX70,2) -> 0 | BG70: =SUM(AY70:BF70) -> 0
A71: 69 | B71: =AY70 -> 0 | C71: =AZ70 -> 0 | D71: =BA70 -> 0 | E71: =BB70 -> 0 | F71: =BC70 -> 0 | G71: =BD70 -> 0 | H71: =BE70 -> 0 | I71: =BF70 -> 0 | J71: =B71*N('Debt Payoff'!D9)/12 -> 0 | K71: =C71*N('Debt Payoff'!D10)/12 -> 0 | L71: =D71*N('Debt Payoff'!D11)/12 -> 0 | M71: =E71*N('Debt Payoff'!D12)/12 -> 0 | N71: =F71*N('Debt Payoff'!D13)/12 -> 0 | O71: =G71*N('Debt Payoff'!D14)/12 -> 0 | P71: =H71*N('Debt Payoff'!D15)/12 -> 0 | Q71: =I71*N('Debt Payoff'!D16)/12 -> 0 | R71: =B71+J71 -> 0 | S71: =C71+K71 -> 0 | T71: =D71+L71 -> 0 | U71: =E71+M71 -> 0 | V71: =F71+N71 -> 0 | W71: =G71+O71 -> 0 | X71: =H71+P71 -> 0 | Y71: =I71+Q71 -> 0 | Z71: =MIN(R71,N('Debt Payoff'!E9)) -> 0 | AA71: =MIN(S71,N('Debt Payoff'!E10)) -> 0 | AB71: =MIN(T71,N('Debt Payoff'!E11)) -> 0 | AC71: =MIN(U71,N('Debt Payoff'!E12)) -> 0 | AD71: =MIN(V71,N('Debt Payoff'!E13)) -> 0 | AE71: =MIN(W71,N('Debt Payoff'!E14)) -> 0 | AF71: =MIN(X71,N('Debt Payoff'!E15)) -> 0 | AG71: =MIN(Y71,N('Debt Payoff'!E16)) -> 0 | AH71: =R71-Z71 -> 0 | AI71: =S71-AA71 -> 0 | AJ71: =T71-AB71 -> 0 | AK71: =U71-AC71 -> 0 | AL71: =V71-AD71 -> 0 | AM71: =W71-AE71 -> 0 | AN71: =X71-AF71 -> 0 | AO71: =Y71-AG71 -> 0 | AP71: =MAX(0,'Debt Payoff'!$D$17-SUM(Z71:AG71)) -> 805 | AQ71: =MIN(AH71,MAX(0,$AP71-SUMPRODUCT(($AH$1:$AO$1<AH$1)*$AH71:$AO71))) -> 0 | AR71: =MIN(AI71,MAX(0,$AP71-SUMPRODUCT(($AH$1:$AO$1<AI$1)*$AH71:$AO71))) -> 0 | AS71: =MIN(AJ71,MAX(0,$AP71-SUMPRODUCT(($AH$1:$AO$1<AJ$1)*$AH71:$AO71))) -> 0 | AT71: =MIN(AK71,MAX(0,$AP71-SUMPRODUCT(($AH$1:$AO$1<AK$1)*$AH71:$AO71))) -> 0 | AU71: =MIN(AL71,MAX(0,$AP71-SUMPRODUCT(($AH$1:$AO$1<AL$1)*$AH71:$AO71))) -> 0 | AV71: =MIN(AM71,MAX(0,$AP71-SUMPRODUCT(($AH$1:$AO$1<AM$1)*$AH71:$AO71))) -> 0 | AW71: =MIN(AN71,MAX(0,$AP71-SUMPRODUCT(($AH$1:$AO$1<AN$1)*$AH71:$AO71))) -> 0 | AX71: =MIN(AO71,MAX(0,$AP71-SUMPRODUCT(($AH$1:$AO$1<AO$1)*$AH71:$AO71))) -> 0 | AY71: =ROUND(AH71-AQ71,2) -> 0 | AZ71: =ROUND(AI71-AR71,2) -> 0 | BA71: =ROUND(AJ71-AS71,2) -> 0 | BB71: =ROUND(AK71-AT71,2) -> 0 | BC71: =ROUND(AL71-AU71,2) -> 0 | BD71: =ROUND(AM71-AV71,2) -> 0 | BE71: =ROUND(AN71-AW71,2) -> 0 | BF71: =ROUND(AO71-AX71,2) -> 0 | BG71: =SUM(AY71:BF71) -> 0
A72: 70 | B72: =AY71 -> 0 | C72: =AZ71 -> 0 | D72: =BA71 -> 0 | E72: =BB71 -> 0 | F72: =BC71 -> 0 | G72: =BD71 -> 0 | H72: =BE71 -> 0 | I72: =BF71 -> 0 | J72: =B72*N('Debt Payoff'!D9)/12 -> 0 | K72: =C72*N('Debt Payoff'!D10)/12 -> 0 | L72: =D72*N('Debt Payoff'!D11)/12 -> 0 | M72: =E72*N('Debt Payoff'!D12)/12 -> 0 | N72: =F72*N('Debt Payoff'!D13)/12 -> 0 | O72: =G72*N('Debt Payoff'!D14)/12 -> 0 | P72: =H72*N('Debt Payoff'!D15)/12 -> 0 | Q72: =I72*N('Debt Payoff'!D16)/12 -> 0 | R72: =B72+J72 -> 0 | S72: =C72+K72 -> 0 | T72: =D72+L72 -> 0 | U72: =E72+M72 -> 0 | V72: =F72+N72 -> 0 | W72: =G72+O72 -> 0 | X72: =H72+P72 -> 0 | Y72: =I72+Q72 -> 0 | Z72: =MIN(R72,N('Debt Payoff'!E9)) -> 0 | AA72: =MIN(S72,N('Debt Payoff'!E10)) -> 0 | AB72: =MIN(T72,N('Debt Payoff'!E11)) -> 0 | AC72: =MIN(U72,N('Debt Payoff'!E12)) -> 0 | AD72: =MIN(V72,N('Debt Payoff'!E13)) -> 0 | AE72: =MIN(W72,N('Debt Payoff'!E14)) -> 0 | AF72: =MIN(X72,N('Debt Payoff'!E15)) -> 0 | AG72: =MIN(Y72,N('Debt Payoff'!E16)) -> 0 | AH72: =R72-Z72 -> 0 | AI72: =S72-AA72 -> 0 | AJ72: =T72-AB72 -> 0 | AK72: =U72-AC72 -> 0 | AL72: =V72-AD72 -> 0 | AM72: =W72-AE72 -> 0 | AN72: =X72-AF72 -> 0 | AO72: =Y72-AG72 -> 0 | AP72: =MAX(0,'Debt Payoff'!$D$17-SUM(Z72:AG72)) -> 805 | AQ72: =MIN(AH72,MAX(0,$AP72-SUMPRODUCT(($AH$1:$AO$1<AH$1)*$AH72:$AO72))) -> 0 | AR72: =MIN(AI72,MAX(0,$AP72-SUMPRODUCT(($AH$1:$AO$1<AI$1)*$AH72:$AO72))) -> 0 | AS72: =MIN(AJ72,MAX(0,$AP72-SUMPRODUCT(($AH$1:$AO$1<AJ$1)*$AH72:$AO72))) -> 0 | AT72: =MIN(AK72,MAX(0,$AP72-SUMPRODUCT(($AH$1:$AO$1<AK$1)*$AH72:$AO72))) -> 0 | AU72: =MIN(AL72,MAX(0,$AP72-SUMPRODUCT(($AH$1:$AO$1<AL$1)*$AH72:$AO72))) -> 0 | AV72: =MIN(AM72,MAX(0,$AP72-SUMPRODUCT(($AH$1:$AO$1<AM$1)*$AH72:$AO72))) -> 0 | AW72: =MIN(AN72,MAX(0,$AP72-SUMPRODUCT(($AH$1:$AO$1<AN$1)*$AH72:$AO72))) -> 0 | AX72: =MIN(AO72,MAX(0,$AP72-SUMPRODUCT(($AH$1:$AO$1<AO$1)*$AH72:$AO72))) -> 0 | AY72: =ROUND(AH72-AQ72,2) -> 0 | AZ72: =ROUND(AI72-AR72,2) -> 0 | BA72: =ROUND(AJ72-AS72,2) -> 0 | BB72: =ROUND(AK72-AT72,2) -> 0 | BC72: =ROUND(AL72-AU72,2) -> 0 | BD72: =ROUND(AM72-AV72,2) -> 0 | BE72: =ROUND(AN72-AW72,2) -> 0 | BF72: =ROUND(AO72-AX72,2) -> 0 | BG72: =SUM(AY72:BF72) -> 0
A73: 71 | B73: =AY72 -> 0 | C73: =AZ72 -> 0 | D73: =BA72 -> 0 | E73: =BB72 -> 0 | F73: =BC72 -> 0 | G73: =BD72 -> 0 | H73: =BE72 -> 0 | I73: =BF72 -> 0 | J73: =B73*N('Debt Payoff'!D9)/12 -> 0 | K73: =C73*N('Debt Payoff'!D10)/12 -> 0 | L73: =D73*N('Debt Payoff'!D11)/12 -> 0 | M73: =E73*N('Debt Payoff'!D12)/12 -> 0 | N73: =F73*N('Debt Payoff'!D13)/12 -> 0 | O73: =G73*N('Debt Payoff'!D14)/12 -> 0 | P73: =H73*N('Debt Payoff'!D15)/12 -> 0 | Q73: =I73*N('Debt Payoff'!D16)/12 -> 0 | R73: =B73+J73 -> 0 | S73: =C73+K73 -> 0 | T73: =D73+L73 -> 0 | U73: =E73+M73 -> 0 | V73: =F73+N73 -> 0 | W73: =G73+O73 -> 0 | X73: =H73+P73 -> 0 | Y73: =I73+Q73 -> 0 | Z73: =MIN(R73,N('Debt Payoff'!E9)) -> 0 | AA73: =MIN(S73,N('Debt Payoff'!E10)) -> 0 | AB73: =MIN(T73,N('Debt Payoff'!E11)) -> 0 | AC73: =MIN(U73,N('Debt Payoff'!E12)) -> 0 | AD73: =MIN(V73,N('Debt Payoff'!E13)) -> 0 | AE73: =MIN(W73,N('Debt Payoff'!E14)) -> 0 | AF73: =MIN(X73,N('Debt Payoff'!E15)) -> 0 | AG73: =MIN(Y73,N('Debt Payoff'!E16)) -> 0 | AH73: =R73-Z73 -> 0 | AI73: =S73-AA73 -> 0 | AJ73: =T73-AB73 -> 0 | AK73: =U73-AC73 -> 0 | AL73: =V73-AD73 -> 0 | AM73: =W73-AE73 -> 0 | AN73: =X73-AF73 -> 0 | AO73: =Y73-AG73 -> 0 | AP73: =MAX(0,'Debt Payoff'!$D$17-SUM(Z73:AG73)) -> 805 | AQ73: =MIN(AH73,MAX(0,$AP73-SUMPRODUCT(($AH$1:$AO$1<AH$1)*$AH73:$AO73))) -> 0 | AR73: =MIN(AI73,MAX(0,$AP73-SUMPRODUCT(($AH$1:$AO$1<AI$1)*$AH73:$AO73))) -> 0 | AS73: =MIN(AJ73,MAX(0,$AP73-SUMPRODUCT(($AH$1:$AO$1<AJ$1)*$AH73:$AO73))) -> 0 | AT73: =MIN(AK73,MAX(0,$AP73-SUMPRODUCT(($AH$1:$AO$1<AK$1)*$AH73:$AO73))) -> 0 | AU73: =MIN(AL73,MAX(0,$AP73-SUMPRODUCT(($AH$1:$AO$1<AL$1)*$AH73:$AO73))) -> 0 | AV73: =MIN(AM73,MAX(0,$AP73-SUMPRODUCT(($AH$1:$AO$1<AM$1)*$AH73:$AO73))) -> 0 | AW73: =MIN(AN73,MAX(0,$AP73-SUMPRODUCT(($AH$1:$AO$1<AN$1)*$AH73:$AO73))) -> 0 | AX73: =MIN(AO73,MAX(0,$AP73-SUMPRODUCT(($AH$1:$AO$1<AO$1)*$AH73:$AO73))) -> 0 | AY73: =ROUND(AH73-AQ73,2) -> 0 | AZ73: =ROUND(AI73-AR73,2) -> 0 | BA73: =ROUND(AJ73-AS73,2) -> 0 | BB73: =ROUND(AK73-AT73,2) -> 0 | BC73: =ROUND(AL73-AU73,2) -> 0 | BD73: =ROUND(AM73-AV73,2) -> 0 | BE73: =ROUND(AN73-AW73,2) -> 0 | BF73: =ROUND(AO73-AX73,2) -> 0 | BG73: =SUM(AY73:BF73) -> 0
A74: 72 | B74: =AY73 -> 0 | C74: =AZ73 -> 0 | D74: =BA73 -> 0 | E74: =BB73 -> 0 | F74: =BC73 -> 0 | G74: =BD73 -> 0 | H74: =BE73 -> 0 | I74: =BF73 -> 0 | J74: =B74*N('Debt Payoff'!D9)/12 -> 0 | K74: =C74*N('Debt Payoff'!D10)/12 -> 0 | L74: =D74*N('Debt Payoff'!D11)/12 -> 0 | M74: =E74*N('Debt Payoff'!D12)/12 -> 0 | N74: =F74*N('Debt Payoff'!D13)/12 -> 0 | O74: =G74*N('Debt Payoff'!D14)/12 -> 0 | P74: =H74*N('Debt Payoff'!D15)/12 -> 0 | Q74: =I74*N('Debt Payoff'!D16)/12 -> 0 | R74: =B74+J74 -> 0 | S74: =C74+K74 -> 0 | T74: =D74+L74 -> 0 | U74: =E74+M74 -> 0 | V74: =F74+N74 -> 0 | W74: =G74+O74 -> 0 | X74: =H74+P74 -> 0 | Y74: =I74+Q74 -> 0 | Z74: =MIN(R74,N('Debt Payoff'!E9)) -> 0 | AA74: =MIN(S74,N('Debt Payoff'!E10)) -> 0 | AB74: =MIN(T74,N('Debt Payoff'!E11)) -> 0 | AC74: =MIN(U74,N('Debt Payoff'!E12)) -> 0 | AD74: =MIN(V74,N('Debt Payoff'!E13)) -> 0 | AE74: =MIN(W74,N('Debt Payoff'!E14)) -> 0 | AF74: =MIN(X74,N('Debt Payoff'!E15)) -> 0 | AG74: =MIN(Y74,N('Debt Payoff'!E16)) -> 0 | AH74: =R74-Z74 -> 0 | AI74: =S74-AA74 -> 0 | AJ74: =T74-AB74 -> 0 | AK74: =U74-AC74 -> 0 | AL74: =V74-AD74 -> 0 | AM74: =W74-AE74 -> 0 | AN74: =X74-AF74 -> 0 | AO74: =Y74-AG74 -> 0 | AP74: =MAX(0,'Debt Payoff'!$D$17-SUM(Z74:AG74)) -> 805 | AQ74: =MIN(AH74,MAX(0,$AP74-SUMPRODUCT(($AH$1:$AO$1<AH$1)*$AH74:$AO74))) -> 0 | AR74: =MIN(AI74,MAX(0,$AP74-SUMPRODUCT(($AH$1:$AO$1<AI$1)*$AH74:$AO74))) -> 0 | AS74: =MIN(AJ74,MAX(0,$AP74-SUMPRODUCT(($AH$1:$AO$1<AJ$1)*$AH74:$AO74))) -> 0 | AT74: =MIN(AK74,MAX(0,$AP74-SUMPRODUCT(($AH$1:$AO$1<AK$1)*$AH74:$AO74))) -> 0 | AU74: =MIN(AL74,MAX(0,$AP74-SUMPRODUCT(($AH$1:$AO$1<AL$1)*$AH74:$AO74))) -> 0 | AV74: =MIN(AM74,MAX(0,$AP74-SUMPRODUCT(($AH$1:$AO$1<AM$1)*$AH74:$AO74))) -> 0 | AW74: =MIN(AN74,MAX(0,$AP74-SUMPRODUCT(($AH$1:$AO$1<AN$1)*$AH74:$AO74))) -> 0 | AX74: =MIN(AO74,MAX(0,$AP74-SUMPRODUCT(($AH$1:$AO$1<AO$1)*$AH74:$AO74))) -> 0 | AY74: =ROUND(AH74-AQ74,2) -> 0 | AZ74: =ROUND(AI74-AR74,2) -> 0 | BA74: =ROUND(AJ74-AS74,2) -> 0 | BB74: =ROUND(AK74-AT74,2) -> 0 | BC74: =ROUND(AL74-AU74,2) -> 0 | BD74: =ROUND(AM74-AV74,2) -> 0 | BE74: =ROUND(AN74-AW74,2) -> 0 | BF74: =ROUND(AO74-AX74,2) -> 0 | BG74: =SUM(AY74:BF74) -> 0
A75: 73 | B75: =AY74 -> 0 | C75: =AZ74 -> 0 | D75: =BA74 -> 0 | E75: =BB74 -> 0 | F75: =BC74 -> 0 | G75: =BD74 -> 0 | H75: =BE74 -> 0 | I75: =BF74 -> 0 | J75: =B75*N('Debt Payoff'!D9)/12 -> 0 | K75: =C75*N('Debt Payoff'!D10)/12 -> 0 | L75: =D75*N('Debt Payoff'!D11)/12 -> 0 | M75: =E75*N('Debt Payoff'!D12)/12 -> 0 | N75: =F75*N('Debt Payoff'!D13)/12 -> 0 | O75: =G75*N('Debt Payoff'!D14)/12 -> 0 | P75: =H75*N('Debt Payoff'!D15)/12 -> 0 | Q75: =I75*N('Debt Payoff'!D16)/12 -> 0 | R75: =B75+J75 -> 0 | S75: =C75+K75 -> 0 | T75: =D75+L75 -> 0 | U75: =E75+M75 -> 0 | V75: =F75+N75 -> 0 | W75: =G75+O75 -> 0 | X75: =H75+P75 -> 0 | Y75: =I75+Q75 -> 0 | Z75: =MIN(R75,N('Debt Payoff'!E9)) -> 0 | AA75: =MIN(S75,N('Debt Payoff'!E10)) -> 0 | AB75: =MIN(T75,N('Debt Payoff'!E11)) -> 0 | AC75: =MIN(U75,N('Debt Payoff'!E12)) -> 0 | AD75: =MIN(V75,N('Debt Payoff'!E13)) -> 0 | AE75: =MIN(W75,N('Debt Payoff'!E14)) -> 0 | AF75: =MIN(X75,N('Debt Payoff'!E15)) -> 0 | AG75: =MIN(Y75,N('Debt Payoff'!E16)) -> 0 | AH75: =R75-Z75 -> 0 | AI75: =S75-AA75 -> 0 | AJ75: =T75-AB75 -> 0 | AK75: =U75-AC75 -> 0 | AL75: =V75-AD75 -> 0 | AM75: =W75-AE75 -> 0 | AN75: =X75-AF75 -> 0 | AO75: =Y75-AG75 -> 0 | AP75: =MAX(0,'Debt Payoff'!$D$17-SUM(Z75:AG75)) -> 805 | AQ75: =MIN(AH75,MAX(0,$AP75-SUMPRODUCT(($AH$1:$AO$1<AH$1)*$AH75:$AO75))) -> 0 | AR75: =MIN(AI75,MAX(0,$AP75-SUMPRODUCT(($AH$1:$AO$1<AI$1)*$AH75:$AO75))) -> 0 | AS75: =MIN(AJ75,MAX(0,$AP75-SUMPRODUCT(($AH$1:$AO$1<AJ$1)*$AH75:$AO75))) -> 0 | AT75: =MIN(AK75,MAX(0,$AP75-SUMPRODUCT(($AH$1:$AO$1<AK$1)*$AH75:$AO75))) -> 0 | AU75: =MIN(AL75,MAX(0,$AP75-SUMPRODUCT(($AH$1:$AO$1<AL$1)*$AH75:$AO75))) -> 0 | AV75: =MIN(AM75,MAX(0,$AP75-SUMPRODUCT(($AH$1:$AO$1<AM$1)*$AH75:$AO75))) -> 0 | AW75: =MIN(AN75,MAX(0,$AP75-SUMPRODUCT(($AH$1:$AO$1<AN$1)*$AH75:$AO75))) -> 0 | AX75: =MIN(AO75,MAX(0,$AP75-SUMPRODUCT(($AH$1:$AO$1<AO$1)*$AH75:$AO75))) -> 0 | AY75: =ROUND(AH75-AQ75,2) -> 0 | AZ75: =ROUND(AI75-AR75,2) -> 0 | BA75: =ROUND(AJ75-AS75,2) -> 0 | BB75: =ROUND(AK75-AT75,2) -> 0 | BC75: =ROUND(AL75-AU75,2) -> 0 | BD75: =ROUND(AM75-AV75,2) -> 0 | BE75: =ROUND(AN75-AW75,2) -> 0 | BF75: =ROUND(AO75-AX75,2) -> 0 | BG75: =SUM(AY75:BF75) -> 0
A76: 74 | B76: =AY75 -> 0 | C76: =AZ75 -> 0 | D76: =BA75 -> 0 | E76: =BB75 -> 0 | F76: =BC75 -> 0 | G76: =BD75 -> 0 | H76: =BE75 -> 0 | I76: =BF75 -> 0 | J76: =B76*N('Debt Payoff'!D9)/12 -> 0 | K76: =C76*N('Debt Payoff'!D10)/12 -> 0 | L76: =D76*N('Debt Payoff'!D11)/12 -> 0 | M76: =E76*N('Debt Payoff'!D12)/12 -> 0 | N76: =F76*N('Debt Payoff'!D13)/12 -> 0 | O76: =G76*N('Debt Payoff'!D14)/12 -> 0 | P76: =H76*N('Debt Payoff'!D15)/12 -> 0 | Q76: =I76*N('Debt Payoff'!D16)/12 -> 0 | R76: =B76+J76 -> 0 | S76: =C76+K76 -> 0 | T76: =D76+L76 -> 0 | U76: =E76+M76 -> 0 | V76: =F76+N76 -> 0 | W76: =G76+O76 -> 0 | X76: =H76+P76 -> 0 | Y76: =I76+Q76 -> 0 | Z76: =MIN(R76,N('Debt Payoff'!E9)) -> 0 | AA76: =MIN(S76,N('Debt Payoff'!E10)) -> 0 | AB76: =MIN(T76,N('Debt Payoff'!E11)) -> 0 | AC76: =MIN(U76,N('Debt Payoff'!E12)) -> 0 | AD76: =MIN(V76,N('Debt Payoff'!E13)) -> 0 | AE76: =MIN(W76,N('Debt Payoff'!E14)) -> 0 | AF76: =MIN(X76,N('Debt Payoff'!E15)) -> 0 | AG76: =MIN(Y76,N('Debt Payoff'!E16)) -> 0 | AH76: =R76-Z76 -> 0 | AI76: =S76-AA76 -> 0 | AJ76: =T76-AB76 -> 0 | AK76: =U76-AC76 -> 0 | AL76: =V76-AD76 -> 0 | AM76: =W76-AE76 -> 0 | AN76: =X76-AF76 -> 0 | AO76: =Y76-AG76 -> 0 | AP76: =MAX(0,'Debt Payoff'!$D$17-SUM(Z76:AG76)) -> 805 | AQ76: =MIN(AH76,MAX(0,$AP76-SUMPRODUCT(($AH$1:$AO$1<AH$1)*$AH76:$AO76))) -> 0 | AR76: =MIN(AI76,MAX(0,$AP76-SUMPRODUCT(($AH$1:$AO$1<AI$1)*$AH76:$AO76))) -> 0 | AS76: =MIN(AJ76,MAX(0,$AP76-SUMPRODUCT(($AH$1:$AO$1<AJ$1)*$AH76:$AO76))) -> 0 | AT76: =MIN(AK76,MAX(0,$AP76-SUMPRODUCT(($AH$1:$AO$1<AK$1)*$AH76:$AO76))) -> 0 | AU76: =MIN(AL76,MAX(0,$AP76-SUMPRODUCT(($AH$1:$AO$1<AL$1)*$AH76:$AO76))) -> 0 | AV76: =MIN(AM76,MAX(0,$AP76-SUMPRODUCT(($AH$1:$AO$1<AM$1)*$AH76:$AO76))) -> 0 | AW76: =MIN(AN76,MAX(0,$AP76-SUMPRODUCT(($AH$1:$AO$1<AN$1)*$AH76:$AO76))) -> 0 | AX76: =MIN(AO76,MAX(0,$AP76-SUMPRODUCT(($AH$1:$AO$1<AO$1)*$AH76:$AO76))) -> 0 | AY76: =ROUND(AH76-AQ76,2) -> 0 | AZ76: =ROUND(AI76-AR76,2) -> 0 | BA76: =ROUND(AJ76-AS76,2) -> 0 | BB76: =ROUND(AK76-AT76,2) -> 0 | BC76: =ROUND(AL76-AU76,2) -> 0 | BD76: =ROUND(AM76-AV76,2) -> 0 | BE76: =ROUND(AN76-AW76,2) -> 0 | BF76: =ROUND(AO76-AX76,2) -> 0 | BG76: =SUM(AY76:BF76) -> 0
A77: 75 | B77: =AY76 -> 0 | C77: =AZ76 -> 0 | D77: =BA76 -> 0 | E77: =BB76 -> 0 | F77: =BC76 -> 0 | G77: =BD76 -> 0 | H77: =BE76 -> 0 | I77: =BF76 -> 0 | J77: =B77*N('Debt Payoff'!D9)/12 -> 0 | K77: =C77*N('Debt Payoff'!D10)/12 -> 0 | L77: =D77*N('Debt Payoff'!D11)/12 -> 0 | M77: =E77*N('Debt Payoff'!D12)/12 -> 0 | N77: =F77*N('Debt Payoff'!D13)/12 -> 0 | O77: =G77*N('Debt Payoff'!D14)/12 -> 0 | P77: =H77*N('Debt Payoff'!D15)/12 -> 0 | Q77: =I77*N('Debt Payoff'!D16)/12 -> 0 | R77: =B77+J77 -> 0 | S77: =C77+K77 -> 0 | T77: =D77+L77 -> 0 | U77: =E77+M77 -> 0 | V77: =F77+N77 -> 0 | W77: =G77+O77 -> 0 | X77: =H77+P77 -> 0 | Y77: =I77+Q77 -> 0 | Z77: =MIN(R77,N('Debt Payoff'!E9)) -> 0 | AA77: =MIN(S77,N('Debt Payoff'!E10)) -> 0 | AB77: =MIN(T77,N('Debt Payoff'!E11)) -> 0 | AC77: =MIN(U77,N('Debt Payoff'!E12)) -> 0 | AD77: =MIN(V77,N('Debt Payoff'!E13)) -> 0 | AE77: =MIN(W77,N('Debt Payoff'!E14)) -> 0 | AF77: =MIN(X77,N('Debt Payoff'!E15)) -> 0 | AG77: =MIN(Y77,N('Debt Payoff'!E16)) -> 0 | AH77: =R77-Z77 -> 0 | AI77: =S77-AA77 -> 0 | AJ77: =T77-AB77 -> 0 | AK77: =U77-AC77 -> 0 | AL77: =V77-AD77 -> 0 | AM77: =W77-AE77 -> 0 | AN77: =X77-AF77 -> 0 | AO77: =Y77-AG77 -> 0 | AP77: =MAX(0,'Debt Payoff'!$D$17-SUM(Z77:AG77)) -> 805 | AQ77: =MIN(AH77,MAX(0,$AP77-SUMPRODUCT(($AH$1:$AO$1<AH$1)*$AH77:$AO77))) -> 0 | AR77: =MIN(AI77,MAX(0,$AP77-SUMPRODUCT(($AH$1:$AO$1<AI$1)*$AH77:$AO77))) -> 0 | AS77: =MIN(AJ77,MAX(0,$AP77-SUMPRODUCT(($AH$1:$AO$1<AJ$1)*$AH77:$AO77))) -> 0 | AT77: =MIN(AK77,MAX(0,$AP77-SUMPRODUCT(($AH$1:$AO$1<AK$1)*$AH77:$AO77))) -> 0 | AU77: =MIN(AL77,MAX(0,$AP77-SUMPRODUCT(($AH$1:$AO$1<AL$1)*$AH77:$AO77))) -> 0 | AV77: =MIN(AM77,MAX(0,$AP77-SUMPRODUCT(($AH$1:$AO$1<AM$1)*$AH77:$AO77))) -> 0 | AW77: =MIN(AN77,MAX(0,$AP77-SUMPRODUCT(($AH$1:$AO$1<AN$1)*$AH77:$AO77))) -> 0 | AX77: =MIN(AO77,MAX(0,$AP77-SUMPRODUCT(($AH$1:$AO$1<AO$1)*$AH77:$AO77))) -> 0 | AY77: =ROUND(AH77-AQ77,2) -> 0 | AZ77: =ROUND(AI77-AR77,2) -> 0 | BA77: =ROUND(AJ77-AS77,2) -> 0 | BB77: =ROUND(AK77-AT77,2) -> 0 | BC77: =ROUND(AL77-AU77,2) -> 0 | BD77: =ROUND(AM77-AV77,2) -> 0 | BE77: =ROUND(AN77-AW77,2) -> 0 | BF77: =ROUND(AO77-AX77,2) -> 0 | BG77: =SUM(AY77:BF77) -> 0
A78: 76 | B78: =AY77 -> 0 | C78: =AZ77 -> 0 | D78: =BA77 -> 0 | E78: =BB77 -> 0 | F78: =BC77 -> 0 | G78: =BD77 -> 0 | H78: =BE77 -> 0 | I78: =BF77 -> 0 | J78: =B78*N('Debt Payoff'!D9)/12 -> 0 | K78: =C78*N('Debt Payoff'!D10)/12 -> 0 | L78: =D78*N('Debt Payoff'!D11)/12 -> 0 | M78: =E78*N('Debt Payoff'!D12)/12 -> 0 | N78: =F78*N('Debt Payoff'!D13)/12 -> 0 | O78: =G78*N('Debt Payoff'!D14)/12 -> 0 | P78: =H78*N('Debt Payoff'!D15)/12 -> 0 | Q78: =I78*N('Debt Payoff'!D16)/12 -> 0 | R78: =B78+J78 -> 0 | S78: =C78+K78 -> 0 | T78: =D78+L78 -> 0 | U78: =E78+M78 -> 0 | V78: =F78+N78 -> 0 | W78: =G78+O78 -> 0 | X78: =H78+P78 -> 0 | Y78: =I78+Q78 -> 0 | Z78: =MIN(R78,N('Debt Payoff'!E9)) -> 0 | AA78: =MIN(S78,N('Debt Payoff'!E10)) -> 0 | AB78: =MIN(T78,N('Debt Payoff'!E11)) -> 0 | AC78: =MIN(U78,N('Debt Payoff'!E12)) -> 0 | AD78: =MIN(V78,N('Debt Payoff'!E13)) -> 0 | AE78: =MIN(W78,N('Debt Payoff'!E14)) -> 0 | AF78: =MIN(X78,N('Debt Payoff'!E15)) -> 0 | AG78: =MIN(Y78,N('Debt Payoff'!E16)) -> 0 | AH78: =R78-Z78 -> 0 | AI78: =S78-AA78 -> 0 | AJ78: =T78-AB78 -> 0 | AK78: =U78-AC78 -> 0 | AL78: =V78-AD78 -> 0 | AM78: =W78-AE78 -> 0 | AN78: =X78-AF78 -> 0 | AO78: =Y78-AG78 -> 0 | AP78: =MAX(0,'Debt Payoff'!$D$17-SUM(Z78:AG78)) -> 805 | AQ78: =MIN(AH78,MAX(0,$AP78-SUMPRODUCT(($AH$1:$AO$1<AH$1)*$AH78:$AO78))) -> 0 | AR78: =MIN(AI78,MAX(0,$AP78-SUMPRODUCT(($AH$1:$AO$1<AI$1)*$AH78:$AO78))) -> 0 | AS78: =MIN(AJ78,MAX(0,$AP78-SUMPRODUCT(($AH$1:$AO$1<AJ$1)*$AH78:$AO78))) -> 0 | AT78: =MIN(AK78,MAX(0,$AP78-SUMPRODUCT(($AH$1:$AO$1<AK$1)*$AH78:$AO78))) -> 0 | AU78: =MIN(AL78,MAX(0,$AP78-SUMPRODUCT(($AH$1:$AO$1<AL$1)*$AH78:$AO78))) -> 0 | AV78: =MIN(AM78,MAX(0,$AP78-SUMPRODUCT(($AH$1:$AO$1<AM$1)*$AH78:$AO78))) -> 0 | AW78: =MIN(AN78,MAX(0,$AP78-SUMPRODUCT(($AH$1:$AO$1<AN$1)*$AH78:$AO78))) -> 0 | AX78: =MIN(AO78,MAX(0,$AP78-SUMPRODUCT(($AH$1:$AO$1<AO$1)*$AH78:$AO78))) -> 0 | AY78: =ROUND(AH78-AQ78,2) -> 0 | AZ78: =ROUND(AI78-AR78,2) -> 0 | BA78: =ROUND(AJ78-AS78,2) -> 0 | BB78: =ROUND(AK78-AT78,2) -> 0 | BC78: =ROUND(AL78-AU78,2) -> 0 | BD78: =ROUND(AM78-AV78,2) -> 0 | BE78: =ROUND(AN78-AW78,2) -> 0 | BF78: =ROUND(AO78-AX78,2) -> 0 | BG78: =SUM(AY78:BF78) -> 0
A79: 77 | B79: =AY78 -> 0 | C79: =AZ78 -> 0 | D79: =BA78 -> 0 | E79: =BB78 -> 0 | F79: =BC78 -> 0 | G79: =BD78 -> 0 | H79: =BE78 -> 0 | I79: =BF78 -> 0 | J79: =B79*N('Debt Payoff'!D9)/12 -> 0 | K79: =C79*N('Debt Payoff'!D10)/12 -> 0 | L79: =D79*N('Debt Payoff'!D11)/12 -> 0 | M79: =E79*N('Debt Payoff'!D12)/12 -> 0 | N79: =F79*N('Debt Payoff'!D13)/12 -> 0 | O79: =G79*N('Debt Payoff'!D14)/12 -> 0 | P79: =H79*N('Debt Payoff'!D15)/12 -> 0 | Q79: =I79*N('Debt Payoff'!D16)/12 -> 0 | R79: =B79+J79 -> 0 | S79: =C79+K79 -> 0 | T79: =D79+L79 -> 0 | U79: =E79+M79 -> 0 | V79: =F79+N79 -> 0 | W79: =G79+O79 -> 0 | X79: =H79+P79 -> 0 | Y79: =I79+Q79 -> 0 | Z79: =MIN(R79,N('Debt Payoff'!E9)) -> 0 | AA79: =MIN(S79,N('Debt Payoff'!E10)) -> 0 | AB79: =MIN(T79,N('Debt Payoff'!E11)) -> 0 | AC79: =MIN(U79,N('Debt Payoff'!E12)) -> 0 | AD79: =MIN(V79,N('Debt Payoff'!E13)) -> 0 | AE79: =MIN(W79,N('Debt Payoff'!E14)) -> 0 | AF79: =MIN(X79,N('Debt Payoff'!E15)) -> 0 | AG79: =MIN(Y79,N('Debt Payoff'!E16)) -> 0 | AH79: =R79-Z79 -> 0 | AI79: =S79-AA79 -> 0 | AJ79: =T79-AB79 -> 0 | AK79: =U79-AC79 -> 0 | AL79: =V79-AD79 -> 0 | AM79: =W79-AE79 -> 0 | AN79: =X79-AF79 -> 0 | AO79: =Y79-AG79 -> 0 | AP79: =MAX(0,'Debt Payoff'!$D$17-SUM(Z79:AG79)) -> 805 | AQ79: =MIN(AH79,MAX(0,$AP79-SUMPRODUCT(($AH$1:$AO$1<AH$1)*$AH79:$AO79))) -> 0 | AR79: =MIN(AI79,MAX(0,$AP79-SUMPRODUCT(($AH$1:$AO$1<AI$1)*$AH79:$AO79))) -> 0 | AS79: =MIN(AJ79,MAX(0,$AP79-SUMPRODUCT(($AH$1:$AO$1<AJ$1)*$AH79:$AO79))) -> 0 | AT79: =MIN(AK79,MAX(0,$AP79-SUMPRODUCT(($AH$1:$AO$1<AK$1)*$AH79:$AO79))) -> 0 | AU79: =MIN(AL79,MAX(0,$AP79-SUMPRODUCT(($AH$1:$AO$1<AL$1)*$AH79:$AO79))) -> 0 | AV79: =MIN(AM79,MAX(0,$AP79-SUMPRODUCT(($AH$1:$AO$1<AM$1)*$AH79:$AO79))) -> 0 | AW79: =MIN(AN79,MAX(0,$AP79-SUMPRODUCT(($AH$1:$AO$1<AN$1)*$AH79:$AO79))) -> 0 | AX79: =MIN(AO79,MAX(0,$AP79-SUMPRODUCT(($AH$1:$AO$1<AO$1)*$AH79:$AO79))) -> 0 | AY79: =ROUND(AH79-AQ79,2) -> 0 | AZ79: =ROUND(AI79-AR79,2) -> 0 | BA79: =ROUND(AJ79-AS79,2) -> 0 | BB79: =ROUND(AK79-AT79,2) -> 0 | BC79: =ROUND(AL79-AU79,2) -> 0 | BD79: =ROUND(AM79-AV79,2) -> 0 | BE79: =ROUND(AN79-AW79,2) -> 0 | BF79: =ROUND(AO79-AX79,2) -> 0 | BG79: =SUM(AY79:BF79) -> 0
A80: 78 | B80: =AY79 -> 0 | C80: =AZ79 -> 0 | D80: =BA79 -> 0 | E80: =BB79 -> 0 | F80: =BC79 -> 0 | G80: =BD79 -> 0 | H80: =BE79 -> 0 | I80: =BF79 -> 0 | J80: =B80*N('Debt Payoff'!D9)/12 -> 0 | K80: =C80*N('Debt Payoff'!D10)/12 -> 0 | L80: =D80*N('Debt Payoff'!D11)/12 -> 0 | M80: =E80*N('Debt Payoff'!D12)/12 -> 0 | N80: =F80*N('Debt Payoff'!D13)/12 -> 0 | O80: =G80*N('Debt Payoff'!D14)/12 -> 0 | P80: =H80*N('Debt Payoff'!D15)/12 -> 0 | Q80: =I80*N('Debt Payoff'!D16)/12 -> 0 | R80: =B80+J80 -> 0 | S80: =C80+K80 -> 0 | T80: =D80+L80 -> 0 | U80: =E80+M80 -> 0 | V80: =F80+N80 -> 0 | W80: =G80+O80 -> 0 | X80: =H80+P80 -> 0 | Y80: =I80+Q80 -> 0 | Z80: =MIN(R80,N('Debt Payoff'!E9)) -> 0 | AA80: =MIN(S80,N('Debt Payoff'!E10)) -> 0 | AB80: =MIN(T80,N('Debt Payoff'!E11)) -> 0 | AC80: =MIN(U80,N('Debt Payoff'!E12)) -> 0 | AD80: =MIN(V80,N('Debt Payoff'!E13)) -> 0 | AE80: =MIN(W80,N('Debt Payoff'!E14)) -> 0 | AF80: =MIN(X80,N('Debt Payoff'!E15)) -> 0 | AG80: =MIN(Y80,N('Debt Payoff'!E16)) -> 0 | AH80: =R80-Z80 -> 0 | AI80: =S80-AA80 -> 0 | AJ80: =T80-AB80 -> 0 | AK80: =U80-AC80 -> 0 | AL80: =V80-AD80 -> 0 | AM80: =W80-AE80 -> 0 | AN80: =X80-AF80 -> 0 | AO80: =Y80-AG80 -> 0 | AP80: =MAX(0,'Debt Payoff'!$D$17-SUM(Z80:AG80)) -> 805 | AQ80: =MIN(AH80,MAX(0,$AP80-SUMPRODUCT(($AH$1:$AO$1<AH$1)*$AH80:$AO80))) -> 0 | AR80: =MIN(AI80,MAX(0,$AP80-SUMPRODUCT(($AH$1:$AO$1<AI$1)*$AH80:$AO80))) -> 0 | AS80: =MIN(AJ80,MAX(0,$AP80-SUMPRODUCT(($AH$1:$AO$1<AJ$1)*$AH80:$AO80))) -> 0 | AT80: =MIN(AK80,MAX(0,$AP80-SUMPRODUCT(($AH$1:$AO$1<AK$1)*$AH80:$AO80))) -> 0 | AU80: =MIN(AL80,MAX(0,$AP80-SUMPRODUCT(($AH$1:$AO$1<AL$1)*$AH80:$AO80))) -> 0 | AV80: =MIN(AM80,MAX(0,$AP80-SUMPRODUCT(($AH$1:$AO$1<AM$1)*$AH80:$AO80))) -> 0 | AW80: =MIN(AN80,MAX(0,$AP80-SUMPRODUCT(($AH$1:$AO$1<AN$1)*$AH80:$AO80))) -> 0 | AX80: =MIN(AO80,MAX(0,$AP80-SUMPRODUCT(($AH$1:$AO$1<AO$1)*$AH80:$AO80))) -> 0 | AY80: =ROUND(AH80-AQ80,2) -> 0 | AZ80: =ROUND(AI80-AR80,2) -> 0 | BA80: =ROUND(AJ80-AS80,2) -> 0 | BB80: =ROUND(AK80-AT80,2) -> 0 | BC80: =ROUND(AL80-AU80,2) -> 0 | BD80: =ROUND(AM80-AV80,2) -> 0 | BE80: =ROUND(AN80-AW80,2) -> 0 | BF80: =ROUND(AO80-AX80,2) -> 0 | BG80: =SUM(AY80:BF80) -> 0
A81: 79 | B81: =AY80 -> 0 | C81: =AZ80 -> 0 | D81: =BA80 -> 0 | E81: =BB80 -> 0 | F81: =BC80 -> 0 | G81: =BD80 -> 0 | H81: =BE80 -> 0 | I81: =BF80 -> 0 | J81: =B81*N('Debt Payoff'!D9)/12 -> 0 | K81: =C81*N('Debt Payoff'!D10)/12 -> 0 | L81: =D81*N('Debt Payoff'!D11)/12 -> 0 | M81: =E81*N('Debt Payoff'!D12)/12 -> 0 | N81: =F81*N('Debt Payoff'!D13)/12 -> 0 | O81: =G81*N('Debt Payoff'!D14)/12 -> 0 | P81: =H81*N('Debt Payoff'!D15)/12 -> 0 | Q81: =I81*N('Debt Payoff'!D16)/12 -> 0 | R81: =B81+J81 -> 0 | S81: =C81+K81 -> 0 | T81: =D81+L81 -> 0 | U81: =E81+M81 -> 0 | V81: =F81+N81 -> 0 | W81: =G81+O81 -> 0 | X81: =H81+P81 -> 0 | Y81: =I81+Q81 -> 0 | Z81: =MIN(R81,N('Debt Payoff'!E9)) -> 0 | AA81: =MIN(S81,N('Debt Payoff'!E10)) -> 0 | AB81: =MIN(T81,N('Debt Payoff'!E11)) -> 0 | AC81: =MIN(U81,N('Debt Payoff'!E12)) -> 0 | AD81: =MIN(V81,N('Debt Payoff'!E13)) -> 0 | AE81: =MIN(W81,N('Debt Payoff'!E14)) -> 0 | AF81: =MIN(X81,N('Debt Payoff'!E15)) -> 0 | AG81: =MIN(Y81,N('Debt Payoff'!E16)) -> 0 | AH81: =R81-Z81 -> 0 | AI81: =S81-AA81 -> 0 | AJ81: =T81-AB81 -> 0 | AK81: =U81-AC81 -> 0 | AL81: =V81-AD81 -> 0 | AM81: =W81-AE81 -> 0 | AN81: =X81-AF81 -> 0 | AO81: =Y81-AG81 -> 0 | AP81: =MAX(0,'Debt Payoff'!$D$17-SUM(Z81:AG81)) -> 805 | AQ81: =MIN(AH81,MAX(0,$AP81-SUMPRODUCT(($AH$1:$AO$1<AH$1)*$AH81:$AO81))) -> 0 | AR81: =MIN(AI81,MAX(0,$AP81-SUMPRODUCT(($AH$1:$AO$1<AI$1)*$AH81:$AO81))) -> 0 | AS81: =MIN(AJ81,MAX(0,$AP81-SUMPRODUCT(($AH$1:$AO$1<AJ$1)*$AH81:$AO81))) -> 0 | AT81: =MIN(AK81,MAX(0,$AP81-SUMPRODUCT(($AH$1:$AO$1<AK$1)*$AH81:$AO81))) -> 0 | AU81: =MIN(AL81,MAX(0,$AP81-SUMPRODUCT(($AH$1:$AO$1<AL$1)*$AH81:$AO81))) -> 0 | AV81: =MIN(AM81,MAX(0,$AP81-SUMPRODUCT(($AH$1:$AO$1<AM$1)*$AH81:$AO81))) -> 0 | AW81: =MIN(AN81,MAX(0,$AP81-SUMPRODUCT(($AH$1:$AO$1<AN$1)*$AH81:$AO81))) -> 0 | AX81: =MIN(AO81,MAX(0,$AP81-SUMPRODUCT(($AH$1:$AO$1<AO$1)*$AH81:$AO81))) -> 0 | AY81: =ROUND(AH81-AQ81,2) -> 0 | AZ81: =ROUND(AI81-AR81,2) -> 0 | BA81: =ROUND(AJ81-AS81,2) -> 0 | BB81: =ROUND(AK81-AT81,2) -> 0 | BC81: =ROUND(AL81-AU81,2) -> 0 | BD81: =ROUND(AM81-AV81,2) -> 0 | BE81: =ROUND(AN81-AW81,2) -> 0 | BF81: =ROUND(AO81-AX81,2) -> 0 | BG81: =SUM(AY81:BF81) -> 0
A82: 80 | B82: =AY81 -> 0 | C82: =AZ81 -> 0 | D82: =BA81 -> 0 | E82: =BB81 -> 0 | F82: =BC81 -> 0 | G82: =BD81 -> 0 | H82: =BE81 -> 0 | I82: =BF81 -> 0 | J82: =B82*N('Debt Payoff'!D9)/12 -> 0 | K82: =C82*N('Debt Payoff'!D10)/12 -> 0 | L82: =D82*N('Debt Payoff'!D11)/12 -> 0 | M82: =E82*N('Debt Payoff'!D12)/12 -> 0 | N82: =F82*N('Debt Payoff'!D13)/12 -> 0 | O82: =G82*N('Debt Payoff'!D14)/12 -> 0 | P82: =H82*N('Debt Payoff'!D15)/12 -> 0 | Q82: =I82*N('Debt Payoff'!D16)/12 -> 0 | R82: =B82+J82 -> 0 | S82: =C82+K82 -> 0 | T82: =D82+L82 -> 0 | U82: =E82+M82 -> 0 | V82: =F82+N82 -> 0 | W82: =G82+O82 -> 0 | X82: =H82+P82 -> 0 | Y82: =I82+Q82 -> 0 | Z82: =MIN(R82,N('Debt Payoff'!E9)) -> 0 | AA82: =MIN(S82,N('Debt Payoff'!E10)) -> 0 | AB82: =MIN(T82,N('Debt Payoff'!E11)) -> 0 | AC82: =MIN(U82,N('Debt Payoff'!E12)) -> 0 | AD82: =MIN(V82,N('Debt Payoff'!E13)) -> 0 | AE82: =MIN(W82,N('Debt Payoff'!E14)) -> 0 | AF82: =MIN(X82,N('Debt Payoff'!E15)) -> 0 | AG82: =MIN(Y82,N('Debt Payoff'!E16)) -> 0 | AH82: =R82-Z82 -> 0 | AI82: =S82-AA82 -> 0 | AJ82: =T82-AB82 -> 0 | AK82: =U82-AC82 -> 0 | AL82: =V82-AD82 -> 0 | AM82: =W82-AE82 -> 0 | AN82: =X82-AF82 -> 0 | AO82: =Y82-AG82 -> 0 | AP82: =MAX(0,'Debt Payoff'!$D$17-SUM(Z82:AG82)) -> 805 | AQ82: =MIN(AH82,MAX(0,$AP82-SUMPRODUCT(($AH$1:$AO$1<AH$1)*$AH82:$AO82))) -> 0 | AR82: =MIN(AI82,MAX(0,$AP82-SUMPRODUCT(($AH$1:$AO$1<AI$1)*$AH82:$AO82))) -> 0 | AS82: =MIN(AJ82,MAX(0,$AP82-SUMPRODUCT(($AH$1:$AO$1<AJ$1)*$AH82:$AO82))) -> 0 | AT82: =MIN(AK82,MAX(0,$AP82-SUMPRODUCT(($AH$1:$AO$1<AK$1)*$AH82:$AO82))) -> 0 | AU82: =MIN(AL82,MAX(0,$AP82-SUMPRODUCT(($AH$1:$AO$1<AL$1)*$AH82:$AO82))) -> 0 | AV82: =MIN(AM82,MAX(0,$AP82-SUMPRODUCT(($AH$1:$AO$1<AM$1)*$AH82:$AO82))) -> 0 | AW82: =MIN(AN82,MAX(0,$AP82-SUMPRODUCT(($AH$1:$AO$1<AN$1)*$AH82:$AO82))) -> 0 | AX82: =MIN(AO82,MAX(0,$AP82-SUMPRODUCT(($AH$1:$AO$1<AO$1)*$AH82:$AO82))) -> 0 | AY82: =ROUND(AH82-AQ82,2) -> 0 | AZ82: =ROUND(AI82-AR82,2) -> 0 | BA82: =ROUND(AJ82-AS82,2) -> 0 | BB82: =ROUND(AK82-AT82,2) -> 0 | BC82: =ROUND(AL82-AU82,2) -> 0 | BD82: =ROUND(AM82-AV82,2) -> 0 | BE82: =ROUND(AN82-AW82,2) -> 0 | BF82: =ROUND(AO82-AX82,2) -> 0 | BG82: =SUM(AY82:BF82) -> 0
A83: 81 | B83: =AY82 -> 0 | C83: =AZ82 -> 0 | D83: =BA82 -> 0 | E83: =BB82 -> 0 | F83: =BC82 -> 0 | G83: =BD82 -> 0 | H83: =BE82 -> 0 | I83: =BF82 -> 0 | J83: =B83*N('Debt Payoff'!D9)/12 -> 0 | K83: =C83*N('Debt Payoff'!D10)/12 -> 0 | L83: =D83*N('Debt Payoff'!D11)/12 -> 0 | M83: =E83*N('Debt Payoff'!D12)/12 -> 0 | N83: =F83*N('Debt Payoff'!D13)/12 -> 0 | O83: =G83*N('Debt Payoff'!D14)/12 -> 0 | P83: =H83*N('Debt Payoff'!D15)/12 -> 0 | Q83: =I83*N('Debt Payoff'!D16)/12 -> 0 | R83: =B83+J83 -> 0 | S83: =C83+K83 -> 0 | T83: =D83+L83 -> 0 | U83: =E83+M83 -> 0 | V83: =F83+N83 -> 0 | W83: =G83+O83 -> 0 | X83: =H83+P83 -> 0 | Y83: =I83+Q83 -> 0 | Z83: =MIN(R83,N('Debt Payoff'!E9)) -> 0 | AA83: =MIN(S83,N('Debt Payoff'!E10)) -> 0 | AB83: =MIN(T83,N('Debt Payoff'!E11)) -> 0 | AC83: =MIN(U83,N('Debt Payoff'!E12)) -> 0 | AD83: =MIN(V83,N('Debt Payoff'!E13)) -> 0 | AE83: =MIN(W83,N('Debt Payoff'!E14)) -> 0 | AF83: =MIN(X83,N('Debt Payoff'!E15)) -> 0 | AG83: =MIN(Y83,N('Debt Payoff'!E16)) -> 0 | AH83: =R83-Z83 -> 0 | AI83: =S83-AA83 -> 0 | AJ83: =T83-AB83 -> 0 | AK83: =U83-AC83 -> 0 | AL83: =V83-AD83 -> 0 | AM83: =W83-AE83 -> 0 | AN83: =X83-AF83 -> 0 | AO83: =Y83-AG83 -> 0 | AP83: =MAX(0,'Debt Payoff'!$D$17-SUM(Z83:AG83)) -> 805 | AQ83: =MIN(AH83,MAX(0,$AP83-SUMPRODUCT(($AH$1:$AO$1<AH$1)*$AH83:$AO83))) -> 0 | AR83: =MIN(AI83,MAX(0,$AP83-SUMPRODUCT(($AH$1:$AO$1<AI$1)*$AH83:$AO83))) -> 0 | AS83: =MIN(AJ83,MAX(0,$AP83-SUMPRODUCT(($AH$1:$AO$1<AJ$1)*$AH83:$AO83))) -> 0 | AT83: =MIN(AK83,MAX(0,$AP83-SUMPRODUCT(($AH$1:$AO$1<AK$1)*$AH83:$AO83))) -> 0 | AU83: =MIN(AL83,MAX(0,$AP83-SUMPRODUCT(($AH$1:$AO$1<AL$1)*$AH83:$AO83))) -> 0 | AV83: =MIN(AM83,MAX(0,$AP83-SUMPRODUCT(($AH$1:$AO$1<AM$1)*$AH83:$AO83))) -> 0 | AW83: =MIN(AN83,MAX(0,$AP83-SUMPRODUCT(($AH$1:$AO$1<AN$1)*$AH83:$AO83))) -> 0 | AX83: =MIN(AO83,MAX(0,$AP83-SUMPRODUCT(($AH$1:$AO$1<AO$1)*$AH83:$AO83))) -> 0 | AY83: =ROUND(AH83-AQ83,2) -> 0 | AZ83: =ROUND(AI83-AR83,2) -> 0 | BA83: =ROUND(AJ83-AS83,2) -> 0 | BB83: =ROUND(AK83-AT83,2) -> 0 | BC83: =ROUND(AL83-AU83,2) -> 0 | BD83: =ROUND(AM83-AV83,2) -> 0 | BE83: =ROUND(AN83-AW83,2) -> 0 | BF83: =ROUND(AO83-AX83,2) -> 0 | BG83: =SUM(AY83:BF83) -> 0
A84: 82 | B84: =AY83 -> 0 | C84: =AZ83 -> 0 | D84: =BA83 -> 0 | E84: =BB83 -> 0 | F84: =BC83 -> 0 | G84: =BD83 -> 0 | H84: =BE83 -> 0 | I84: =BF83 -> 0 | J84: =B84*N('Debt Payoff'!D9)/12 -> 0 | K84: =C84*N('Debt Payoff'!D10)/12 -> 0 | L84: =D84*N('Debt Payoff'!D11)/12 -> 0 | M84: =E84*N('Debt Payoff'!D12)/12 -> 0 | N84: =F84*N('Debt Payoff'!D13)/12 -> 0 | O84: =G84*N('Debt Payoff'!D14)/12 -> 0 | P84: =H84*N('Debt Payoff'!D15)/12 -> 0 | Q84: =I84*N('Debt Payoff'!D16)/12 -> 0 | R84: =B84+J84 -> 0 | S84: =C84+K84 -> 0 | T84: =D84+L84 -> 0 | U84: =E84+M84 -> 0 | V84: =F84+N84 -> 0 | W84: =G84+O84 -> 0 | X84: =H84+P84 -> 0 | Y84: =I84+Q84 -> 0 | Z84: =MIN(R84,N('Debt Payoff'!E9)) -> 0 | AA84: =MIN(S84,N('Debt Payoff'!E10)) -> 0 | AB84: =MIN(T84,N('Debt Payoff'!E11)) -> 0 | AC84: =MIN(U84,N('Debt Payoff'!E12)) -> 0 | AD84: =MIN(V84,N('Debt Payoff'!E13)) -> 0 | AE84: =MIN(W84,N('Debt Payoff'!E14)) -> 0 | AF84: =MIN(X84,N('Debt Payoff'!E15)) -> 0 | AG84: =MIN(Y84,N('Debt Payoff'!E16)) -> 0 | AH84: =R84-Z84 -> 0 | AI84: =S84-AA84 -> 0 | AJ84: =T84-AB84 -> 0 | AK84: =U84-AC84 -> 0 | AL84: =V84-AD84 -> 0 | AM84: =W84-AE84 -> 0 | AN84: =X84-AF84 -> 0 | AO84: =Y84-AG84 -> 0 | AP84: =MAX(0,'Debt Payoff'!$D$17-SUM(Z84:AG84)) -> 805 | AQ84: =MIN(AH84,MAX(0,$AP84-SUMPRODUCT(($AH$1:$AO$1<AH$1)*$AH84:$AO84))) -> 0 | AR84: =MIN(AI84,MAX(0,$AP84-SUMPRODUCT(($AH$1:$AO$1<AI$1)*$AH84:$AO84))) -> 0 | AS84: =MIN(AJ84,MAX(0,$AP84-SUMPRODUCT(($AH$1:$AO$1<AJ$1)*$AH84:$AO84))) -> 0 | AT84: =MIN(AK84,MAX(0,$AP84-SUMPRODUCT(($AH$1:$AO$1<AK$1)*$AH84:$AO84))) -> 0 | AU84: =MIN(AL84,MAX(0,$AP84-SUMPRODUCT(($AH$1:$AO$1<AL$1)*$AH84:$AO84))) -> 0 | AV84: =MIN(AM84,MAX(0,$AP84-SUMPRODUCT(($AH$1:$AO$1<AM$1)*$AH84:$AO84))) -> 0 | AW84: =MIN(AN84,MAX(0,$AP84-SUMPRODUCT(($AH$1:$AO$1<AN$1)*$AH84:$AO84))) -> 0 | AX84: =MIN(AO84,MAX(0,$AP84-SUMPRODUCT(($AH$1:$AO$1<AO$1)*$AH84:$AO84))) -> 0 | AY84: =ROUND(AH84-AQ84,2) -> 0 | AZ84: =ROUND(AI84-AR84,2) -> 0 | BA84: =ROUND(AJ84-AS84,2) -> 0 | BB84: =ROUND(AK84-AT84,2) -> 0 | BC84: =ROUND(AL84-AU84,2) -> 0 | BD84: =ROUND(AM84-AV84,2) -> 0 | BE84: =ROUND(AN84-AW84,2) -> 0 | BF84: =ROUND(AO84-AX84,2) -> 0 | BG84: =SUM(AY84:BF84) -> 0
A85: 83 | B85: =AY84 -> 0 | C85: =AZ84 -> 0 | D85: =BA84 -> 0 | E85: =BB84 -> 0 | F85: =BC84 -> 0 | G85: =BD84 -> 0 | H85: =BE84 -> 0 | I85: =BF84 -> 0 | J85: =B85*N('Debt Payoff'!D9)/12 -> 0 | K85: =C85*N('Debt Payoff'!D10)/12 -> 0 | L85: =D85*N('Debt Payoff'!D11)/12 -> 0 | M85: =E85*N('Debt Payoff'!D12)/12 -> 0 | N85: =F85*N('Debt Payoff'!D13)/12 -> 0 | O85: =G85*N('Debt Payoff'!D14)/12 -> 0 | P85: =H85*N('Debt Payoff'!D15)/12 -> 0 | Q85: =I85*N('Debt Payoff'!D16)/12 -> 0 | R85: =B85+J85 -> 0 | S85: =C85+K85 -> 0 | T85: =D85+L85 -> 0 | U85: =E85+M85 -> 0 | V85: =F85+N85 -> 0 | W85: =G85+O85 -> 0 | X85: =H85+P85 -> 0 | Y85: =I85+Q85 -> 0 | Z85: =MIN(R85,N('Debt Payoff'!E9)) -> 0 | AA85: =MIN(S85,N('Debt Payoff'!E10)) -> 0 | AB85: =MIN(T85,N('Debt Payoff'!E11)) -> 0 | AC85: =MIN(U85,N('Debt Payoff'!E12)) -> 0 | AD85: =MIN(V85,N('Debt Payoff'!E13)) -> 0 | AE85: =MIN(W85,N('Debt Payoff'!E14)) -> 0 | AF85: =MIN(X85,N('Debt Payoff'!E15)) -> 0 | AG85: =MIN(Y85,N('Debt Payoff'!E16)) -> 0 | AH85: =R85-Z85 -> 0 | AI85: =S85-AA85 -> 0 | AJ85: =T85-AB85 -> 0 | AK85: =U85-AC85 -> 0 | AL85: =V85-AD85 -> 0 | AM85: =W85-AE85 -> 0 | AN85: =X85-AF85 -> 0 | AO85: =Y85-AG85 -> 0 | AP85: =MAX(0,'Debt Payoff'!$D$17-SUM(Z85:AG85)) -> 805 | AQ85: =MIN(AH85,MAX(0,$AP85-SUMPRODUCT(($AH$1:$AO$1<AH$1)*$AH85:$AO85))) -> 0 | AR85: =MIN(AI85,MAX(0,$AP85-SUMPRODUCT(($AH$1:$AO$1<AI$1)*$AH85:$AO85))) -> 0 | AS85: =MIN(AJ85,MAX(0,$AP85-SUMPRODUCT(($AH$1:$AO$1<AJ$1)*$AH85:$AO85))) -> 0 | AT85: =MIN(AK85,MAX(0,$AP85-SUMPRODUCT(($AH$1:$AO$1<AK$1)*$AH85:$AO85))) -> 0 | AU85: =MIN(AL85,MAX(0,$AP85-SUMPRODUCT(($AH$1:$AO$1<AL$1)*$AH85:$AO85))) -> 0 | AV85: =MIN(AM85,MAX(0,$AP85-SUMPRODUCT(($AH$1:$AO$1<AM$1)*$AH85:$AO85))) -> 0 | AW85: =MIN(AN85,MAX(0,$AP85-SUMPRODUCT(($AH$1:$AO$1<AN$1)*$AH85:$AO85))) -> 0 | AX85: =MIN(AO85,MAX(0,$AP85-SUMPRODUCT(($AH$1:$AO$1<AO$1)*$AH85:$AO85))) -> 0 | AY85: =ROUND(AH85-AQ85,2) -> 0 | AZ85: =ROUND(AI85-AR85,2) -> 0 | BA85: =ROUND(AJ85-AS85,2) -> 0 | BB85: =ROUND(AK85-AT85,2) -> 0 | BC85: =ROUND(AL85-AU85,2) -> 0 | BD85: =ROUND(AM85-AV85,2) -> 0 | BE85: =ROUND(AN85-AW85,2) -> 0 | BF85: =ROUND(AO85-AX85,2) -> 0 | BG85: =SUM(AY85:BF85) -> 0
A86: 84 | B86: =AY85 -> 0 | C86: =AZ85 -> 0 | D86: =BA85 -> 0 | E86: =BB85 -> 0 | F86: =BC85 -> 0 | G86: =BD85 -> 0 | H86: =BE85 -> 0 | I86: =BF85 -> 0 | J86: =B86*N('Debt Payoff'!D9)/12 -> 0 | K86: =C86*N('Debt Payoff'!D10)/12 -> 0 | L86: =D86*N('Debt Payoff'!D11)/12 -> 0 | M86: =E86*N('Debt Payoff'!D12)/12 -> 0 | N86: =F86*N('Debt Payoff'!D13)/12 -> 0 | O86: =G86*N('Debt Payoff'!D14)/12 -> 0 | P86: =H86*N('Debt Payoff'!D15)/12 -> 0 | Q86: =I86*N('Debt Payoff'!D16)/12 -> 0 | R86: =B86+J86 -> 0 | S86: =C86+K86 -> 0 | T86: =D86+L86 -> 0 | U86: =E86+M86 -> 0 | V86: =F86+N86 -> 0 | W86: =G86+O86 -> 0 | X86: =H86+P86 -> 0 | Y86: =I86+Q86 -> 0 | Z86: =MIN(R86,N('Debt Payoff'!E9)) -> 0 | AA86: =MIN(S86,N('Debt Payoff'!E10)) -> 0 | AB86: =MIN(T86,N('Debt Payoff'!E11)) -> 0 | AC86: =MIN(U86,N('Debt Payoff'!E12)) -> 0 | AD86: =MIN(V86,N('Debt Payoff'!E13)) -> 0 | AE86: =MIN(W86,N('Debt Payoff'!E14)) -> 0 | AF86: =MIN(X86,N('Debt Payoff'!E15)) -> 0 | AG86: =MIN(Y86,N('Debt Payoff'!E16)) -> 0 | AH86: =R86-Z86 -> 0 | AI86: =S86-AA86 -> 0 | AJ86: =T86-AB86 -> 0 | AK86: =U86-AC86 -> 0 | AL86: =V86-AD86 -> 0 | AM86: =W86-AE86 -> 0 | AN86: =X86-AF86 -> 0 | AO86: =Y86-AG86 -> 0 | AP86: =MAX(0,'Debt Payoff'!$D$17-SUM(Z86:AG86)) -> 805 | AQ86: =MIN(AH86,MAX(0,$AP86-SUMPRODUCT(($AH$1:$AO$1<AH$1)*$AH86:$AO86))) -> 0 | AR86: =MIN(AI86,MAX(0,$AP86-SUMPRODUCT(($AH$1:$AO$1<AI$1)*$AH86:$AO86))) -> 0 | AS86: =MIN(AJ86,MAX(0,$AP86-SUMPRODUCT(($AH$1:$AO$1<AJ$1)*$AH86:$AO86))) -> 0 | AT86: =MIN(AK86,MAX(0,$AP86-SUMPRODUCT(($AH$1:$AO$1<AK$1)*$AH86:$AO86))) -> 0 | AU86: =MIN(AL86,MAX(0,$AP86-SUMPRODUCT(($AH$1:$AO$1<AL$1)*$AH86:$AO86))) -> 0 | AV86: =MIN(AM86,MAX(0,$AP86-SUMPRODUCT(($AH$1:$AO$1<AM$1)*$AH86:$AO86))) -> 0 | AW86: =MIN(AN86,MAX(0,$AP86-SUMPRODUCT(($AH$1:$AO$1<AN$1)*$AH86:$AO86))) -> 0 | AX86: =MIN(AO86,MAX(0,$AP86-SUMPRODUCT(($AH$1:$AO$1<AO$1)*$AH86:$AO86))) -> 0 | AY86: =ROUND(AH86-AQ86,2) -> 0 | AZ86: =ROUND(AI86-AR86,2) -> 0 | BA86: =ROUND(AJ86-AS86,2) -> 0 | BB86: =ROUND(AK86-AT86,2) -> 0 | BC86: =ROUND(AL86-AU86,2) -> 0 | BD86: =ROUND(AM86-AV86,2) -> 0 | BE86: =ROUND(AN86-AW86,2) -> 0 | BF86: =ROUND(AO86-AX86,2) -> 0 | BG86: =SUM(AY86:BF86) -> 0
A87: 85 | B87: =AY86 -> 0 | C87: =AZ86 -> 0 | D87: =BA86 -> 0 | E87: =BB86 -> 0 | F87: =BC86 -> 0 | G87: =BD86 -> 0 | H87: =BE86 -> 0 | I87: =BF86 -> 0 | J87: =B87*N('Debt Payoff'!D9)/12 -> 0 | K87: =C87*N('Debt Payoff'!D10)/12 -> 0 | L87: =D87*N('Debt Payoff'!D11)/12 -> 0 | M87: =E87*N('Debt Payoff'!D12)/12 -> 0 | N87: =F87*N('Debt Payoff'!D13)/12 -> 0 | O87: =G87*N('Debt Payoff'!D14)/12 -> 0 | P87: =H87*N('Debt Payoff'!D15)/12 -> 0 | Q87: =I87*N('Debt Payoff'!D16)/12 -> 0 | R87: =B87+J87 -> 0 | S87: =C87+K87 -> 0 | T87: =D87+L87 -> 0 | U87: =E87+M87 -> 0 | V87: =F87+N87 -> 0 | W87: =G87+O87 -> 0 | X87: =H87+P87 -> 0 | Y87: =I87+Q87 -> 0 | Z87: =MIN(R87,N('Debt Payoff'!E9)) -> 0 | AA87: =MIN(S87,N('Debt Payoff'!E10)) -> 0 | AB87: =MIN(T87,N('Debt Payoff'!E11)) -> 0 | AC87: =MIN(U87,N('Debt Payoff'!E12)) -> 0 | AD87: =MIN(V87,N('Debt Payoff'!E13)) -> 0 | AE87: =MIN(W87,N('Debt Payoff'!E14)) -> 0 | AF87: =MIN(X87,N('Debt Payoff'!E15)) -> 0 | AG87: =MIN(Y87,N('Debt Payoff'!E16)) -> 0 | AH87: =R87-Z87 -> 0 | AI87: =S87-AA87 -> 0 | AJ87: =T87-AB87 -> 0 | AK87: =U87-AC87 -> 0 | AL87: =V87-AD87 -> 0 | AM87: =W87-AE87 -> 0 | AN87: =X87-AF87 -> 0 | AO87: =Y87-AG87 -> 0 | AP87: =MAX(0,'Debt Payoff'!$D$17-SUM(Z87:AG87)) -> 805 | AQ87: =MIN(AH87,MAX(0,$AP87-SUMPRODUCT(($AH$1:$AO$1<AH$1)*$AH87:$AO87))) -> 0 | AR87: =MIN(AI87,MAX(0,$AP87-SUMPRODUCT(($AH$1:$AO$1<AI$1)*$AH87:$AO87))) -> 0 | AS87: =MIN(AJ87,MAX(0,$AP87-SUMPRODUCT(($AH$1:$AO$1<AJ$1)*$AH87:$AO87))) -> 0 | AT87: =MIN(AK87,MAX(0,$AP87-SUMPRODUCT(($AH$1:$AO$1<AK$1)*$AH87:$AO87))) -> 0 | AU87: =MIN(AL87,MAX(0,$AP87-SUMPRODUCT(($AH$1:$AO$1<AL$1)*$AH87:$AO87))) -> 0 | AV87: =MIN(AM87,MAX(0,$AP87-SUMPRODUCT(($AH$1:$AO$1<AM$1)*$AH87:$AO87))) -> 0 | AW87: =MIN(AN87,MAX(0,$AP87-SUMPRODUCT(($AH$1:$AO$1<AN$1)*$AH87:$AO87))) -> 0 | AX87: =MIN(AO87,MAX(0,$AP87-SUMPRODUCT(($AH$1:$AO$1<AO$1)*$AH87:$AO87))) -> 0 | AY87: =ROUND(AH87-AQ87,2) -> 0 | AZ87: =ROUND(AI87-AR87,2) -> 0 | BA87: =ROUND(AJ87-AS87,2) -> 0 | BB87: =ROUND(AK87-AT87,2) -> 0 | BC87: =ROUND(AL87-AU87,2) -> 0 | BD87: =ROUND(AM87-AV87,2) -> 0 | BE87: =ROUND(AN87-AW87,2) -> 0 | BF87: =ROUND(AO87-AX87,2) -> 0 | BG87: =SUM(AY87:BF87) -> 0
A88: 86 | B88: =AY87 -> 0 | C88: =AZ87 -> 0 | D88: =BA87 -> 0 | E88: =BB87 -> 0 | F88: =BC87 -> 0 | G88: =BD87 -> 0 | H88: =BE87 -> 0 | I88: =BF87 -> 0 | J88: =B88*N('Debt Payoff'!D9)/12 -> 0 | K88: =C88*N('Debt Payoff'!D10)/12 -> 0 | L88: =D88*N('Debt Payoff'!D11)/12 -> 0 | M88: =E88*N('Debt Payoff'!D12)/12 -> 0 | N88: =F88*N('Debt Payoff'!D13)/12 -> 0 | O88: =G88*N('Debt Payoff'!D14)/12 -> 0 | P88: =H88*N('Debt Payoff'!D15)/12 -> 0 | Q88: =I88*N('Debt Payoff'!D16)/12 -> 0 | R88: =B88+J88 -> 0 | S88: =C88+K88 -> 0 | T88: =D88+L88 -> 0 | U88: =E88+M88 -> 0 | V88: =F88+N88 -> 0 | W88: =G88+O88 -> 0 | X88: =H88+P88 -> 0 | Y88: =I88+Q88 -> 0 | Z88: =MIN(R88,N('Debt Payoff'!E9)) -> 0 | AA88: =MIN(S88,N('Debt Payoff'!E10)) -> 0 | AB88: =MIN(T88,N('Debt Payoff'!E11)) -> 0 | AC88: =MIN(U88,N('Debt Payoff'!E12)) -> 0 | AD88: =MIN(V88,N('Debt Payoff'!E13)) -> 0 | AE88: =MIN(W88,N('Debt Payoff'!E14)) -> 0 | AF88: =MIN(X88,N('Debt Payoff'!E15)) -> 0 | AG88: =MIN(Y88,N('Debt Payoff'!E16)) -> 0 | AH88: =R88-Z88 -> 0 | AI88: =S88-AA88 -> 0 | AJ88: =T88-AB88 -> 0 | AK88: =U88-AC88 -> 0 | AL88: =V88-AD88 -> 0 | AM88: =W88-AE88 -> 0 | AN88: =X88-AF88 -> 0 | AO88: =Y88-AG88 -> 0 | AP88: =MAX(0,'Debt Payoff'!$D$17-SUM(Z88:AG88)) -> 805 | AQ88: =MIN(AH88,MAX(0,$AP88-SUMPRODUCT(($AH$1:$AO$1<AH$1)*$AH88:$AO88))) -> 0 | AR88: =MIN(AI88,MAX(0,$AP88-SUMPRODUCT(($AH$1:$AO$1<AI$1)*$AH88:$AO88))) -> 0 | AS88: =MIN(AJ88,MAX(0,$AP88-SUMPRODUCT(($AH$1:$AO$1<AJ$1)*$AH88:$AO88))) -> 0 | AT88: =MIN(AK88,MAX(0,$AP88-SUMPRODUCT(($AH$1:$AO$1<AK$1)*$AH88:$AO88))) -> 0 | AU88: =MIN(AL88,MAX(0,$AP88-SUMPRODUCT(($AH$1:$AO$1<AL$1)*$AH88:$AO88))) -> 0 | AV88: =MIN(AM88,MAX(0,$AP88-SUMPRODUCT(($AH$1:$AO$1<AM$1)*$AH88:$AO88))) -> 0 | AW88: =MIN(AN88,MAX(0,$AP88-SUMPRODUCT(($AH$1:$AO$1<AN$1)*$AH88:$AO88))) -> 0 | AX88: =MIN(AO88,MAX(0,$AP88-SUMPRODUCT(($AH$1:$AO$1<AO$1)*$AH88:$AO88))) -> 0 | AY88: =ROUND(AH88-AQ88,2) -> 0 | AZ88: =ROUND(AI88-AR88,2) -> 0 | BA88: =ROUND(AJ88-AS88,2) -> 0 | BB88: =ROUND(AK88-AT88,2) -> 0 | BC88: =ROUND(AL88-AU88,2) -> 0 | BD88: =ROUND(AM88-AV88,2) -> 0 | BE88: =ROUND(AN88-AW88,2) -> 0 | BF88: =ROUND(AO88-AX88,2) -> 0 | BG88: =SUM(AY88:BF88) -> 0
